Workbook

Sheet Fichier Anik et ajouts
A1: ID_JTL | B1: ID unique | C1: groupe_final | D1: pheno | E1: ech# Lipidomique | F1: ech Lipidomique | G1: ech AAAO | H1: age | I1: BMI | J1: sex | K1: NYHA | L1: Diabete | M1: gfr_CKDepi | N1: ST2 ng/mL | O1: Ct_FGF23_ELISARUmL | P1: NTproBNP | Q1: Tropo_T | R1: LA_Vol_simpsoni | S1: septalEeprim | T1: MeanVDOD | U1: LVEndoGLS | V1: LVMigm2 | W1: ECVpc | X1: dosageMyo1 | Y1: BPCO | Z1: SAS | AA1: Hb_gdL | AB1: loopdiuretics | AC1: CMI | AD1: FA_ATCD | AE1: EFsimpson | AF1: E_A | AG1: Mean_TAPSE | AH1: FUP 02/2019 résumé | AI1: DateBilan | AJ1: date FUP | AK1: Death | AL1: DateDeath_naturalhistory | AM1: TimeDeath_Nat_Hist_M | AN1: Hospit | AO1: DateHospit | AP1: TimeHospitM | AQ1: Combined | AR1: DateCombined | AS1: TimeCombinedM | AT1: Mean FUP months | AU1: MeanFUPdays | AV1: RVEndoGLSSib | AW1: Alanine | AX1: Arginine | AY1: Asparagine | AZ1: Aspartate | BA1: Cysteine | BB1: Glutamate | BC1: Glutamine | BD1: Glycine | BE1: Histidine | BF1: Hydroxyproline | BG1: Isoleucine | BH1: Leucine | BI1: Lysine | BJ1: Methionine | BK1: Phenylalanine | BL1: Proline | BM1: Serine | BN1: Threonine | BO1: Tryptophan | BP1: Tyrosine | BQ1: Valine | BR1: Acetoacetate | BS1: Alpha.hydroxy.butyrate | BT1: Alpha.keto.butyrate | BU1: Beta.hydroxy.butyrate | BV1: Citrate | BW1: Alpha.keto.glutarate | BX1: Lactate | BY1: Malate | BZ1: Pyruvate | CA1: Succinate | CB1: Lac_Pyr_ratio | CC1: BHB_AcAc_ratio | CD1: AHB_AKB_ratio
A2: 1 | B2: 1 | C2: 2 | D2: HFpEF | E2: 10429 | F2: YES | G2: YES | H2: 77 | I2: 27.34375 | J2: 1 | K2: 2 | L2: 0 | M2: 70 | N2: 44.46 | O2: 613.93854 | P2: 1519 | Q2: 11 | R2: 40.273951 | S2: 19.484848 | T2: 44 | U2: -19.67 | V2: 62.91479 | W2: 33.649027 | X2: 21.3037 | Y2: =VLOOKUP($A:$A,Variables_extraites!$A:$AD,7,FALSE) -> 0 | Z2: =VLOOKUP($A:$A,Variables_extraites!$A:$AD,8,FALSE) -> 1 | AA2: =VLOOKUP($A:$A,Variables_extraites!$A:$AD,9,FALSE) -> 12.2 | AB2: =VLOOKUP($A:$A,Variables_extraites!$A:$AD,10,FALSE) -> 1 | AC2: =VLOOKUP($A:$A,Variables_extraites!$A:$AD,11,FALSE) -> 0 | AD2: =VLOOKUP($A:$A,Variables_extraites!$A:$AD,12,FALSE) -> 1 | AE2: =VLOOKUP($A:$A,Variables_extraites!$A:$AD,13,FALSE) -> 62.124711 | AF2: =VLOOKUP($A:$A,Variables_extraites!$A:$AD,14,FALSE) -> NA | AG2: =VLOOKUP($A:$A,Variables_extraites!$A:$AD,15,FALSE) -> 14.333333 | AH2: =VLOOKUP($A:$A,Variables_extraites!$A:$AD,16,FALSE) -> 1 | AI2: =VLOOKUP($A:$A,Variables_extraites!$A:$AD,17,FALSE) -> 42065 | AJ2: =VLOOKUP($A:$A,Variables_extraites!$A:$AD,18,FALSE) -> 43514 | AK2: =VLOOKUP($A:$A,Variables_extraites!$A:$AD,19,FALSE) -> 0 | AL2: =VLOOKUP($A:$A,Variables_extraites!$A:$AD,20,FALSE) -> 43514 | AM2: =VLOOKUP($A:$A,Variables_extraites!$A:$AD,21,FALSE) -> 47 | AN2: =VLOOKUP($A:$A,Variables_extraites!$A:$AD,22,FALSE) -> 1 | AO2: =VLOOKUP($A:$A,Variables_extraites!$A:$AD,23,FALSE) -> 43166 | AP2: =VLOOKUP($A:$A,Variables_extraites!$A:$AD,24,FALSE) -> 36 | AQ2: =VLOOKUP($A:$A,Variables_extraites!$A:$AD,25,FALSE) -> 1 | AR2: =VLOOKUP($A:$A,Variables_extraites!$A:$AD,26,FALSE) -> 43166 | AS2: =VLOOKUP($A:$A,Variables_extraites!$A:$AD,27,FALSE) -> 36 | AT2: =VLOOKUP($A:$A,Variables_extraites!$A:$AD,28,FALSE) -> 47 | AU2: =VLOOKUP($A:$A,Variables_extraites!$A:$AD,29,FALSE) -> 1449 | AV2: =VLOOKUP($A:$A,Variables_extraites!$A:$AD,30,FALSE) -> NA | AW2: 8.1396025 | AX2: 7.2647241 | AY2: 5.0343038 | AZ2: 2.4541759 | BA2: 7.9648029 | BB2: 5.9692426 | BC2: 9.3438519 | BD2: 7.7308437 | BE2: 6.1045463 | BF2: 1.1375035 | BG2: 5.8389518 | BH2: 6.6516258 | BI2: 7.0936024 | BJ2: 4.4918531 | BK2: 5.9995491 | BL2: 7.7457751 | BM2: 6.2692202 | BN2: 6.8417216 | BO2: 5.78999 | BP2: 6.0338635 | BQ2: 7.8819093 | BR2: 3.7463128 | BS2: 10.419476 | BT2: 1.448901 | BU2: 5.549053 | BV2: 6.9525665 | BW2: 5.7931156 | BX2: 10.891974 | BY2: 3.6380738 | BZ2: 8.2183937 | CA2: 4.592756 | CB2: 2.6735798 | CC2: 1.8027403 | CD2: 8.9705747
A3: 2 | B3: 2 | C3: 2 | D3: HFpEF | E3: 10297 | F3: YES | H3: 75 | I3: 21.612812 | J3: 1 | K3: 4 | L3: 0 | M3: 84 | N3: 34.58 | O3: 173.36512 | P3: 1597 | Q3: 48 | R3: 60.892985 | S3: 16.4 | T3: 37 | U3: -16.9 | V3: 56.589862 | W3: 33.516899 | X3: 23.4603 | Y3: =VLOOKUP($A:$A,Variables_extraites!$A:$AD,7,FALSE) -> 0 | Z3: =VLOOKUP($A:$A,Variables_extraites!$A:$AD,8,FALSE) -> 0 | AA3: =VLOOKUP($A:$A,Variables_extraites!$A:$AD,9,FALSE) -> 9.8 | AB3: =VLOOKUP($A:$A,Variables_extraites!$A:$AD,10,FALSE) -> 1 | AC3: =VLOOKUP($A:$A,Variables_extraites!$A:$AD,11,FALSE) -> 0 | AD3: =VLOOKUP($A:$A,Variables_extraites!$A:$AD,12,FALSE) -> 1 | AE3: =VLOOKUP($A:$A,Variables_extraites!$A:$AD,13,FALSE) -> 54.750594 | AF3: =VLOOKUP($A:$A,Variables_extraites!$A:$AD,14,FALSE) -> 1 | AG3: =VLOOKUP($A:$A,Variables_extraites!$A:$AD,15,FALSE) -> 30 | AH3: =VLOOKUP($A:$A,Variables_extraites!$A:$AD,16,FALSE) -> 2 | AI3: =VLOOKUP($A:$A,Variables_extraites!$A:$AD,17,FALSE) -> 42317 | AJ3: =VLOOKUP($A:$A,Variables_extraites!$A:$AD,18,FALSE) -> 43272 | AK3: =VLOOKUP($A:$A,Variables_extraites!$A:$AD,19,FALSE) -> 0 | AL3: =VLOOKUP($A:$A,Variables_extraites!$A:$AD,20,FALSE) -> 43272 | AM3: =VLOOKUP($A:$A,Variables_extraites!$A:$AD,21,FALSE) -> 31 | AN3: =VLOOKUP($A:$A,Variables_extraites!$A:$AD,22,FALSE) -> 0 | AO3: =VLOOKUP($A:$A,Variables_extraites!$A:$AD,23,FALSE) -> 43272 | AP3: =VLOOKUP($A:$A,Variables_extraites!$A:$AD,24,FALSE) -> 31 | AQ3: =VLOOKUP($A:$A,Variables_extraites!$A:$AD,25,FALSE) -> 0 | AR3: =VLOOKUP($A:$A,Variables_extraites!$A:$AD,26,FALSE) -> 43272 | AS3: =VLOOKUP($A:$A,Variables_extraites!$A:$AD,27,FALSE) -> 31 | AT3: =VLOOKUP($A:$A,Variables_extraites!$A:$AD,28,FALSE) -> 31 | AU3: =VLOOKUP($A:$A,Variables_extraites!$A:$AD,29,FALSE) -> 955 | AV3: =VLOOKUP($A:$A,Variables_extraites!$A:$AD,30,FALSE) -> -22.89
A4: 5 | B4: 5 | C4: 2 | D4: HFpEF | E4: 10547 | F4: YES | G4: YES | H4: 67 | I4: 30.42185 | J4: 0 | K4: 0 | L4: 1 | M4: 79 | N4: 24.48 | O4: 49.122977 | P4: 483.8 | Q4: 14 | R4: 45.350504 | S4: 18.928571 | T4: 34 | U4: -20.12 | V4: 65.941287 | W4: 33.789973 | X4: 25.5106 | Y4: =VLOOKUP($A:$A,Variables_extraites!$A:$AD,7,FALSE) -> 0 | Z4: =VLOOKUP($A:$A,Variables_extraites!$A:$AD,8,FALSE) -> 0 | AA4: =VLOOKUP($A:$A,Variables_extraites!$A:$AD,9,FALSE) -> 11.1 | AB4: =VLOOKUP($A:$A,Variables_extraites!$A:$AD,10,FALSE) -> 0 | AC4: =VLOOKUP($A:$A,Variables_extraites!$A:$AD,11,FALSE) -> 1 | AD4: =VLOOKUP($A:$A,Variables_extraites!$A:$AD,12,FALSE) -> 1 | AE4: =VLOOKUP($A:$A,Variables_extraites!$A:$AD,13,FALSE) -> 65.268139 | AF4: =VLOOKUP($A:$A,Variables_extraites!$A:$AD,14,FALSE) -> 1.8275862 | AG4: =VLOOKUP($A:$A,Variables_extraites!$A:$AD,15,FALSE) -> 15 | AH4: =VLOOKUP($A:$A,Variables_extraites!$A:$AD,16,FALSE) -> 5 | AI4: =VLOOKUP($A:$A,Variables_extraites!$A:$AD,17,FALSE) -> 42262 | AJ4: =VLOOKUP($A:$A,Variables_extraites!$A:$AD,18,FALSE) -> 43048 | AK4: =VLOOKUP($A:$A,Variables_extraites!$A:$AD,19,FALSE) -> 0 | AL4: =VLOOKUP($A:$A,Variables_extraites!$A:$AD,20,FALSE) -> 43048 | AM4: =VLOOKUP($A:$A,Variables_extraites!$A:$AD,21,FALSE) -> 26 | AN4: =VLOOKUP($A:$A,Variables_extraites!$A:$AD,22,FALSE) -> 0 | AO4: =VLOOKUP($A:$A,Variables_extraites!$A:$AD,23,FALSE) -> 43048 | AP4: =VLOOKUP($A:$A,Variables_extraites!$A:$AD,24,FALSE) -> 26 | AQ4: =VLOOKUP($A:$A,Variables_extraites!$A:$AD,25,FALSE) -> 0 | AR4: =VLOOKUP($A:$A,Variables_extraites!$A:$AD,26,FALSE) -> 43048 | AS4: =VLOOKUP($A:$A,Variables_extraites!$A:$AD,27,FALSE) -> 26 | AT4: =VLOOKUP($A:$A,Variables_extraites!$A:$AD,28,FALSE) -> 25.8 | AU4: =VLOOKUP($A:$A,Variables_extraites!$A:$AD,29,FALSE) -> 786 | AV4: =VLOOKUP($A:$A,Variables_extraites!$A:$AD,30,FALSE) -> -20.5 | AW4: 9.0643116 | AX4: 7.5465858 | AY4: 5.4299507 | AZ4: 2.1731274 | BA4: 7.8492487 | BB4: 6.274448 | BC4: 9.3467353 | BD4: 8.0001691 | BE4: 5.895545 | BF4: 1.0840643 | BG4: 5.9970665 | BH4: 5.9136075 | BI4: 7.1428218 | BJ4: 4.3059705 | BK4: 5.6070343 | BL4: 7.9457364 | BM4: 6.6088092 | BN4: 6.4899282 | BO4: 5.2816983 | BP4: 5.4763817 | BQ4: 7.0214797 | BR4: 0.29865832 | BS4: 9.620843 | BT4: 1.3729521 | BU4: 5.6513388 | BV4: 7.21072 | BW4: 5.7106687 | BX4: 12.096 | BY4: 3.7322692 | BZ4: 9.548976 | CA4: 3.9532652 | CB4: 2.5470242 | CC4: 5.3526805 | CD4: 8.2478909
A5: 6 | B5: 6 | C5: 2 | D5: HFpEF | E5: 10552 | F5: YES | H5: 77 | I5: 25.925926 | J5: 0 | K5: 4 | L5: 0 | M5: 48 | N5: 57.88 | O5: 122.11922 | R5: 44.793314 | S5: 14.341463 | T5: 40 | U5: -18.81 | V5: 64.171086 | W5: 32.847686 | X5: 39.9844 | Y5: =VLOOKUP($A:$A,Variables_extraites!$A:$AD,7,FALSE) -> 1 | Z5: =VLOOKUP($A:$A,Variables_extraites!$A:$AD,8,FALSE) -> 0 | AA5: =VLOOKUP($A:$A,Variables_extraites!$A:$AD,9,FALSE) -> 16.7 | AB5: =VLOOKUP($A:$A,Variables_extraites!$A:$AD,10,FALSE) -> 0 | AC5: =VLOOKUP($A:$A,Variables_extraites!$A:$AD,11,FALSE) -> 0 | AD5: =VLOOKUP($A:$A,Variables_extraites!$A:$AD,12,FALSE) -> 1 | AE5: =VLOOKUP($A:$A,Variables_extraites!$A:$AD,13,FALSE) -> 67.320261 | AF5: =VLOOKUP($A:$A,Variables_extraites!$A:$AD,14,FALSE) -> NA | AG5: =VLOOKUP($A:$A,Variables_extraites!$A:$AD,15,FALSE) -> 15 | AH5: =VLOOKUP($A:$A,Variables_extraites!$A:$AD,16,FALSE) -> 6 | AI5: =VLOOKUP($A:$A,Variables_extraites!$A:$AD,17,FALSE) -> 42156 | AJ5: =VLOOKUP($A:$A,Variables_extraites!$A:$AD,18,FALSE) -> 43048 | AK5: =VLOOKUP($A:$A,Variables_extraites!$A:$AD,19,FALSE) -> 0 | AL5: =VLOOKUP($A:$A,Variables_extraites!$A:$AD,20,FALSE) -> 43048 | AM5: =VLOOKUP($A:$A,Variables_extraites!$A:$AD,21,FALSE) -> 29 | AN5: =VLOOKUP($A:$A,Variables_extraites!$A:$AD,22,FALSE) -> 1 | AO5: =VLOOKUP($A:$A,Variables_extraites!$A:$AD,23,FALSE) -> 42401 | AP5: =VLOOKUP($A:$A,Variables_extraites!$A:$AD,24,FALSE) -> 8 | AQ5: =VLOOKUP($A:$A,Variables_extraites!$A:$AD,25,FALSE) -> 1 | AR5: =VLOOKUP($A:$A,Variables_extraites!$A:$AD,26,FALSE) -> 42401 | AS5: =VLOOKUP($A:$A,Variables_extraites!$A:$AD,27,FALSE) -> 8 | AT5: =VLOOKUP($A:$A,Variables_extraites!$A:$AD,28,FALSE) -> 29.33 | AU5: =VLOOKUP($A:$A,Variables_extraites!$A:$AD,29,FALSE) -> 892 | AV5: =VLOOKUP($A:$A,Variables_extraites!$A:$AD,30,FALSE) -> -21.37
A6: 8 | B6: 8 | C6: 2 | D6: HFpEF | E6: 10477 | F6: YES | H6: 78 | I6: 34.722222 | J6: 0 | K6: 2 | L6: 1 | M6: 62 | N6: 55.55 | O6: 545.5079 | P6: 3605 | Q6: 17 | R6: 46.809838 | S6: 20.87619 | T6: 38.6 | U6: -14.33 | V6: 82.605597 | W6: 36.531472 | X6: 24.39 | Y6: =VLOOKUP($A:$A,Variables_extraites!$A:$AD,7,FALSE) -> 0 | Z6: =VLOOKUP($A:$A,Variables_extraites!$A:$AD,8,FALSE) -> 1 | AA6: =VLOOKUP($A:$A,Variables_extraites!$A:$AD,9,FALSE) -> 13.8 | AB6: =VLOOKUP($A:$A,Variables_extraites!$A:$AD,10,FALSE) -> 1 | AC6: =VLOOKUP($A:$A,Variables_extraites!$A:$AD,11,FALSE) -> 1 | AD6: =VLOOKUP($A:$A,Variables_extraites!$A:$AD,12,FALSE) -> 1 | AE6: =VLOOKUP($A:$A,Variables_extraites!$A:$AD,13,FALSE) -> 52.132289 | AF6: =VLOOKUP($A:$A,Variables_extraites!$A:$AD,14,FALSE) -> NA | AG6: =VLOOKUP($A:$A,Variables_extraites!$A:$AD,15,FALSE) -> 12.5 | AH6: =VLOOKUP($A:$A,Variables_extraites!$A:$AD,16,FALSE) -> 8 | AI6: =VLOOKUP($A:$A,Variables_extraites!$A:$AD,17,FALSE) -> 42129 | AJ6: =VLOOKUP($A:$A,Variables_extraites!$A:$AD,18,FALSE) -> 43040 | AK6: =VLOOKUP($A:$A,Variables_extraites!$A:$AD,19,FALSE) -> 1 | AL6: =VLOOKUP($A:$A,Variables_extraites!$A:$AD,20,FALSE) -> 43040 | AM6: =VLOOKUP($A:$A,Variables_extraites!$A:$AD,21,FALSE) -> 29 | AN6: =VLOOKUP($A:$A,Variables_extraites!$A:$AD,22,FALSE) -> 1 | AO6: =VLOOKUP($A:$A,Variables_extraites!$A:$AD,23,FALSE) -> 42152 | AP6: =VLOOKUP($A:$A,Variables_extraites!$A:$AD,24,FALSE) -> 1 | AQ6: =VLOOKUP($A:$A,Variables_extraites!$A:$AD,25,FALSE) -> 1 | AR6: =VLOOKUP($A:$A,Variables_extraites!$A:$AD,26,FALSE) -> 42152 | AS6: =VLOOKUP($A:$A,Variables_extraites!$A:$AD,27,FALSE) -> 1 | AT6: =VLOOKUP($A:$A,Variables_extraites!$A:$AD,28,FALSE) -> 29 | AU6: =VLOOKUP($A:$A,Variables_extraites!$A:$AD,29,FALSE) -> 911 | AV6: =VLOOKUP($A:$A,Variables_extraites!$A:$AD,30,FALSE) -> NA
A7: 9 | B7: 9 | C7: 2 | D7: HFpEF | E7: 10298 | F7: YES | G7: YES | H7: 84 | I7: 24.221453 | J7: 1 | K7: 3 | L7: 1 | M7: 20 | N7: 85.09 | O7: 1335.7059 | P7: 6563 | Q7: 77 | R7: 72.663664 | S7: 28.888889 | T7: 43 | U7: -17.17 | X7: 75.9158 | Y7: =VLOOKUP($A:$A,Variables_extraites!$A:$AD,7,FALSE) -> 0 | Z7: =VLOOKUP($A:$A,Variables_extraites!$A:$AD,8,FALSE) -> 0 | AA7: =VLOOKUP($A:$A,Variables_extraites!$A:$AD,9,FALSE) -> 9 | AB7: =VLOOKUP($A:$A,Variables_extraites!$A:$AD,10,FALSE) -> 1 | AC7: =VLOOKUP($A:$A,Variables_extraites!$A:$AD,11,FALSE) -> 1 | AD7: =VLOOKUP($A:$A,Variables_extraites!$A:$AD,12,FALSE) -> 0 | AE7: =VLOOKUP($A:$A,Variables_extraites!$A:$AD,13,FALSE) -> 60.399285 | AF7: =VLOOKUP($A:$A,Variables_extraites!$A:$AD,14,FALSE) -> 1.0586319 | AG7: =VLOOKUP($A:$A,Variables_extraites!$A:$AD,15,FALSE) -> 16 | AH7: =VLOOKUP($A:$A,Variables_extraites!$A:$AD,16,FALSE) -> 9 | AI7: =VLOOKUP($A:$A,Variables_extraites!$A:$AD,17,FALSE) -> 42345 | AJ7: =VLOOKUP($A:$A,Variables_extraites!$A:$AD,18,FALSE) -> 42622 | AK7: =VLOOKUP($A:$A,Variables_extraites!$A:$AD,19,FALSE) -> 1 | AL7: =VLOOKUP($A:$A,Variables_extraites!$A:$AD,20,FALSE) -> 42622 | AM7: =VLOOKUP($A:$A,Variables_extraites!$A:$AD,21,FALSE) -> 9 | AN7: =VLOOKUP($A:$A,Variables_extraites!$A:$AD,22,FALSE) -> 1 | AO7: =VLOOKUP($A:$A,Variables_extraites!$A:$AD,23,FALSE) -> 42397 | AP7: =VLOOKUP($A:$A,Variables_extraites!$A:$AD,24,FALSE) -> 2 | AQ7: =VLOOKUP($A:$A,Variables_extraites!$A:$AD,25,FALSE) -> 1 | AR7: =VLOOKUP($A:$A,Variables_extraites!$A:$AD,26,FALSE) -> 42397 | AS7: =VLOOKUP($A:$A,Variables_extraites!$A:$AD,27,FALSE) -> 2 | AT7: =VLOOKUP($A:$A,Variables_extraites!$A:$AD,28,FALSE) -> 9 | AU7: =VLOOKUP($A:$A,Variables_extraites!$A:$AD,29,FALSE) -> 277 | AV7: =VLOOKUP($A:$A,Variables_extraites!$A:$AD,30,FALSE) -> -20.25 | AW7: 7.6067383 | AX7: 7.397974 | AY7: 5.0461418 | AZ7: 3.1243281 | BA7: 8.5007622 | BB7: 7.1183182 | BC7: 9.1011353 | BD7: 7.9936178 | BE7: 6.3774708 | BF7: 1.1570437 | BG7: 5.6965503 | BH7: 6.3492591 | BI7: 7.5947725 | BJ7: 4.5310695 | BK7: 5.9579146 | BL7: 7.8323837 | BM7: 6.2641611 | BN7: 7.5291963 | BO7: 4.6322682 | BP7: 5.9300276 | BQ7: 7.4654031 | BR7: 0.33342373 | BS7: 10.692816 | BT7: 1.1309309 | BU7: 8.7794567 | BV7: 6.7059779 | BW7: 5.7438919 | BX7: 11.253038 | BY7: 3.5789387 | BZ7: 7.7380923 | CA7: 4.3096128 | CB7: 3.5149456 | CC7: 8.446033 | CD7: 9.5618851
A8: 10 | B8: 10 | C8: 2 | D8: HFpEF | E8: 10332 | F8: YES | G8: YES | H8: 81 | I8: 31.64557 | J8: 1 | K8: 3 | L8: 0 | M8: 48 | N8: 21.97 | O8: 150.29696 | P8: 1717 | Q8: 17 | S8: 17.610063 | T8: 36 | U8: -19.123333 | V8: 40.958825 | W8: 29.127333 | X8: 60.3901 | Y8: =VLOOKUP($A:$A,Variables_extraites!$A:$AD,7,FALSE) -> 0 | Z8: =VLOOKUP($A:$A,Variables_extraites!$A:$AD,8,FALSE) -> 0 | AA8: =VLOOKUP($A:$A,Variables_extraites!$A:$AD,9,FALSE) -> 11.3 | AB8: =VLOOKUP($A:$A,Variables_extraites!$A:$AD,10,FALSE) -> 1 | AC8: =VLOOKUP($A:$A,Variables_extraites!$A:$AD,11,FALSE) -> 0 | AD8: =VLOOKUP($A:$A,Variables_extraites!$A:$AD,12,FALSE) -> 1 | AE8: =VLOOKUP($A:$A,Variables_extraites!$A:$AD,13,FALSE) -> 66.397985 | AF8: =VLOOKUP($A:$A,Variables_extraites!$A:$AD,14,FALSE) -> NA | AG8: =VLOOKUP($A:$A,Variables_extraites!$A:$AD,15,FALSE) -> 23 | AH8: =VLOOKUP($A:$A,Variables_extraites!$A:$AD,16,FALSE) -> 10 | AI8: =VLOOKUP($A:$A,Variables_extraites!$A:$AD,17,FALSE) -> 42041 | AJ8: =VLOOKUP($A:$A,Variables_extraites!$A:$AD,18,FALSE) -> 43480 | AK8: =VLOOKUP($A:$A,Variables_extraites!$A:$AD,19,FALSE) -> 0 | AL8: =VLOOKUP($A:$A,Variables_extraites!$A:$AD,20,FALSE) -> 43480 | AM8: =VLOOKUP($A:$A,Variables_extraites!$A:$AD,21,FALSE) -> 47 | AN8: =VLOOKUP($A:$A,Variables_extraites!$A:$AD,22,FALSE) -> 1 | AO8: =VLOOKUP($A:$A,Variables_extraites!$A:$AD,23,FALSE) -> 42873 | AP8: =VLOOKUP($A:$A,Variables_extraites!$A:$AD,24,FALSE) -> 27 | AQ8: =VLOOKUP($A:$A,Variables_extraites!$A:$AD,25,FALSE) -> 1 | AR8: =VLOOKUP($A:$A,Variables_extraites!$A:$AD,26,FALSE) -> 42873 | AS8: =VLOOKUP($A:$A,Variables_extraites!$A:$AD,27,FALSE) -> 27 | AT8: =VLOOKUP($A:$A,Variables_extraites!$A:$AD,28,FALSE) -> 47 | AU8: =VLOOKUP($A:$A,Variables_extraites!$A:$AD,29,FALSE) -> 1439 | AV8: =VLOOKUP($A:$A,Variables_extraites!$A:$AD,30,FALSE) -> -25.97 | AW8: 8.7643408 | AX8: 8.0100525 | AY8: 5.1034976 | AZ8: 2.5360529 | BA8: 8.0101085 | BB8: 5.5625477 | BC8: 9.4409107 | BD8: 8.0997686 | BE8: 6.2479275 | BF8: 1.5410192 | BG8: 5.8945753 | BH8: 6.1963316 | BI8: 7.611615 | BJ8: 4.3154213 | BK8: 5.8797058 | BL8: 8.0465784 | BM8: 6.4955353 | BN8: 6.6697355 | BO8: 5.3034155 | BP8: 5.7202785 | BQ8: 7.2983834 | BR8: 2.8399596 | BS8: 9.7109442 | BT8: 1.6599246 | BU8: 6.1616862 | BV8: 7.0660892 | BW8: 5.5369854 | BX8: 10.160262 | BY8: 3.3434078 | BZ8: 7.8101217 | CA8: 4.4032677 | CB8: 2.3501405 | CC8: 3.3217266 | CD8: 8.0510196
A9: 12 | B9: 12 | C9: 2 | D9: HFpEF | E9: 10363 | F9: YES | G9: YES | H9: 83 | I9: 29.937595 | J9: 1 | K9: 2 | L9: 1 | M9: 94 | N9: 55.8 | O9: 204.47624 | R9: 47.411341 | S9: 23.243243 | T9: 58.5 | U9: -14.7 | V9: 55.576294 | W9: 31.531215 | X9: 38.5647 | Y9: =VLOOKUP($A:$A,Variables_extraites!$A:$AD,7,FALSE) -> 0 | Z9: =VLOOKUP($A:$A,Variables_extraites!$A:$AD,8,FALSE) -> 0 | AA9: =VLOOKUP($A:$A,Variables_extraites!$A:$AD,9,FALSE) -> 13.4 | AB9: =VLOOKUP($A:$A,Variables_extraites!$A:$AD,10,FALSE) -> 1 | AC9: =VLOOKUP($A:$A,Variables_extraites!$A:$AD,11,FALSE) -> 1 | AD9: =VLOOKUP($A:$A,Variables_extraites!$A:$AD,12,FALSE) -> 0 | AE9: =VLOOKUP($A:$A,Variables_extraites!$A:$AD,13,FALSE) -> 81.558935 | AF9: =VLOOKUP($A:$A,Variables_extraites!$A:$AD,14,FALSE) -> 2.047619 | AG9: =VLOOKUP($A:$A,Variables_extraites!$A:$AD,15,FALSE) -> 16 | AH9: =VLOOKUP($A:$A,Variables_extraites!$A:$AD,16,FALSE) -> 12 | AI9: =VLOOKUP($A:$A,Variables_extraites!$A:$AD,17,FALSE) -> 42254 | AJ9: =VLOOKUP($A:$A,Variables_extraites!$A:$AD,18,FALSE) -> 43119 | AK9: =VLOOKUP($A:$A,Variables_extraites!$A:$AD,19,FALSE) -> 0 | AL9: =VLOOKUP($A:$A,Variables_extraites!$A:$AD,20,FALSE) -> 43119 | AM9: =VLOOKUP($A:$A,Variables_extraites!$A:$AD,21,FALSE) -> 28 | AN9: =VLOOKUP($A:$A,Variables_extraites!$A:$AD,22,FALSE) -> 1 | AO9: =VLOOKUP($A:$A,Variables_extraites!$A:$AD,23,FALSE) -> 43119 | AP9: =VLOOKUP($A:$A,Variables_extraites!$A:$AD,24,FALSE) -> 28 | AQ9: =VLOOKUP($A:$A,Variables_extraites!$A:$AD,25,FALSE) -> 1 | AR9: =VLOOKUP($A:$A,Variables_extraites!$A:$AD,26,FALSE) -> 43119 | AS9: =VLOOKUP($A:$A,Variables_extraites!$A:$AD,27,FALSE) -> 28 | AT9: =VLOOKUP($A:$A,Variables_extraites!$A:$AD,28,FALSE) -> 28 | AU9: =VLOOKUP($A:$A,Variables_extraites!$A:$AD,29,FALSE) -> 865 | AV9: =VLOOKUP($A:$A,Variables_extraites!$A:$AD,30,FALSE) -> -17.56 | AW9: 8.7237292 | AX9: 7.4976124 | AY9: 5.1830895 | AZ9: 3.7824086 | BA9: 7.6510517 | BB9: 8.6892642 | BC9: 7.8963324 | BD9: 8.0714624 | BE9: 6.2176185 | BF9: 1.1375035 | BG9: 5.8482474 | BH9: 6.5161728 | BI9: 7.7338966 | BJ9: 4.7980505 | BK9: 5.9646297 | BL9: 7.8261035 | BM9: 6.7068068 | BN9: 7.219459 | BO9: 6.1731274 | BP9: 6.2772409 | BQ9: 7.5970097 | BR9: -0.32192809 | BS9: 10.3928 | BT9: 0.23878686 | BU9: 5.5888645 | BV9: 6.6444332 | BW9: 5.4469179 | BX9: 11.140203 | BY9: 3.4711875 | BZ9: 6.5722834 | CA9: 4.6135317 | CB9: 4.5679201 | CC9: 5.9107926 | CD9: 10.154014
A10: 16 | B10: 16 | C10: 2 | D10: HFpEF | E10: 10550 | F10: YES | G10: YES | H10: 79 | I10: 32.653061 | J10: 0 | K10: 2 | L10: 0 | M10: 97 | N10: 41.25 | O10: 92.974799 | P10: 1029 | Q10: 17 | R10: 62.283615 | S10: 22.222222 | T10: 41 | U10: -13.1 | X10: 36.6252 | Y10: =VLOOKUP($A:$A,Variables_extraites!$A:$AD,7,FALSE) -> 0 | Z10: =VLOOKUP($A:$A,Variables_extraites!$A:$AD,8,FALSE) -> 1 | AA10: =VLOOKUP($A:$A,Variables_extraites!$A:$AD,9,FALSE) -> 14.5 | AB10: =VLOOKUP($A:$A,Variables_extraites!$A:$AD,10,FALSE) -> 1 | AC10: =VLOOKUP($A:$A,Variables_extraites!$A:$AD,11,FALSE) -> 0 | AD10: =VLOOKUP($A:$A,Variables_extraites!$A:$AD,12,FALSE) -> 1 | AE10: =VLOOKUP($A:$A,Variables_extraites!$A:$AD,13,FALSE) -> 60.529831 | AF10: =VLOOKUP($A:$A,Variables_extraites!$A:$AD,14,FALSE) -> NA | AG10: =VLOOKUP($A:$A,Variables_extraites!$A:$AD,15,FALSE) -> 19 | AH10: =VLOOKUP($A:$A,Variables_extraites!$A:$AD,16,FALSE) -> 16 | AI10: =VLOOKUP($A:$A,Variables_extraites!$A:$AD,17,FALSE) -> 42345 | AJ10: =VLOOKUP($A:$A,Variables_extraites!$A:$AD,18,FALSE) -> 43398 | AK10: =VLOOKUP($A:$A,Variables_extraites!$A:$AD,19,FALSE) -> 0 | AL10: =VLOOKUP($A:$A,Variables_extraites!$A:$AD,20,FALSE) -> 43398 | AM10: =VLOOKUP($A:$A,Variables_extraites!$A:$AD,21,FALSE) -> 34 | AN10: =VLOOKUP($A:$A,Variables_extraites!$A:$AD,22,FALSE) -> 1 | AO10: =VLOOKUP($A:$A,Variables_extraites!$A:$AD,23,FALSE) -> 42522 | AP10: =VLOOKUP($A:$A,Variables_extraites!$A:$AD,24,FALSE) -> 5 | AQ10: =VLOOKUP($A:$A,Variables_extraites!$A:$AD,25,FALSE) -> 1 | AR10: =VLOOKUP($A:$A,Variables_extraites!$A:$AD,26,FALSE) -> 42522 | AS10: =VLOOKUP($A:$A,Variables_extraites!$A:$AD,27,FALSE) -> 5 | AT10: =VLOOKUP($A:$A,Variables_extraites!$A:$AD,28,FALSE) -> 34 | AU10: =VLOOKUP($A:$A,Variables_extraites!$A:$AD,29,FALSE) -> 1053 | AV10: =VLOOKUP($A:$A,Variables_extraites!$A:$AD,30,FALSE) -> -15.01 | AW10: 8.3718637 | AX10: 7.184677 | AY10: 4.9832217 | AZ10: 1.5509007 | BA10: 7.9629538 | BB10: 5.6182387 | BC10: 9.2555715 | BD10: 7.739173 | BE10: 6.0995056 | BF10: 1.1043367 | BG10: 5.4809113 | BH10: 5.9257621 | BI10: 7.182593 | BJ10: 4.0992952 | BK10: 5.7628803 | BL10: 7.6037747 | BM10: 6.4836546 | BN10: 6.5349642 | BO10: 5.6276068 | BP10: 5.4947356 | BQ10: 7.5376843 | BR10: 1.3103401 | BS10: 9.7673237 | BT10: 1.9855004 | BU10: 3.6403896 | BV10: 7.0748907 | BW10: 4.8904467 | BX10: 10.618936 | BY10: 3.1309309 | BZ10: 8.6093635 | CA10: 3.945795 | CB10: 2.0095726 | CC10: 2.3300494 | CD10: 7.7818233
A11: 17 | B11: 17 | C11: 2 | D11: HFpEF | E11: 10430 | F11: YES | G11: YES | H11: 84 | I11: 37.465565 | J11: 1 | K11: 2 | L11: 0 | M11: 35 | N11: 55.44 | O11: 243.67733 | P11: 4680 | Q11: 31 | R11: 33.874696 | S11: 34.333333 | T11: 22 | U11: -22.5 | V11: 65.825572 | W11: 33.348859 | X11: 159.4128 | Y11: =VLOOKUP($A:$A,Variables_extraites!$A:$AD,7,FALSE) -> 0 | Z11: =VLOOKUP($A:$A,Variables_extraites!$A:$AD,8,FALSE) -> 0 | AA11: =VLOOKUP($A:$A,Variables_extraites!$A:$AD,9,FALSE) -> 9.7 | AB11: =VLOOKUP($A:$A,Variables_extraites!$A:$AD,10,FALSE) -> 1 | AC11: =VLOOKUP($A:$A,Variables_extraites!$A:$AD,11,FALSE) -> 1 | AD11: =VLOOKUP($A:$A,Variables_extraites!$A:$AD,12,FALSE) -> 0 | AE11: =VLOOKUP($A:$A,Variables_extraites!$A:$AD,13,FALSE) -> 76.108871 | AF11: =VLOOKUP($A:$A,Variables_extraites!$A:$AD,14,FALSE) -> 0.93570929 | AG11: =VLOOKUP($A:$A,Variables_extraites!$A:$AD,15,FALSE) -> 19 | AH11: =VLOOKUP($A:$A,Variables_extraites!$A:$AD,16,FALSE) -> 17 | AI11: =VLOOKUP($A:$A,Variables_extraites!$A:$AD,17,FALSE) -> 42255 | AJ11: =VLOOKUP($A:$A,Variables_extraites!$A:$AD,18,FALSE) -> 43229 | AK11: =VLOOKUP($A:$A,Variables_extraites!$A:$AD,19,FALSE) -> 0 | AL11: =VLOOKUP($A:$A,Variables_extraites!$A:$AD,20,FALSE) -> 43229 | AM11: =VLOOKUP($A:$A,Variables_extraites!$A:$AD,21,FALSE) -> 32 | AN11: =VLOOKUP($A:$A,Variables_extraites!$A:$AD,22,FALSE) -> 0 | AO11: =VLOOKUP($A:$A,Variables_extraites!$A:$AD,23,FALSE) -> 43229 | AP11: =VLOOKUP($A:$A,Variables_extraites!$A:$AD,24,FALSE) -> 32 | AQ11: =VLOOKUP($A:$A,Variables_extraites!$A:$AD,25,FALSE) -> 0 | AR11: =VLOOKUP($A:$A,Variables_extraites!$A:$AD,26,FALSE) -> 43229 | AS11: =VLOOKUP($A:$A,Variables_extraites!$A:$AD,27,FALSE) -> 32 | AT11: =VLOOKUP($A:$A,Variables_extraites!$A:$AD,28,FALSE) -> 32 | AU11: =VLOOKUP($A:$A,Variables_extraites!$A:$AD,29,FALSE) -> 974 | AV11: =VLOOKUP($A:$A,Variables_extraites!$A:$AD,30,FALSE) -> -33.47 | AW11: 8.2158727 | AX11: 7.654278 | AY11: 4.6455864 | AZ11: 2.6712934 | BA11: 7.3810237 | BB11: 8.0227007 | BC11: 7.9070709 | BD11: 7.6486092 | BE11: 5.949068 | BF11: 1.3895668 | BG11: 6.2387869 | BH11: 6.7110819 | BI11: 7.5835341 | BJ11: 4.33985 | BK11: 6.0024775 | BL11: 7.7533505 | BM11: 6.3824943 | BN11: 6.2605903 | BO11: 5.9724629 | BP11: 5.6670406 | BQ11: 7.7528155 | BR11: -1.9378783 | BS11: 11.024606 | BT11: 1.6276068 | BU11: 6.9776234 | BV11: 6.9419279 | BW11: 5.3273281 | BX11: 10.639006 | BY11: 3.1890338 | BZ11: 7.0571253 | CA11: 4.3412742 | CB11: 3.5818807 | CC11: 8.9155017 | CD11: 9.3969996
A12: 21 | B12: 21 | C12: 2 | D12: HFpEF | E12: 10364 | F12: YES | H12: 71 | I12: 39.519741 | J12: 1 | K12: 2 | L12: 1 | M12: 50 | N12: 35.45 | O12: 308.78077 | P12: 613.8 | Q12: 13 | R12: 36.490252 | S12: 12 | T12: 26 | U12: -17.5 | V12: 64.819747 | W12: 30.408878 | X12: 98.7428 | Y12: =VLOOKUP($A:$A,Variables_extraites!$A:$AD,7,FALSE) -> 0 | Z12: =VLOOKUP($A:$A,Variables_extraites!$A:$AD,8,FALSE) -> 1 | AA12: =VLOOKUP($A:$A,Variables_extraites!$A:$AD,9,FALSE) -> 11.1 | AB12: =VLOOKUP($A:$A,Variables_extraites!$A:$AD,10,FALSE) -> 0 | AC12: =VLOOKUP($A:$A,Variables_extraites!$A:$AD,11,FALSE) -> 1 | AD12: =VLOOKUP($A:$A,Variables_extraites!$A:$AD,12,FALSE) -> 1 | AE12: =VLOOKUP($A:$A,Variables_extraites!$A:$AD,13,FALSE) -> 63.500305 | AF12: =VLOOKUP($A:$A,Variables_extraites!$A:$AD,14,FALSE) -> 0.76190476 | AG12: =VLOOKUP($A:$A,Variables_extraites!$A:$AD,15,FALSE) -> 27 | AH12: =VLOOKUP($A:$A,Variables_extraites!$A:$AD,16,FALSE) -> 21 | AI12: =VLOOKUP($A:$A,Variables_extraites!$A:$AD,17,FALSE) -> 42248 | AJ12: =VLOOKUP($A:$A,Variables_extraites!$A:$AD,18,FALSE) -> 43404 | AK12: =VLOOKUP($A:$A,Variables_extraites!$A:$AD,19,FALSE) -> 0 | AL12: =VLOOKUP($A:$A,Variables_extraites!$A:$AD,20,FALSE) -> 43404 | AM12: =VLOOKUP($A:$A,Variables_extraites!$A:$AD,21,FALSE) -> 37 | AN12: =VLOOKUP($A:$A,Variables_extraites!$A:$AD,22,FALSE) -> 0 | AO12: =VLOOKUP($A:$A,Variables_extraites!$A:$AD,23,FALSE) -> 43404 | AP12: =VLOOKUP($A:$A,Variables_extraites!$A:$AD,24,FALSE) -> 37 | AQ12: =VLOOKUP($A:$A,Variables_extraites!$A:$AD,25,FALSE) -> 0 | AR12: =VLOOKUP($A:$A,Variables_extraites!$A:$AD,26,FALSE) -> 43404 | AS12: =VLOOKUP($A:$A,Variables_extraites!$A:$AD,27,FALSE) -> 37 | AT12: =VLOOKUP($A:$A,Variables_extraites!$A:$AD,28,FALSE) -> 37 | AU12: =VLOOKUP($A:$A,Variables_extraites!$A:$AD,29,FALSE) -> 1156 | AV12: =VLOOKUP($A:$A,Variables_extraites!$A:$AD,30,FALSE) -> -19.19
A13: 23 | B13: 23 | C13: 2 | D13: HFpEF | E13: 10365 | F13: YES | G13: YES | H13: 72 | I13: 30.359251 | J13: 1 | K13: 4 | L13: 1 | M13: 62 | N13: 44.57 | O13: 161.94705 | P13: 5619 | Q13: 26 | R13: 39.768988 | S13: 38.224543 | T13: 20 | U13: -14.8 | V13: 62.715504 | W13: 36.06983 | X13: 37.677 | Y13: =VLOOKUP($A:$A,Variables_extraites!$A:$AD,7,FALSE) -> 0 | Z13: =VLOOKUP($A:$A,Variables_extraites!$A:$AD,8,FALSE) -> 0 | AA13: =VLOOKUP($A:$A,Variables_extraites!$A:$AD,9,FALSE) -> 9.6 | AB13: =VLOOKUP($A:$A,Variables_extraites!$A:$AD,10,FALSE) -> 1 | AC13: =VLOOKUP($A:$A,Variables_extraites!$A:$AD,11,FALSE) -> 1 | AD13: =VLOOKUP($A:$A,Variables_extraites!$A:$AD,12,FALSE) -> 0 | AE13: =VLOOKUP($A:$A,Variables_extraites!$A:$AD,13,FALSE) -> 65.405951 | AF13: =VLOOKUP($A:$A,Variables_extraites!$A:$AD,14,FALSE) -> 1.9212598 | AG13: =VLOOKUP($A:$A,Variables_extraites!$A:$AD,15,FALSE) -> 18 | AH13: =VLOOKUP($A:$A,Variables_extraites!$A:$AD,16,FALSE) -> 23 | AI13: =VLOOKUP($A:$A,Variables_extraites!$A:$AD,17,FALSE) -> 42220 | AJ13: =VLOOKUP($A:$A,Variables_extraites!$A:$AD,18,FALSE) -> 43388 | AK13: =VLOOKUP($A:$A,Variables_extraites!$A:$AD,19,FALSE) -> 0 | AL13: =VLOOKUP($A:$A,Variables_extraites!$A:$AD,20,FALSE) -> 43388 | AM13: =VLOOKUP($A:$A,Variables_extraites!$A:$AD,21,FALSE) -> 38 | AN13: =VLOOKUP($A:$A,Variables_extraites!$A:$AD,22,FALSE) -> 1 | AO13: =VLOOKUP($A:$A,Variables_extraites!$A:$AD,23,FALSE) -> 43388 | AP13: =VLOOKUP($A:$A,Variables_extraites!$A:$AD,24,FALSE) -> 38 | AQ13: =VLOOKUP($A:$A,Variables_extraites!$A:$AD,25,FALSE) -> 1 | AR13: =VLOOKUP($A:$A,Variables_extraites!$A:$AD,26,FALSE) -> 43388 | AS13: =VLOOKUP($A:$A,Variables_extraites!$A:$AD,27,FALSE) -> 38 | AT13: =VLOOKUP($A:$A,Variables_extraites!$A:$AD,28,FALSE) -> 38 | AU13: =VLOOKUP($A:$A,Variables_extraites!$A:$AD,29,FALSE) -> 1168 | AV13: =VLOOKUP($A:$A,Variables_extraites!$A:$AD,30,FALSE) -> -18.22 | AW13: 9.0088768 | AX13: 8.1583067 | AY13: 5.6624904 | AZ13: 0.81885056 | BA13: 6.9214839 | BB13: 8.3583435 | BC13: 8.7861716 | BD13: 8.4541348 | BE13: 5.9183862 | BF13: 1.5310695 | BG13: 6.0248072 | BH13: 6.4247542 | BI13: 7.5484366 | BJ13: 4.3596617 | BK13: 6.0751047 | BL13: 8.3239104 | BM13: 6.7236951 | BN13: 7.7092906 | BO13: 5.8532472 | BP13: 5.999098 | BQ13: 7.4865535 | BR13: -0.058893689 | BS13: 10.215582 | BT13: -1.3959287 | BU13: 4.3469569 | BV13: 6.0371626 | BW13: 3.0755326 | BX13: 11.183859 | BY13: 3.5459684 | BZ13: 5.1235007 | CA13: 4.7591558 | CB13: 6.060358 | CC13: 4.4058506 | CD13: 11.61151
A14: 24 | B14: 24 | C14: 2 | D14: HFpEF | E14: 10549 | F14: YES | G14: YES | H14: 78 | I14: 24.023809 | J14: 0 | K14: 3 | L14: 0 | M14: 40 | N14: 82.91 | O14: 2777.9081 | P14: 822.9 | Q14: 28 | R14: 83.573438 | S14: 12.77193 | T14: 25 | U14: -17.3 | V14: 61.936093 | W14: 38.395107 | X14: 69.7887 | Y14: =VLOOKUP($A:$A,Variables_extraites!$A:$AD,7,FALSE) -> 0 | Z14: =VLOOKUP($A:$A,Variables_extraites!$A:$AD,8,FALSE) -> 0 | AA14: =VLOOKUP($A:$A,Variables_extraites!$A:$AD,9,FALSE) -> 8.6 | AB14: =VLOOKUP($A:$A,Variables_extraites!$A:$AD,10,FALSE) -> 1 | AC14: =VLOOKUP($A:$A,Variables_extraites!$A:$AD,11,FALSE) -> 1 | AD14: =VLOOKUP($A:$A,Variables_extraites!$A:$AD,12,FALSE) -> 1 | AE14: =VLOOKUP($A:$A,Variables_extraites!$A:$AD,13,FALSE) -> 63.584906 | AF14: =VLOOKUP($A:$A,Variables_extraites!$A:$AD,14,FALSE) -> NA | AG14: =VLOOKUP($A:$A,Variables_extraites!$A:$AD,15,FALSE) -> 14.333333 | AH14: =VLOOKUP($A:$A,Variables_extraites!$A:$AD,16,FALSE) -> 24 | AI14: =VLOOKUP($A:$A,Variables_extraites!$A:$AD,17,FALSE) -> 42304 | AJ14: =VLOOKUP($A:$A,Variables_extraites!$A:$AD,18,FALSE) -> 42899 | AK14: =VLOOKUP($A:$A,Variables_extraites!$A:$AD,19,FALSE) -> 1 | AL14: =VLOOKUP($A:$A,Variables_extraites!$A:$AD,20,FALSE) -> 42899 | AM14: =VLOOKUP($A:$A,Variables_extraites!$A:$AD,21,FALSE) -> 19 | AN14: =VLOOKUP($A:$A,Variables_extraites!$A:$AD,22,FALSE) -> 1 | AO14: =VLOOKUP($A:$A,Variables_extraites!$A:$AD,23,FALSE) -> 42328 | AP14: =VLOOKUP($A:$A,Variables_extraites!$A:$AD,24,FALSE) -> 1 | AQ14: =VLOOKUP($A:$A,Variables_extraites!$A:$AD,25,FALSE) -> 1 | AR14: =VLOOKUP($A:$A,Variables_extraites!$A:$AD,26,FALSE) -> 42328 | AS14: =VLOOKUP($A:$A,Variables_extraites!$A:$AD,27,FALSE) -> 1 | AT14: =VLOOKUP($A:$A,Variables_extraites!$A:$AD,28,FALSE) -> 19 | AU14: =VLOOKUP($A:$A,Variables_extraites!$A:$AD,29,FALSE) -> 595 | AV14: =VLOOKUP($A:$A,Variables_extraites!$A:$AD,30,FALSE) -> NA | AW14: 8.5761064 | AX14: 7.6420517 | AY14: 5.4518705 | AZ14: 1.6229304 | BA14: 8.3679389 | BB14: 5.4873577 | BC14: 9.1054633 | BD14: 7.614489 | BE14: 6.1801081 | BF14: 0.82374936 | BG14: 6.6881804 | BH14: 7.1798096 | BI14: 8.3001237 | BJ14: 5.2835514 | BK14: 6.4666271 | BL14: 7.0737131 | BM14: 6.1921942 | BN14: 7.3304688 | BO14: 6.4770297 | BP14: 6.8197959 | BQ14: 8.3734307 | BR14: 1.9597702 | BS14: 9.0239206 | BT14: 1.0214797 | BU14: 4.4208866 | BV14: 6.100347 | BW14: 5.4001963 | BX14: 11.04565 | BY14: 3.3729521 | BZ14: 8.6141945 | CA14: 4.2555007 | CB14: 2.431456 | CC14: 2.4611164 | CD14: 8.0024409
A15: 26 | B15: 26 | C15: 2 | D15: HFpEF | E15: 10333 | F15: YES | G15: YES | H15: 53 | I15: 37.5 | J15: 1 | K15: 2 | L15: 1 | M15: 63 | N15: 28.8 | O15: 1228.6101 | P15: 67.1 | Q15: 18 | R15: 29.105879 | S15: 14.145833 | T15: 26 | U15: -18.2 | X15: 38.0923 | Y15: =VLOOKUP($A:$A,Variables_extraites!$A:$AD,7,FALSE) -> 0 | Z15: =VLOOKUP($A:$A,Variables_extraites!$A:$AD,8,FALSE) -> 1 | AA15: =VLOOKUP($A:$A,Variables_extraites!$A:$AD,9,FALSE) -> 10.4 | AB15: =VLOOKUP($A:$A,Variables_extraites!$A:$AD,10,FALSE) -> 1 | AC15: =VLOOKUP($A:$A,Variables_extraites!$A:$AD,11,FALSE) -> 0 | AD15: =VLOOKUP($A:$A,Variables_extraites!$A:$AD,12,FALSE) -> 0 | AE15: =VLOOKUP($A:$A,Variables_extraites!$A:$AD,13,FALSE) -> 74.603175 | AF15: =VLOOKUP($A:$A,Variables_extraites!$A:$AD,14,FALSE) -> 0.69569672 | AG15: =VLOOKUP($A:$A,Variables_extraites!$A:$AD,15,FALSE) -> 21 | AH15: =VLOOKUP($A:$A,Variables_extraites!$A:$AD,16,FALSE) -> 26 | AI15: =VLOOKUP($A:$A,Variables_extraites!$A:$AD,17,FALSE) -> 42048 | AJ15: =VLOOKUP($A:$A,Variables_extraites!$A:$AD,18,FALSE) -> 43480 | AK15: =VLOOKUP($A:$A,Variables_extraites!$A:$AD,19,FALSE) -> 0 | AL15: =VLOOKUP($A:$A,Variables_extraites!$A:$AD,20,FALSE) -> 43480 | AM15: =VLOOKUP($A:$A,Variables_extraites!$A:$AD,21,FALSE) -> 47 | AN15: =VLOOKUP($A:$A,Variables_extraites!$A:$AD,22,FALSE) -> 0 | AO15: =VLOOKUP($A:$A,Variables_extraites!$A:$AD,23,FALSE) -> 43480 | AP15: =VLOOKUP($A:$A,Variables_extraites!$A:$AD,24,FALSE) -> 47 | AQ15: =VLOOKUP($A:$A,Variables_extraites!$A:$AD,25,FALSE) -> 0 | AR15: =VLOOKUP($A:$A,Variables_extraites!$A:$AD,26,FALSE) -> 43480 | AS15: =VLOOKUP($A:$A,Variables_extraites!$A:$AD,27,FALSE) -> 47 | AT15: =VLOOKUP($A:$A,Variables_extraites!$A:$AD,28,FALSE) -> 47 | AU15: =VLOOKUP($A:$A,Variables_extraites!$A:$AD,29,FALSE) -> 1432 | AV15: =VLOOKUP($A:$A,Variables_extraites!$A:$AD,30,FALSE) -> -22.86 | AW15: 8.7173337 | AX15: 7.0381508 | AY15: 4.3750394 | AZ15: 3.2570106 | BA15: 7.9576245 | BB15: 7.5655972 | BC15: 8.3700771 | BD15: 7.3178648 | BE15: 6.0870385 | BF15: 1.169925 | BG15: 6.2639734 | BH15: 6.8027102 | BI15: 7.4139664 | BJ15: 4.1043367 | BK15: 5.746044 | BL15: 8.2771944 | BM15: 6.0889472 | BN15: 6.6431347 | BO15: 5.5533605 | BP15: 5.5062084 | BQ15: 8.1267561 | BR15: -0.64385619 | BS15: 11.679625 | BT15: 3.0107798 | BU15: 6.139142 | BV15: 7.2075025 | BW15: 5.3323499 | BX15: 11.449391 | BY15: 3.1026581 | BZ15: 8.3058793 | CA15: 4.0321008 | CB15: 3.1435118 | CC15: 6.7829982 | CD15: 8.6688454
A16: 29 | B16: 29 | C16: 2 | D16: HFpEF | E16: 10514 | F16: YES | H16: 79 | I16: 23.875433 | J16: 0 | K16: 2 | L16: 1 | M16: 34 | N16: 38.08 | O16: 123.33415 | R16: 42.169935 | T16: 13 | X16: 52.7911 | Y16: =VLOOKUP($A:$A,Variables_extraites!$A:$AD,7,FALSE) -> 0 | Z16: =VLOOKUP($A:$A,Variables_extraites!$A:$AD,8,FALSE) -> 0 | AA16: =VLOOKUP($A:$A,Variables_extraites!$A:$AD,9,FALSE) -> 9.5 | AB16: =VLOOKUP($A:$A,Variables_extraites!$A:$AD,10,FALSE) -> 0 | AC16: =VLOOKUP($A:$A,Variables_extraites!$A:$AD,11,FALSE) -> 1 | AD16: =VLOOKUP($A:$A,Variables_extraites!$A:$AD,12,FALSE) -> 1 | AE16: =VLOOKUP($A:$A,Variables_extraites!$A:$AD,13,FALSE) -> 53.478359 | AF16: =VLOOKUP($A:$A,Variables_extraites!$A:$AD,14,FALSE) -> NA | AG16: =VLOOKUP($A:$A,Variables_extraites!$A:$AD,15,FALSE) -> 16 | AH16: =VLOOKUP($A:$A,Variables_extraites!$A:$AD,16,FALSE) -> NA | AI16: =VLOOKUP($A:$A,Variables_extraites!$A:$AD,17,FALSE) -> NA | AJ16: =VLOOKUP($A:$A,Variables_extraites!$A:$AD,18,FALSE) -> 43542 | AK16: =VLOOKUP($A:$A,Variables_extraites!$A:$AD,19,FALSE) -> 0 | AL16: =VLOOKUP($A:$A,Variables_extraites!$A:$AD,20,FALSE) -> 43542 | AM16: =VLOOKUP($A:$A,Variables_extraites!$A:$AD,21,FALSE) -> 41 | AN16: =VLOOKUP($A:$A,Variables_extraites!$A:$AD,22,FALSE) -> 0 | AO16: =VLOOKUP($A:$A,Variables_extraites!$A:$AD,23,FALSE) -> 43542 | AP16: =VLOOKUP($A:$A,Variables_extraites!$A:$AD,24,FALSE) -> 41 | AQ16: =VLOOKUP($A:$A,Variables_extraites!$A:$AD,25,FALSE) -> 0 | AR16: =VLOOKUP($A:$A,Variables_extraites!$A:$AD,26,FALSE) -> 43542 | AS16: =VLOOKUP($A:$A,Variables_extraites!$A:$AD,27,FALSE) -> 41 | AT16: =VLOOKUP($A:$A,Variables_extraites!$A:$AD,28,FALSE) -> 41 | AU16: =VLOOKUP($A:$A,Variables_extraites!$A:$AD,29,FALSE) -> 1260 | AV16: =VLOOKUP($A:$A,Variables_extraites!$A:$AD,30,FALSE) -> NA
A17: 30 | B17: 30 | C17: 2 | D17: HFpEF | E17: 10334 | F17: YES | G17: YES | H17: 56 | I17: 36.71875 | J17: 1 | K17: 2 | L17: 0 | M17: 34 | N17: 25.53 | O17: 683.63377 | P17: 476.8 | Q17: 11 | R17: 23.509265 | S17: 28.863636 | T17: 47 | V17: 47.884527 | W17: 39.171243 | X17: 84.1588 | Y17: =VLOOKUP($A:$A,Variables_extraites!$A:$AD,7,FALSE) -> 0 | Z17: =VLOOKUP($A:$A,Variables_extraites!$A:$AD,8,FALSE) -> 0 | AA17: =VLOOKUP($A:$A,Variables_extraites!$A:$AD,9,FALSE) -> 10.8 | AB17: =VLOOKUP($A:$A,Variables_extraites!$A:$AD,10,FALSE) -> 1 | AC17: =VLOOKUP($A:$A,Variables_extraites!$A:$AD,11,FALSE) -> 0 | AD17: =VLOOKUP($A:$A,Variables_extraites!$A:$AD,12,FALSE) -> 0 | AE17: =VLOOKUP($A:$A,Variables_extraites!$A:$AD,13,FALSE) -> 59.505703 | AF17: =VLOOKUP($A:$A,Variables_extraites!$A:$AD,14,FALSE) -> 0.71468768 | AG17: =VLOOKUP($A:$A,Variables_extraites!$A:$AD,15,FALSE) -> 25 | AH17: =VLOOKUP($A:$A,Variables_extraites!$A:$AD,16,FALSE) -> NA | AI17: =VLOOKUP($A:$A,Variables_extraites!$A:$AD,17,FALSE) -> NA | AJ17: =VLOOKUP($A:$A,Variables_extraites!$A:$AD,18,FALSE) -> NA | AK17: =VLOOKUP($A:$A,Variables_extraites!$A:$AD,19,FALSE) -> NA | AL17: =VLOOKUP($A:$A,Variables_extraites!$A:$AD,20,FALSE) -> NA | AM17: =VLOOKUP($A:$A,Variables_extraites!$A:$AD,21,FALSE) -> NA | AN17: =VLOOKUP($A:$A,Variables_extraites!$A:$AD,22,FALSE) -> NA | AO17: =VLOOKUP($A:$A,Variables_extraites!$A:$AD,23,FALSE) -> NA | AP17: =VLOOKUP($A:$A,Variables_extraites!$A:$AD,24,FALSE) -> NA | AQ17: =VLOOKUP($A:$A,Variables_extraites!$A:$AD,25,FALSE) -> NA | AR17: =VLOOKUP($A:$A,Variables_extraites!$A:$AD,26,FALSE) -> NA | AS17: =VLOOKUP($A:$A,Variables_extraites!$A:$AD,27,FALSE) -> NA | AT17: =VLOOKUP($A:$A,Variables_extraites!$A:$AD,28,FALSE) -> NA | AU17: =VLOOKUP($A:$A,Variables_extraites!$A:$AD,29,FALSE) -> NA | AV17: =VLOOKUP($A:$A,Variables_extraites!$A:$AD,30,FALSE) -> NA | AW17: 8.4897677 | AX17: 7.6444332 | AY17: 4.2964574 | AZ17: 2.9278965 | BA17: 7.7096353 | BB17: 8.0324866 | BC17: 8.0319906 | BD17: 7.5975312 | BE17: 5.3483741 | BF17: 2.4931349 | BG17: 6.1795111 | BH17: 6.6540631 | BI17: 7.1843795 | BJ17: 3.9107327 | BK17: 6.3366404 | BL17: 8.7000929 | BM17: 5.6313954 | BN17: 6.7305041 | BO17: 3.7937919 | BP17: 6.283181 | BQ17: 8.0490317 | BR17: 1.2509616 | BS17: 9.0071955 | BT17: 0.042644337 | BU17: 5.3004898 | BV17: 6.9653225 | BW17: 5.1235007 | BX17: 10.74145 | BY17: 2.8135247 | BZ17: 7.0057368 | CA17: 4.304511 | CB17: 3.7357133 | CC17: 4.0495283 | CD17: 8.9645512
A18: 31 | B18: 31 | C18: 2 | D18: HFpEF | E18: 10299 | F18: YES | G18: YES | H18: 73 | I18: 25.065746 | J18: 1 | K18: 2 | L18: 1 | M18: 27 | N18: 35.65 | O18: 215.16023 | P18: 2891 | Q18: 18 | R18: 48.354285 | S18: 33.4375 | T18: 57 | U18: -15.2 | V18: 71.421888 | W18: 34.162488 | X18: 116.7772 | Y18: =VLOOKUP($A:$A,Variables_extraites!$A:$AD,7,FALSE) -> 0 | Z18: =VLOOKUP($A:$A,Variables_extraites!$A:$AD,8,FALSE) -> 0 | AA18: =VLOOKUP($A:$A,Variables_extraites!$A:$AD,9,FALSE) -> 9.8 | AB18: =VLOOKUP($A:$A,Variables_extraites!$A:$AD,10,FALSE) -> 1 | AC18: =VLOOKUP($A:$A,Variables_extraites!$A:$AD,11,FALSE) -> 1 | AD18: =VLOOKUP($A:$A,Variables_extraites!$A:$AD,12,FALSE) -> 0 | AE18: =VLOOKUP($A:$A,Variables_extraites!$A:$AD,13,FALSE) -> 60.105557 | AF18: =VLOOKUP($A:$A,Variables_extraites!$A:$AD,14,FALSE) -> 1.7774086 | AG18: =VLOOKUP($A:$A,Variables_extraites!$A:$AD,15,FALSE) -> 22 | AH18: =VLOOKUP($A:$A,Variables_extraites!$A:$AD,16,FALSE) -> 31 | AI18: =VLOOKUP($A:$A,Variables_extraites!$A:$AD,17,FALSE) -> 42290 | AJ18: =VLOOKUP($A:$A,Variables_extraites!$A:$AD,18,FALSE) -> 42861 | AK18: =VLOOKUP($A:$A,Variables_extraites!$A:$AD,19,FALSE) -> 1 | AL18: =VLOOKUP($A:$A,Variables_extraites!$A:$AD,20,FALSE) -> 42861 | AM18: =VLOOKUP($A:$A,Variables_extraites!$A:$AD,21,FALSE) -> 18 | AN18: =VLOOKUP($A:$A,Variables_extraites!$A:$AD,22,FALSE) -> 0 | AO18: =VLOOKUP($A:$A,Variables_extraites!$A:$AD,23,FALSE) -> 42861 | AP18: =VLOOKUP($A:$A,Variables_extraites!$A:$AD,24,FALSE) -> 18 | AQ18: =VLOOKUP($A:$A,Variables_extraites!$A:$AD,25,FALSE) -> 1 | AR18: =VLOOKUP($A:$A,Variables_extraites!$A:$AD,26,FALSE) -> 42861 | AS18: =VLOOKUP($A:$A,Variables_extraites!$A:$AD,27,FALSE) -> 18 | AT18: =VLOOKUP($A:$A,Variables_extraites!$A:$AD,28,FALSE) -> 18 | AU18: =VLOOKUP($A:$A,Variables_extraites!$A:$AD,29,FALSE) -> 571 | AV18: =VLOOKUP($A:$A,Variables_extraites!$A:$AD,30,FALSE) -> -23.1 | AW18: 9.2086977 | AX18: 7.5719043 | AY18: 5.5310695 | AZ18: 2.3103401 | BA18: 8.0618842 | BB18: 8.4037364 | BC18: 7.9926551 | BD18: 7.6237352 | BE18: 6.5112783 | BF18: 1.4854268 | BG18: 6.3974607 | BH18: 6.7889467 | BI18: 7.645082 | BJ18: 5.0552824 | BK18: 6.2605903 | BL18: 8.1704259 | BM18: 6.3275077 | BN18: 7.035074 | BO18: 6.3615929 | BP18: 6.4841381 | BQ18: 7.940754 | BR18: 1.2078929 | BS18: 9.6534721 | BT18: 1.5655972 | BU18: 3.7484612 | BV18: 6.9524501 | BW18: 5.9450926 | BX18: 10.797645 | BY18: 3.598127 | BZ18: 8.3984017 | CA18: 4.2839218 | CB18: 2.3992436 | CC18: 2.5405684 | CD18: 8.0878749
A19: 34 | B19: 34 | C19: 2 | D19: HFpEF | E19: 10335 | F19: YES | H19: 84 | I19: 16.896235 | J19: 1 | K19: 2 | L19: 0 | M19: 47 | N19: 36.34 | O19: 335.77704 | P19: 3330 | Q19: 52 | R19: 39.283369 | S19: 11.383562 | T19: 17 | U19: -14.186667 | V19: 55.36258 | W19: 28.868096 | X19: 98.4318 | Y19: =VLOOKUP($A:$A,Variables_extraites!$A:$AD,7,FALSE) -> 0 | Z19: =VLOOKUP($A:$A,Variables_extraites!$A:$AD,8,FALSE) -> 0 | AA19: =VLOOKUP($A:$A,Variables_extraites!$A:$AD,9,FALSE) -> 12.4 | AB19: =VLOOKUP($A:$A,Variables_extraites!$A:$AD,10,FALSE) -> 1 | AC19: =VLOOKUP($A:$A,Variables_extraites!$A:$AD,11,FALSE) -> 0 | AD19: =VLOOKUP($A:$A,Variables_extraites!$A:$AD,12,FALSE) -> 1 | AE19: =VLOOKUP($A:$A,Variables_extraites!$A:$AD,13,FALSE) -> 68.52861 | AF19: =VLOOKUP($A:$A,Variables_extraites!$A:$AD,14,FALSE) -> NA | AG19: =VLOOKUP($A:$A,Variables_extraites!$A:$AD,15,FALSE) -> 11 | AH19: =VLOOKUP($A:$A,Variables_extraites!$A:$AD,16,FALSE) -> 34 | AI19: =VLOOKUP($A:$A,Variables_extraites!$A:$AD,17,FALSE) -> 42199 | AJ19: =VLOOKUP($A:$A,Variables_extraites!$A:$AD,18,FALSE) -> 43437 | AK19: =VLOOKUP($A:$A,Variables_extraites!$A:$AD,19,FALSE) -> 0 | AL19: =VLOOKUP($A:$A,Variables_extraites!$A:$AD,20,FALSE) -> 43437 | AM19: =VLOOKUP($A:$A,Variables_extraites!$A:$AD,21,FALSE) -> 40 | AN19: =VLOOKUP($A:$A,Variables_extraites!$A:$AD,22,FALSE) -> 1 | AO19: =VLOOKUP($A:$A,Variables_extraites!$A:$AD,23,FALSE) -> 43000 | AP19: =VLOOKUP($A:$A,Variables_extraites!$A:$AD,24,FALSE) -> 26 | AQ19: =VLOOKUP($A:$A,Variables_extraites!$A:$AD,25,FALSE) -> 1 | AR19: =VLOOKUP($A:$A,Variables_extraites!$A:$AD,26,FALSE) -> 43000 | AS19: =VLOOKUP($A:$A,Variables_extraites!$A:$AD,27,FALSE) -> 26 | AT19: =VLOOKUP($A:$A,Variables_extraites!$A:$AD,28,FALSE) -> 40 | AU19: =VLOOKUP($A:$A,Variables_extraites!$A:$AD,29,FALSE) -> 1238 | AV19: =VLOOKUP($A:$A,Variables_extraites!$A:$AD,30,FALSE) -> NA
A20: 37 | B20: 37 | C20: 2 | D20: HFpEF | E20: 10431 | F20: YES | H20: 71 | I20: 23.138507 | J20: 1 | K20: 2 | L20: 1 | M20: 64 | N20: 45.96 | O20: 712.66131 | P20: 2495 | Q20: 29 | R20: 49.48035 | S20: 17.05314 | T20: 24 | U20: -15.666667 | V20: 78.630192 | W20: 31.678041 | X20: 34.0253 | Y20: =VLOOKUP($A:$A,Variables_extraites!$A:$AD,7,FALSE) -> 0 | Z20: =VLOOKUP($A:$A,Variables_extraites!$A:$AD,8,FALSE) -> 0 | AA20: =VLOOKUP($A:$A,Variables_extraites!$A:$AD,9,FALSE) -> 11.8 | AB20: =VLOOKUP($A:$A,Variables_extraites!$A:$AD,10,FALSE) -> 1 | AC20: =VLOOKUP($A:$A,Variables_extraites!$A:$AD,11,FALSE) -> 0 | AD20: =VLOOKUP($A:$A,Variables_extraites!$A:$AD,12,FALSE) -> 1 | AE20: =VLOOKUP($A:$A,Variables_extraites!$A:$AD,13,FALSE) -> 71.907344 | AF20: =VLOOKUP($A:$A,Variables_extraites!$A:$AD,14,FALSE) -> NA | AG20: =VLOOKUP($A:$A,Variables_extraites!$A:$AD,15,FALSE) -> 14.666667 | AH20: =VLOOKUP($A:$A,Variables_extraites!$A:$AD,16,FALSE) -> 37 | AI20: =VLOOKUP($A:$A,Variables_extraites!$A:$AD,17,FALSE) -> 42111 | AJ20: =VLOOKUP($A:$A,Variables_extraites!$A:$AD,18,FALSE) -> 43245 | AK20: =VLOOKUP($A:$A,Variables_extraites!$A:$AD,19,FALSE) -> 1 | AL20: =VLOOKUP($A:$A,Variables_extraites!$A:$AD,20,FALSE) -> 43245 | AM20: =VLOOKUP($A:$A,Variables_extraites!$A:$AD,21,FALSE) -> 37 | AN20: =VLOOKUP($A:$A,Variables_extraites!$A:$AD,22,FALSE) -> 1 | AO20: =VLOOKUP($A:$A,Variables_extraites!$A:$AD,23,FALSE) -> 42637 | AP20: =VLOOKUP($A:$A,Variables_extraites!$A:$AD,24,FALSE) -> 17 | AQ20: =VLOOKUP($A:$A,Variables_extraites!$A:$AD,25,FALSE) -> 1 | AR20: =VLOOKUP($A:$A,Variables_extraites!$A:$AD,26,FALSE) -> 42637 | AS20: =VLOOKUP($A:$A,Variables_extraites!$A:$AD,27,FALSE) -> 17 | AT20: =VLOOKUP($A:$A,Variables_extraites!$A:$AD,28,FALSE) -> 37 | AU20: =VLOOKUP($A:$A,Variables_extraites!$A:$AD,29,FALSE) -> 1133 | AV20: =VLOOKUP($A:$A,Variables_extraites!$A:$AD,30,FALSE) -> -23.116667
A21: 38 | B21: 38 | C21: 2 | D21: HFpEF | E21: 10645 | F21: YES | G21: YES | H21: 68 | I21: 23.62949 | J21: 0 | K21: 0 | L21: 0 | M21: 89 | N21: 37.63 | O21: 690.235 | P21: 1791 | Q21: 10 | R21: 46.463173 | S21: 9.56621 | T21: 23 | U21: -14.56 | V21: 55.949224 | W21: 32.837057 | X21: 16.8044 | Y21: =VLOOKUP($A:$A,Variables_extraites!$A:$AD,7,FALSE) -> 0 | Z21: =VLOOKUP($A:$A,Variables_extraites!$A:$AD,8,FALSE) -> 0 | AA21: =VLOOKUP($A:$A,Variables_extraites!$A:$AD,9,FALSE) -> 12.2 | AB21: =VLOOKUP($A:$A,Variables_extraites!$A:$AD,10,FALSE) -> 1 | AC21: =VLOOKUP($A:$A,Variables_extraites!$A:$AD,11,FALSE) -> 0 | AD21: =VLOOKUP($A:$A,Variables_extraites!$A:$AD,12,FALSE) -> 1 | AE21: =VLOOKUP($A:$A,Variables_extraites!$A:$AD,13,FALSE) -> 63.525132 | AF21: =VLOOKUP($A:$A,Variables_extraites!$A:$AD,14,FALSE) -> NA | AG21: =VLOOKUP($A:$A,Variables_extraites!$A:$AD,15,FALSE) -> 28 | AH21: =VLOOKUP($A:$A,Variables_extraites!$A:$AD,16,FALSE) -> 38 | AI21: =VLOOKUP($A:$A,Variables_extraites!$A:$AD,17,FALSE) -> 42128 | AJ21: =VLOOKUP($A:$A,Variables_extraites!$A:$AD,18,FALSE) -> 43542 | AK21: =VLOOKUP($A:$A,Variables_extraites!$A:$AD,19,FALSE) -> 0 | AL21: =VLOOKUP($A:$A,Variables_extraites!$A:$AD,20,FALSE) -> 43542 | AM21: =VLOOKUP($A:$A,Variables_extraites!$A:$AD,21,FALSE) -> 46 | AN21: =VLOOKUP($A:$A,Variables_extraites!$A:$AD,22,FALSE) -> 0 | AO21: =VLOOKUP($A:$A,Variables_extraites!$A:$AD,23,FALSE) -> 43542 | AP21: =VLOOKUP($A:$A,Variables_extraites!$A:$AD,24,FALSE) -> 46 | AQ21: =VLOOKUP($A:$A,Variables_extraites!$A:$AD,25,FALSE) -> 0 | AR21: =VLOOKUP($A:$A,Variables_extraites!$A:$AD,26,FALSE) -> 43542 | AS21: =VLOOKUP($A:$A,Variables_extraites!$A:$AD,27,FALSE) -> 46 | AT21: =VLOOKUP($A:$A,Variables_extraites!$A:$AD,28,FALSE) -> 46 | AU21: =VLOOKUP($A:$A,Variables_extraites!$A:$AD,29,FALSE) -> 1414 | AV21: =VLOOKUP($A:$A,Variables_extraites!$A:$AD,30,FALSE) -> -20.41 | AW21: 8.6310679 | AX21: 8.3717766 | AY21: 5.7189096 | AZ21: 2.3504972 | BA21: 8.4911316 | BB21: 6.742141 | BC21: 9.1847018 | BD21: 8.0050631 | BE21: 6.1739269 | BF21: 1.1309309 | BG21: 6.968206 | BH21: 7.3975463 | BI21: 8.1214817 | BJ21: 5.5762198 | BK21: 6.5362084 | BL21: 8.1629955 | BM21: 6.8812975 | BN21: 7.6711518 | BO21: 6.035184 | BP21: 6.6230767 | BQ21: 8.4220227 | BR21: 3.2509616 | BS21: 11.161963 | BT21: 3.5861642 | BU21: 5.7570232 | BV21: 6.1801081 | BW21: 5.1902198 | BX21: 10.471513 | BY21: 3.1375035 | BZ21: 8.6696292 | CA21: 3.6016965 | CB21: 1.8018835 | CC21: 2.5060617 | CD21: 7.575799
A22: 40 | B22: 40 | C22: 2 | D22: HFpEF | E22: 10509 | F22: YES | G22: YES | H22: 73 | I22: 33.834027 | J22: 0 | K22: 2 | L22: 1 | M22: 64 | N22: 110.63 | O22: 104.76655 | P22: 158.4 | Q22: 24 | R22: 19.582431 | S22: 14.022727 | T22: 31 | U22: -13.7 | V22: 63.771803 | W22: 36.015702 | X22: 54.2997 | Y22: =VLOOKUP($A:$A,Variables_extraites!$A:$AD,7,FALSE) -> 0 | Z22: =VLOOKUP($A:$A,Variables_extraites!$A:$AD,8,FALSE) -> 1 | AA22: =VLOOKUP($A:$A,Variables_extraites!$A:$AD,9,FALSE) -> 14.8 | AB22: =VLOOKUP($A:$A,Variables_extraites!$A:$AD,10,FALSE) -> 0 | AC22: =VLOOKUP($A:$A,Variables_extraites!$A:$AD,11,FALSE) -> 0 | AD22: =VLOOKUP($A:$A,Variables_extraites!$A:$AD,12,FALSE) -> 0 | AE22: =VLOOKUP($A:$A,Variables_extraites!$A:$AD,13,FALSE) -> 58.626329 | AF22: =VLOOKUP($A:$A,Variables_extraites!$A:$AD,14,FALSE) -> 0.77610063 | AG22: =VLOOKUP($A:$A,Variables_extraites!$A:$AD,15,FALSE) -> 11 | AH22: =VLOOKUP($A:$A,Variables_extraites!$A:$AD,16,FALSE) -> 40 | AI22: =VLOOKUP($A:$A,Variables_extraites!$A:$AD,17,FALSE) -> 42262 | AJ22: =VLOOKUP($A:$A,Variables_extraites!$A:$AD,18,FALSE) -> 43244 | AK22: =VLOOKUP($A:$A,Variables_extraites!$A:$AD,19,FALSE) -> 0 | AL22: =VLOOKUP($A:$A,Variables_extraites!$A:$AD,20,FALSE) -> 43244 | AM22: =VLOOKUP($A:$A,Variables_extraites!$A:$AD,21,FALSE) -> 32 | AN22: =VLOOKUP($A:$A,Variables_extraites!$A:$AD,22,FALSE) -> 0 | AO22: =VLOOKUP($A:$A,Variables_extraites!$A:$AD,23,FALSE) -> 43244 | AP22: =VLOOKUP($A:$A,Variables_extraites!$A:$AD,24,FALSE) -> 32 | AQ22: =VLOOKUP($A:$A,Variables_extraites!$A:$AD,25,FALSE) -> 0 | AR22: =VLOOKUP($A:$A,Variables_extraites!$A:$AD,26,FALSE) -> 43244 | AS22: =VLOOKUP($A:$A,Variables_extraites!$A:$AD,27,FALSE) -> 32 | AT22: =VLOOKUP($A:$A,Variables_extraites!$A:$AD,28,FALSE) -> 32 | AU22: =VLOOKUP($A:$A,Variables_extraites!$A:$AD,29,FALSE) -> 982 | AV22: =VLOOKUP($A:$A,Variables_extraites!$A:$AD,30,FALSE) -> -16.25 | AW22: 8.2176669 | AX22: 7.1627941 | AY22: 4.4409522 | AZ22: 2.7004397 | BA22: 6.7638099 | BB22: 6.7405229 | BC22: 8.5247768 | BD22: 7.8712276 | BE22: 5.9049657 | BF22: 2.2839218 | BG22: 6.8593484 | BH22: 7.0678108 | BI22: 7.3431413 | BJ22: 4.052242 | BK22: 6.0746767 | BL22: 7.4323749 | BM22: 5.6102867 | BN22: 6.2494453 | BO22: 4.6853796 | BP22: 5.6602099 | BQ22: 8.1369399 | BR22: 2.6937657 | BS22: 10.751117 | BT22: 1.5058909 | BU22: 5.4124428 | BV22: 7.0083166 | BW22: 4.5360529 | BX22: 10.71041 | BY22: 3.3419857 | BZ22: 7.3388701 | CA22: 4.1101962 | CB22: 3.3715404 | CC22: 2.7186771 | CD22: 9.2452263
A23: 41 | B23: 41 | C23: 2 | D23: HFpEF | E23: 10432 | F23: YES | H23: 78 | I23: 37.729725 | J23: 1 | K23: 2 | L23: 1 | M23: 61 | N23: 46.86 | O23: 435.73259 | P23: 2441 | Q23: 14 | R23: 44.798505 | S23: 14.102041 | T23: 35.366667 | U23: -18.553333 | V23: 49.950967 | W23: 30.164534 | X23: 77.5146 | Y23: =VLOOKUP($A:$A,Variables_extraites!$A:$AD,7,FALSE) -> 0 | Z23: =VLOOKUP($A:$A,Variables_extraites!$A:$AD,8,FALSE) -> 0 | AA23: =VLOOKUP($A:$A,Variables_extraites!$A:$AD,9,FALSE) -> 10.7 | AB23: =VLOOKUP($A:$A,Variables_extraites!$A:$AD,10,FALSE) -> 1 | AC23: =VLOOKUP($A:$A,Variables_extraites!$A:$AD,11,FALSE) -> 0 | AD23: =VLOOKUP($A:$A,Variables_extraites!$A:$AD,12,FALSE) -> 1 | AE23: =VLOOKUP($A:$A,Variables_extraites!$A:$AD,13,FALSE) -> 61.273337 | AF23: =VLOOKUP($A:$A,Variables_extraites!$A:$AD,14,FALSE) -> NA | AG23: =VLOOKUP($A:$A,Variables_extraites!$A:$AD,15,FALSE) -> 14.333333 | AH23: =VLOOKUP($A:$A,Variables_extraites!$A:$AD,16,FALSE) -> 41 | AI23: =VLOOKUP($A:$A,Variables_extraites!$A:$AD,17,FALSE) -> 42202 | AJ23: =VLOOKUP($A:$A,Variables_extraites!$A:$AD,18,FALSE) -> 43326 | AK23: =VLOOKUP($A:$A,Variables_extraites!$A:$AD,19,FALSE) -> 0 | AL23: =VLOOKUP($A:$A,Variables_extraites!$A:$AD,20,FALSE) -> 43326 | AM23: =VLOOKUP($A:$A,Variables_extraites!$A:$AD,21,FALSE) -> 36 | AN23: =VLOOKUP($A:$A,Variables_extraites!$A:$AD,22,FALSE) -> 1 | AO23: =VLOOKUP($A:$A,Variables_extraites!$A:$AD,23,FALSE) -> 42668 | AP23: =VLOOKUP($A:$A,Variables_extraites!$A:$AD,24,FALSE) -> 15 | AQ23: =VLOOKUP($A:$A,Variables_extraites!$A:$AD,25,FALSE) -> 1 | AR23: =VLOOKUP($A:$A,Variables_extraites!$A:$AD,26,FALSE) -> 42668 | AS23: =VLOOKUP($A:$A,Variables_extraites!$A:$AD,27,FALSE) -> 15 | AT23: =VLOOKUP($A:$A,Variables_extraites!$A:$AD,28,FALSE) -> 36 | AU23: =VLOOKUP($A:$A,Variables_extraites!$A:$AD,29,FALSE) -> 1124 | AV23: =VLOOKUP($A:$A,Variables_extraites!$A:$AD,30,FALSE) -> NA
A24: 43 | B24: 43 | C24: 2 | D24: HFpEF | E24: 10394 | F24: YES | G24: YES | H24: 72 | I24: 15.22192 | J24: 1 | K24: 3 | L24: 0 | M24: 40 | N24: 56.82 | O24: 353.54088 | P24: 2219 | Q24: 16 | R24: 46.572799 | S24: 9.5530726 | T24: 40 | U24: -14.14 | X24: 68.3847 | Y24: =VLOOKUP($A:$A,Variables_extraites!$A:$AD,7,FALSE) -> 1 | Z24: =VLOOKUP($A:$A,Variables_extraites!$A:$AD,8,FALSE) -> 0 | AA24: =VLOOKUP($A:$A,Variables_extraites!$A:$AD,9,FALSE) -> 15.3 | AB24: =VLOOKUP($A:$A,Variables_extraites!$A:$AD,10,FALSE) -> 0 | AC24: =VLOOKUP($A:$A,Variables_extraites!$A:$AD,11,FALSE) -> 0 | AD24: =VLOOKUP($A:$A,Variables_extraites!$A:$AD,12,FALSE) -> 1 | AE24: =VLOOKUP($A:$A,Variables_extraites!$A:$AD,13,FALSE) -> 65.261383 | AF24: =VLOOKUP($A:$A,Variables_extraites!$A:$AD,14,FALSE) -> NA | AG24: =VLOOKUP($A:$A,Variables_extraites!$A:$AD,15,FALSE) -> 14.333333 | AH24: =VLOOKUP($A:$A,Variables_extraites!$A:$AD,16,FALSE) -> 43 | AI24: =VLOOKUP($A:$A,Variables_extraites!$A:$AD,17,FALSE) -> 42242 | AJ24: =VLOOKUP($A:$A,Variables_extraites!$A:$AD,18,FALSE) -> 42695 | AK24: =VLOOKUP($A:$A,Variables_extraites!$A:$AD,19,FALSE) -> 1 | AL24: =VLOOKUP($A:$A,Variables_extraites!$A:$AD,20,FALSE) -> 42695 | AM24: =VLOOKUP($A:$A,Variables_extraites!$A:$AD,21,FALSE) -> 14 | AN24: =VLOOKUP($A:$A,Variables_extraites!$A:$AD,22,FALSE) -> 1 | AO24: =VLOOKUP($A:$A,Variables_extraites!$A:$AD,23,FALSE) -> 42382 | AP24: =VLOOKUP($A:$A,Variables_extraites!$A:$AD,24,FALSE) -> 4 | AQ24: =VLOOKUP($A:$A,Variables_extraites!$A:$AD,25,FALSE) -> 1 | AR24: =VLOOKUP($A:$A,Variables_extraites!$A:$AD,26,FALSE) -> 42382 | AS24: =VLOOKUP($A:$A,Variables_extraites!$A:$AD,27,FALSE) -> 4 | AT24: =VLOOKUP($A:$A,Variables_extraites!$A:$AD,28,FALSE) -> 14 | AU24: =VLOOKUP($A:$A,Variables_extraites!$A:$AD,29,FALSE) -> 453 | AV24: =VLOOKUP($A:$A,Variables_extraites!$A:$AD,30,FALSE) -> NA | AW24: 8.5597212 | AX24: 7.842916 | AY24: 5.3483741 | AZ24: 3.619413 | BA24: 7.6322682 | BB24: 7.7974021 | BC24: 8.6815547 | BD24: 7.9935612 | BE24: 6.2813273 | BF24: 0.94860085 | BG24: 6.3705131 | BH24: 6.9318012 | BI24: 7.9509349 | BJ24: 4.7473874 | BK24: 6.2785424 | BL24: 8.157448 | BM24: 6.7090149 | BN24: 7.0110036 | BO24: 6.0263574 | BP24: 6.1582562 | BQ24: 8.0001127 | BR24: -0.074000581 | BS24: 10.186919 | BT24: -0.97143085 | BU24: 4.2735159 | BV24: 6.5169607 | BW24: 3.5071603 | BX24: 10.802258 | BY24: 3.6724253 | BZ24: 4.9713136 | CA24: 5.0263574 | CB24: 5.8309442 | CC24: 4.3475165 | CD24: 11.15835
A25: 51 | B25: 51 | C25: 2 | D25: HFpEF | E25: 10336 | F25: YES | G25: YES | H25: 83 | I25: 27.555556 | J25: 1 | K25: 2 | L25: 0 | M25: 60 | N25: 53.3 | O25: 254.27693 | P25: 2091 | Q25: 49 | R25: 53.260756 | S25: 27.15625 | T25: 28 | U25: -14.9 | V25: 55.0203 | W25: 34.315961 | X25: 67.8122 | Y25: =VLOOKUP($A:$A,Variables_extraites!$A:$AD,7,FALSE) -> 0 | Z25: =VLOOKUP($A:$A,Variables_extraites!$A:$AD,8,FALSE) -> 0 | AA25: =VLOOKUP($A:$A,Variables_extraites!$A:$AD,9,FALSE) -> 13.4 | AB25: =VLOOKUP($A:$A,Variables_extraites!$A:$AD,10,FALSE) -> 1 | AC25: =VLOOKUP($A:$A,Variables_extraites!$A:$AD,11,FALSE) -> 0 | AD25: =VLOOKUP($A:$A,Variables_extraites!$A:$AD,12,FALSE) -> 1 | AE25: =VLOOKUP($A:$A,Variables_extraites!$A:$AD,13,FALSE) -> 68.408262 | AF25: =VLOOKUP($A:$A,Variables_extraites!$A:$AD,14,FALSE) -> 3.381323 | AG25: =VLOOKUP($A:$A,Variables_extraites!$A:$AD,15,FALSE) -> 15 | AH25: =VLOOKUP($A:$A,Variables_extraites!$A:$AD,16,FALSE) -> 51 | AI25: =VLOOKUP($A:$A,Variables_extraites!$A:$AD,17,FALSE) -> 42083 | AJ25: =VLOOKUP($A:$A,Variables_extraites!$A:$AD,18,FALSE) -> 43123 | AK25: =VLOOKUP($A:$A,Variables_extraites!$A:$AD,19,FALSE) -> 1 | AL25: =VLOOKUP($A:$A,Variables_extraites!$A:$AD,20,FALSE) -> 43123 | AM25: =VLOOKUP($A:$A,Variables_extraites!$A:$AD,21,FALSE) -> 34 | AN25: =VLOOKUP($A:$A,Variables_extraites!$A:$AD,22,FALSE) -> 1 | AO25: =VLOOKUP($A:$A,Variables_extraites!$A:$AD,23,FALSE) -> 43047 | AP25: =VLOOKUP($A:$A,Variables_extraites!$A:$AD,24,FALSE) -> 31 | AQ25: =VLOOKUP($A:$A,Variables_extraites!$A:$AD,25,FALSE) -> 1 | AR25: =VLOOKUP($A:$A,Variables_extraites!$A:$AD,26,FALSE) -> 43047 | AS25: =VLOOKUP($A:$A,Variables_extraites!$A:$AD,27,FALSE) -> 31 | AT25: =VLOOKUP($A:$A,Variables_extraites!$A:$AD,28,FALSE) -> 34 | AU25: =VLOOKUP($A:$A,Variables_extraites!$A:$AD,29,FALSE) -> 1040 | AV25: =VLOOKUP($A:$A,Variables_extraites!$A:$AD,30,FALSE) -> -27.42 | AW25: 8.7109442 | AX25: 7.6065903 | AY25: 5.1830895 | AZ25: 1.7655347 | BA25: 8.0924929 | BB25: 5.2861419 | BC25: 9.300467 | BD25: 7.3904269 | BE25: 5.8419731 | BF25: 1.275007 | BG25: 6.0723202 | BH25: 6.5902128 | BI25: 7.6022906 | BJ25: 4.1826923 | BK25: 5.9742999 | BL25: 6.9642831 | BM25: 6.2494453 | BN25: 6.5332519 | BO25: 5.6037747 | BP25: 6.5337191 | BQ25: 7.7499364 | BR25: 4.4679315 | BS25: 9.8487638 | BT25: 2.0356239 | BU25: 6.3717331 | BV25: 6.9411063 | BW25: 5.8534967 | BX25: 10.903129 | BY25: 3.3812834 | BZ25: 8.5050176 | CA25: 4.2257377 | CB25: 2.3981111 | CC25: 1.9038015 | CD25: 7.8131399
A26: 53 | B26: 53 | C26: 2 | D26: HFpEF | E26: 10395 | F26: YES | G26: YES | H26: 85 | I26: 26.233556 | J26: 1 | K26: 2 | L26: 0 | M26: 40 | N26: 47.05 | O26: 89.29229 | P26: 4906 | Q26: 49 | R26: 50.423989 | S26: 30.590164 | T26: 34 | U26: -12.97 | X26: 56.7487 | Y26: =VLOOKUP($A:$A,Variables_extraites!$A:$AD,7,FALSE) -> 0 | Z26: =VLOOKUP($A:$A,Variables_extraites!$A:$AD,8,FALSE) -> 0 | AA26: =VLOOKUP($A:$A,Variables_extraites!$A:$AD,9,FALSE) -> 13 | AB26: =VLOOKUP($A:$A,Variables_extraites!$A:$AD,10,FALSE) -> 1 | AC26: =VLOOKUP($A:$A,Variables_extraites!$A:$AD,11,FALSE) -> 1 | AD26: =VLOOKUP($A:$A,Variables_extraites!$A:$AD,12,FALSE) -> 1 | AE26: =VLOOKUP($A:$A,Variables_extraites!$A:$AD,13,FALSE) -> 47.010551 | AF26: =VLOOKUP($A:$A,Variables_extraites!$A:$AD,14,FALSE) -> 1.5245098 | AG26: =VLOOKUP($A:$A,Variables_extraites!$A:$AD,15,FALSE) -> 19 | AH26: =VLOOKUP($A:$A,Variables_extraites!$A:$AD,16,FALSE) -> 53 | AI26: =VLOOKUP($A:$A,Variables_extraites!$A:$AD,17,FALSE) -> 42080 | AJ26: =VLOOKUP($A:$A,Variables_extraites!$A:$AD,18,FALSE) -> 43231 | AK26: =VLOOKUP($A:$A,Variables_extraites!$A:$AD,19,FALSE) -> 0 | AL26: =VLOOKUP($A:$A,Variables_extraites!$A:$AD,20,FALSE) -> 43231 | AM26: =VLOOKUP($A:$A,Variables_extraites!$A:$AD,21,FALSE) -> 37 | AN26: =VLOOKUP($A:$A,Variables_extraites!$A:$AD,22,FALSE) -> 1 | AO26: =VLOOKUP($A:$A,Variables_extraites!$A:$AD,23,FALSE) -> 42214 | AP26: =VLOOKUP($A:$A,Variables_extraites!$A:$AD,24,FALSE) -> 4 | AQ26: =VLOOKUP($A:$A,Variables_extraites!$A:$AD,25,FALSE) -> 1 | AR26: =VLOOKUP($A:$A,Variables_extraites!$A:$AD,26,FALSE) -> 42214 | AS26: =VLOOKUP($A:$A,Variables_extraites!$A:$AD,27,FALSE) -> 4 | AT26: =VLOOKUP($A:$A,Variables_extraites!$A:$AD,28,FALSE) -> 37 | AU26: =VLOOKUP($A:$A,Variables_extraites!$A:$AD,29,FALSE) -> 1151 | AV26: =VLOOKUP($A:$A,Variables_extraites!$A:$AD,30,FALSE) -> -25.51 | AW26: 8.7030384 | AX26: 7.6678921 | AY26: 4.7532836 | AZ26: 1.5704629 | BA26: 8.0831602 | BB26: 4.9514013 | BC26: 9.1107182 | BD26: 7.6611368 | BE26: 6.1255685 | BF26: 1.1505597 | BG26: 6.0654431 | BH26: 6.4024152 | BI26: 7.5625477 | BJ26: 4.3603643 | BK26: 5.8081276 | BL26: 7.6564964 | BM26: 5.9231492 | BN26: 6.2414589 | BO26: 5.515069 | BP26: 5.7860736 | BQ26: 7.87621 | BR26: 3.7246503 | BS26: 9.8152872 | BT26: 1.5210507 | BU26: 5.6539199 | BV26: 7.2134445 | BW26: 5.3586072 | BX26: 10.611532 | BY26: 3.3812834 | BZ26: 8.2160183 | CA26: 4.5855635 | CB26: 2.3955138 | CC26: 1.9292696 | CD26: 8.2942365
A27: 54 | B27: 54 | C27: 2 | D27: HFpEF | E27: 10473 | F27: YES | G27: YES | H27: 75 | I27: 24.567474 | J27: 0 | K27: 4 | L27: 1 | M27: 39 | N27: 33.02 | O27: 769.16673 | P27: 1138 | Q27: 33 | R27: 29.604803 | S27: 16.618182 | T27: 36 | U27: -19.24 | V27: 46.137355 | W27: 42.478717 | X27: 51.2976 | Y27: =VLOOKUP($A:$A,Variables_extraites!$A:$AD,7,FALSE) -> 1 | Z27: =VLOOKUP($A:$A,Variables_extraites!$A:$AD,8,FALSE) -> 0 | AA27: =VLOOKUP($A:$A,Variables_extraites!$A:$AD,9,FALSE) -> 7.1 | AB27: =VLOOKUP($A:$A,Variables_extraites!$A:$AD,10,FALSE) -> 0 | AC27: =VLOOKUP($A:$A,Variables_extraites!$A:$AD,11,FALSE) -> 1 | AD27: =VLOOKUP($A:$A,Variables_extraites!$A:$AD,12,FALSE) -> 1 | AE27: =VLOOKUP($A:$A,Variables_extraites!$A:$AD,13,FALSE) -> 59.315403 | AF27: =VLOOKUP($A:$A,Variables_extraites!$A:$AD,14,FALSE) -> 0.93360572 | AG27: =VLOOKUP($A:$A,Variables_extraites!$A:$AD,15,FALSE) -> 22 | AH27: =VLOOKUP($A:$A,Variables_extraites!$A:$AD,16,FALSE) -> 54 | AI27: =VLOOKUP($A:$A,Variables_extraites!$A:$AD,17,FALSE) -> 42317 | AJ27: =VLOOKUP($A:$A,Variables_extraites!$A:$AD,18,FALSE) -> 43052 | AK27: =VLOOKUP($A:$A,Variables_extraites!$A:$AD,19,FALSE) -> 0 | AL27: =VLOOKUP($A:$A,Variables_extraites!$A:$AD,20,FALSE) -> 43052 | AM27: =VLOOKUP($A:$A,Variables_extraites!$A:$AD,21,FALSE) -> 24 | AN27: =VLOOKUP($A:$A,Variables_extraites!$A:$AD,22,FALSE) -> 1 | AO27: =VLOOKUP($A:$A,Variables_extraites!$A:$AD,23,FALSE) -> 42460 | AP27: =VLOOKUP($A:$A,Variables_extraites!$A:$AD,24,FALSE) -> 4 | AQ27: =VLOOKUP($A:$A,Variables_extraites!$A:$AD,25,FALSE) -> 1 | AR27: =VLOOKUP($A:$A,Variables_extraites!$A:$AD,26,FALSE) -> 42460 | AS27: =VLOOKUP($A:$A,Variables_extraites!$A:$AD,27,FALSE) -> 4 | AT27: =VLOOKUP($A:$A,Variables_extraites!$A:$AD,28,FALSE) -> 24.16 | AU27: =VLOOKUP($A:$A,Variables_extraites!$A:$AD,29,FALSE) -> 735 | AV27: =VLOOKUP($A:$A,Variables_extraites!$A:$AD,30,FALSE) -> -28.39 | AW27: 8.928992 | AX27: 7.8922089 | AY27: 5.6920924 | AZ27: 3.3715589 | BA27: 8.1897257 | BB27: 7.3421636 | BC27: 9.3118164 | BD27: 7.8661043 | BE27: 6.6660464 | BF27: 1.4114262 | BG27: 7.5107246 | BH27: 7.8073549 | BI27: 8.7130084 | BJ27: 5.5930549 | BK27: 6.7213727 | BL27: 8.3791184 | BM27: 6.8050344 | BN27: 7.4813958 | BO27: 5.3387809 | BP27: 6.9623177 | BQ27: 8.6499028 | BR27: 3.8529976 | BS27: 10.407172 | BT27: 2.5728897 | BU27: 4.6971066 | BV27: 6.0236989 | BW27: 4.3729521 | BX27: 10.408128 | BY27: 2.6667566 | BZ27: 8.3030044 | CA27: 4.2479275 | CB27: 2.1051236 | CC27: 0.84410899 | CD27: 7.8342825
A28: 55 | B28: 55 | C28: 2 | D28: HFpEF | E28: 10606 | F28: YES | G28: YES | H28: 84 | I28: 36.289737 | J28: 0 | K28: 0 | L28: 1 | M28: 47 | N28: 23.45 | O28: 99.892854 | P28: 858.8 | Q28: 47 | R28: 42.635369 | S28: 24.3 | T28: 29 | U28: -10.18 | V28: 98.073427 | W28: 23.53314 | X28: 141.4115 | Y28: =VLOOKUP($A:$A,Variables_extraites!$A:$AD,7,FALSE) -> 0 | Z28: =VLOOKUP($A:$A,Variables_extraites!$A:$AD,8,FALSE) -> 1 | AA28: =VLOOKUP($A:$A,Variables_extraites!$A:$AD,9,FALSE) -> 11.5 | AB28: =VLOOKUP($A:$A,Variables_extraites!$A:$AD,10,FALSE) -> 1 | AC28: =VLOOKUP($A:$A,Variables_extraites!$A:$AD,11,FALSE) -> 1 | AD28: =VLOOKUP($A:$A,Variables_extraites!$A:$AD,12,FALSE) -> 0 | AE28: =VLOOKUP($A:$A,Variables_extraites!$A:$AD,13,FALSE) -> 60.322279 | AF28: =VLOOKUP($A:$A,Variables_extraites!$A:$AD,14,FALSE) -> 2.8928571 | AG28: =VLOOKUP($A:$A,Variables_extraites!$A:$AD,15,FALSE) -> 18 | AH28: =VLOOKUP($A:$A,Variables_extraites!$A:$AD,16,FALSE) -> 55 | AI28: =VLOOKUP($A:$A,Variables_extraites!$A:$AD,17,FALSE) -> 42101 | AJ28: =VLOOKUP($A:$A,Variables_extraites!$A:$AD,18,FALSE) -> 43482 | AK28: =VLOOKUP($A:$A,Variables_extraites!$A:$AD,19,FALSE) -> 0 | AL28: =VLOOKUP($A:$A,Variables_extraites!$A:$AD,20,FALSE) -> 43482 | AM28: =VLOOKUP($A:$A,Variables_extraites!$A:$AD,21,FALSE) -> 45 | AN28: =VLOOKUP($A:$A,Variables_extraites!$A:$AD,22,FALSE) -> 0 | AO28: =VLOOKUP($A:$A,Variables_extraites!$A:$AD,23,FALSE) -> 43482 | AP28: =VLOOKUP($A:$A,Variables_extraites!$A:$AD,24,FALSE) -> 45 | AQ28: =VLOOKUP($A:$A,Variables_extraites!$A:$AD,25,FALSE) -> 0 | AR28: =VLOOKUP($A:$A,Variables_extraites!$A:$AD,26,FALSE) -> 43482 | AS28: =VLOOKUP($A:$A,Variables_extraites!$A:$AD,27,FALSE) -> 45 | AT28: =VLOOKUP($A:$A,Variables_extraites!$A:$AD,28,FALSE) -> 45 | AU28: =VLOOKUP($A:$A,Variables_extraites!$A:$AD,29,FALSE) -> 1381 | AV28: =VLOOKUP($A:$A,Variables_extraites!$A:$AD,30,FALSE) -> -16.46 | AW28: 9.0652276 | AX28: 7.6005076 | AY28: 5.197315 | AZ28: 3.5372961 | BA28: 8.0177549 | BB28: 7.0113391 | BC28: 8.8043247 | BD28: 7.7268993 | BE28: 6.1009776 | BF28: 1.0071955 | BG28: 6.1346317 | BH28: 6.6550656 | BI28: 7.7644736 | BJ28: 5.006298 | BK28: 6.6756748 | BL28: 7.5221499 | BM28: 6.7247867 | BN28: 7.2890045 | BO28: 6.1531973 | BP28: 6.4852658 | BQ28: 7.8628233 | BR28: -1.9378783 | BS28: 11.584211 | BT28: 2.4249221 | BU28: 6.2301646 | BV28: 6.6295023 | BW28: 4.3701643 | BX28: 11.749752 | BY28: 3.3645724 | BZ28: 7.5223854 | CA28: 4.4620523 | CB28: 4.2273668 | CC28: 8.1680429 | CD28: 9.1592888
A29: 57 | B29: 57 | C29: 2 | D29: HFpEF | E29: 10301 | F29: YES | G29: YES | H29: 65 | I29: 30.22435 | J29: 1 | K29: 2 | L29: 1 | M29: 33 | N29: 57.99 | O29: 268.0491 | P29: 529.8 | Q29: 47 | R29: 38.053209 | S29: 16.354167 | T29: 47 | U29: -13.67 | X29: 76.4554 | Y29: =VLOOKUP($A:$A,Variables_extraites!$A:$AD,7,FALSE) -> 0 | Z29: =VLOOKUP($A:$A,Variables_extraites!$A:$AD,8,FALSE) -> 0 | AA29: =VLOOKUP($A:$A,Variables_extraites!$A:$AD,9,FALSE) -> 9.8 | AB29: =VLOOKUP($A:$A,Variables_extraites!$A:$AD,10,FALSE) -> 1 | AC29: =VLOOKUP($A:$A,Variables_extraites!$A:$AD,11,FALSE) -> 0 | AD29: =VLOOKUP($A:$A,Variables_extraites!$A:$AD,12,FALSE) -> 1 | AE29: =VLOOKUP($A:$A,Variables_extraites!$A:$AD,13,FALSE) -> 50.08547 | AF29: =VLOOKUP($A:$A,Variables_extraites!$A:$AD,14,FALSE) -> 1.3018242 | AG29: =VLOOKUP($A:$A,Variables_extraites!$A:$AD,15,FALSE) -> 14 | AH29: =VLOOKUP($A:$A,Variables_extraites!$A:$AD,16,FALSE) -> 57 | AI29: =VLOOKUP($A:$A,Variables_extraites!$A:$AD,17,FALSE) -> 42185 | AJ29: =VLOOKUP($A:$A,Variables_extraites!$A:$AD,18,FALSE) -> 42656 | AK29: =VLOOKUP($A:$A,Variables_extraites!$A:$AD,19,FALSE) -> 1 | AL29: =VLOOKUP($A:$A,Variables_extraites!$A:$AD,20,FALSE) -> 42656 | AM29: =VLOOKUP($A:$A,Variables_extraites!$A:$AD,21,FALSE) -> 15 | AN29: =VLOOKUP($A:$A,Variables_extraites!$A:$AD,22,FALSE) -> 1 | AO29: =VLOOKUP($A:$A,Variables_extraites!$A:$AD,23,FALSE) -> 42569 | AP29: =VLOOKUP($A:$A,Variables_extraites!$A:$AD,24,FALSE) -> 12 | AQ29: =VLOOKUP($A:$A,Variables_extraites!$A:$AD,25,FALSE) -> 1 | AR29: =VLOOKUP($A:$A,Variables_extraites!$A:$AD,26,FALSE) -> 42569 | AS29: =VLOOKUP($A:$A,Variables_extraites!$A:$AD,27,FALSE) -> 12 | AT29: =VLOOKUP($A:$A,Variables_extraites!$A:$AD,28,FALSE) -> 15 | AU29: =VLOOKUP($A:$A,Variables_extraites!$A:$AD,29,FALSE) -> 471 | AV29: =VLOOKUP($A:$A,Variables_extraites!$A:$AD,30,FALSE) -> -17.02 | AW29: 8.1565888 | AX29: 7.5164092 | AY29: 5.4356286 | AZ29: 0.81885056 | BA29: 8.4928546 | BB29: 6.2622828 | BC29: 8.7940259 | BD29: 7.53683 | BE29: 6.0112273 | BF29: 1.5410192 | BG29: 5.8402114 | BH29: 6.4996865 | BI29: 7.840715 | BJ29: 4.0967679 | BK29: 6.2353441 | BL29: 8.0559331 | BM29: 6.0386996 | BN29: 6.6745454 | BO29: 6.0957135 | BP29: 6.4679315 | BQ29: 7.8325736 | BR29: 3.6587827 | BS29: 9.5616698 | BT29: 1.0426443 | BU29: 4.1473067 | BV29: 5.680043 | BW29: 5.383013 | BX29: 10.462809 | BY29: 3.3504972 | BZ29: 8.0497941 | CA29: 4.2772409 | CB29: 2.4130149 | CC29: 0.48852396 | CD29: 8.5190255
A30: 58 | B30: 58 | C30: 2 | D30: HFpEF | E30: 10366 | F30: YES | G30: YES | H30: 65 | I30: 38.541117 | J30: 1 | K30: 2 | L30: 1 | M30: 45 | N30: 44.53 | O30: 336.66772 | P30: 526.5 | Q30: 6 | R30: 31.747597 | S30: 17.277778 | T30: 35 | U30: -19.3 | V30: 59.654876 | W30: 27.565082 | X30: 59.6186 | Y30: =VLOOKUP($A:$A,Variables_extraites!$A:$AD,7,FALSE) -> 0 | Z30: =VLOOKUP($A:$A,Variables_extraites!$A:$AD,8,FALSE) -> 0 | AA30: =VLOOKUP($A:$A,Variables_extraites!$A:$AD,9,FALSE) -> 11.6 | AB30: =VLOOKUP($A:$A,Variables_extraites!$A:$AD,10,FALSE) -> 1 | AC30: =VLOOKUP($A:$A,Variables_extraites!$A:$AD,11,FALSE) -> 0 | AD30: =VLOOKUP($A:$A,Variables_extraites!$A:$AD,12,FALSE) -> 0 | AE30: =VLOOKUP($A:$A,Variables_extraites!$A:$AD,13,FALSE) -> 63.368221 | AF30: =VLOOKUP($A:$A,Variables_extraites!$A:$AD,14,FALSE) -> 1.8772636 | AG30: =VLOOKUP($A:$A,Variables_extraites!$A:$AD,15,FALSE) -> 25 | AH30: =VLOOKUP($A:$A,Variables_extraites!$A:$AD,16,FALSE) -> 58 | AI30: =VLOOKUP($A:$A,Variables_extraites!$A:$AD,17,FALSE) -> 42289 | AJ30: =VLOOKUP($A:$A,Variables_extraites!$A:$AD,18,FALSE) -> 43395 | AK30: =VLOOKUP($A:$A,Variables_extraites!$A:$AD,19,FALSE) -> 0 | AL30: =VLOOKUP($A:$A,Variables_extraites!$A:$AD,20,FALSE) -> 43395 | AM30: =VLOOKUP($A:$A,Variables_extraites!$A:$AD,21,FALSE) -> 36 | AN30: =VLOOKUP($A:$A,Variables_extraites!$A:$AD,22,FALSE) -> 0 | AO30: =VLOOKUP($A:$A,Variables_extraites!$A:$AD,23,FALSE) -> 43395 | AP30: =VLOOKUP($A:$A,Variables_extraites!$A:$AD,24,FALSE) -> 36 | AQ30: =VLOOKUP($A:$A,Variables_extraites!$A:$AD,25,FALSE) -> 0 | AR30: =VLOOKUP($A:$A,Variables_extraites!$A:$AD,26,FALSE) -> 43395 | AS30: =VLOOKUP($A:$A,Variables_extraites!$A:$AD,27,FALSE) -> 36 | AT30: =VLOOKUP($A:$A,Variables_extraites!$A:$AD,28,FALSE) -> 36 | AU30: =VLOOKUP($A:$A,Variables_extraites!$A:$AD,29,FALSE) -> 1106 | AV30: =VLOOKUP($A:$A,Variables_extraites!$A:$AD,30,FALSE) -> -24.88 | AW30: 9.2378792 | AX30: 8.0083726 | AY30: 5.3981451 | AZ30: 0.81885056 | BA30: 7.3956627 | BB30: 7.6114675 | BC30: 8.9602916 | BD30: 8.1895775 | BE30: 6.3348543 | BF30: 1.4802651 | BG30: 6.2809563 | BH30: 6.7596885 | BI30: 7.6186057 | BJ30: 4.5945485 | BK30: 5.9493015 | BL30: 8.7229783 | BM30: 6.655638 | BN30: 7.3969472 | BO30: 5.5351198 | BP30: 6.0988743 | BQ30: 8.1040745 | BR30: 0.98550043 | BS30: 9.6549224 | BT30: 0.36737107 | BU30: 4.0487593 | BV30: 6.3097946 | BW30: 4.0942361 | BX30: 10.67919 | BY30: 3.2418402 | BZ30: 6.691255 | CA30: 4.4515408 | CB30: 3.9879348 | CC30: 3.0632589 | CD30: 9.2875513
A31: 59 | B31: 59 | C31: 2 | D31: HFpEF | E31: 10396 | F31: YES | H31: 69 | I31: 17.709563 | J31: 1 | K31: 3 | L31: 0 | M31: 26 | N31: 119.42 | O31: 6765.9672 | P31: 9352 | Q31: 48 | R31: 27.806194 | S31: 38.933333 | T31: 32 | U31: -16.06 | V31: 55.550958 | W31: 46.478913 | X31: 37.2557 | Y31: =VLOOKUP($A:$A,Variables_extraites!$A:$AD,7,FALSE) -> 0 | Z31: =VLOOKUP($A:$A,Variables_extraites!$A:$AD,8,FALSE) -> 0 | AA31: =VLOOKUP($A:$A,Variables_extraites!$A:$AD,9,FALSE) -> 9.2 | AB31: =VLOOKUP($A:$A,Variables_extraites!$A:$AD,10,FALSE) -> 1 | AC31: =VLOOKUP($A:$A,Variables_extraites!$A:$AD,11,FALSE) -> 0 | AD31: =VLOOKUP($A:$A,Variables_extraites!$A:$AD,12,FALSE) -> 0 | AE31: =VLOOKUP($A:$A,Variables_extraites!$A:$AD,13,FALSE) -> 49.640288 | AF31: =VLOOKUP($A:$A,Variables_extraites!$A:$AD,14,FALSE) -> 2.162963 | AG31: =VLOOKUP($A:$A,Variables_extraites!$A:$AD,15,FALSE) -> 11 | AH31: =VLOOKUP($A:$A,Variables_extraites!$A:$AD,16,FALSE) -> 59 | AI31: =VLOOKUP($A:$A,Variables_extraites!$A:$AD,17,FALSE) -> 42171 | AJ31: =VLOOKUP($A:$A,Variables_extraites!$A:$AD,18,FALSE) -> 42320 | AK31: =VLOOKUP($A:$A,Variables_extraites!$A:$AD,19,FALSE) -> 1 | AL31: =VLOOKUP($A:$A,Variables_extraites!$A:$AD,20,FALSE) -> 42320 | AM31: =VLOOKUP($A:$A,Variables_extraites!$A:$AD,21,FALSE) -> 4 | AN31: =VLOOKUP($A:$A,Variables_extraites!$A:$AD,22,FALSE) -> 1 | AO31: =VLOOKUP($A:$A,Variables_extraites!$A:$AD,23,FALSE) -> 42318 | AP31: =VLOOKUP($A:$A,Variables_extraites!$A:$AD,24,FALSE) -> 4 | AQ31: =VLOOKUP($A:$A,Variables_extraites!$A:$AD,25,FALSE) -> 1 | AR31: =VLOOKUP($A:$A,Variables_extraites!$A:$AD,26,FALSE) -> 42318 | AS31: =VLOOKUP($A:$A,Variables_extraites!$A:$AD,27,FALSE) -> 4 | AT31: =VLOOKUP($A:$A,Variables_extraites!$A:$AD,28,FALSE) -> 4 | AU31: =VLOOKUP($A:$A,Variables_extraites!$A:$AD,29,FALSE) -> 149 | AV31: =VLOOKUP($A:$A,Variables_extraites!$A:$AD,30,FALSE) -> NA
A32: 62 | B32: 62 | C32: 2 | D32: HFpEF | E32: 10649 | F32: YES | H32: 68 | I32: 24.03461 | J32: 0 | K32: 2 | L32: 0 | M32: 34 | N32: 25.18 | O32: 124.69139 | P32: 4233 | Q32: 32 | R32: 40.501769 | S32: 14.547872 | T32: 26.666667 | U32: -16.476667 | V32: 49.149613 | W32: 31.546303 | X32: 57.8434 | Y32: =VLOOKUP($A:$A,Variables_extraites!$A:$AD,7,FALSE) -> 1 | Z32: =VLOOKUP($A:$A,Variables_extraites!$A:$AD,8,FALSE) -> 0 | AA32: =VLOOKUP($A:$A,Variables_extraites!$A:$AD,9,FALSE) -> 13 | AB32: =VLOOKUP($A:$A,Variables_extraites!$A:$AD,10,FALSE) -> 1 | AC32: =VLOOKUP($A:$A,Variables_extraites!$A:$AD,11,FALSE) -> 1 | AD32: =VLOOKUP($A:$A,Variables_extraites!$A:$AD,12,FALSE) -> 1 | AE32: =VLOOKUP($A:$A,Variables_extraites!$A:$AD,13,FALSE) -> 61.059766 | AF32: =VLOOKUP($A:$A,Variables_extraites!$A:$AD,14,FALSE) -> NA | AG32: =VLOOKUP($A:$A,Variables_extraites!$A:$AD,15,FALSE) -> 20 | AH32: =VLOOKUP($A:$A,Variables_extraites!$A:$AD,16,FALSE) -> 62 | AI32: =VLOOKUP($A:$A,Variables_extraites!$A:$AD,17,FALSE) -> 42381 | AJ32: =VLOOKUP($A:$A,Variables_extraites!$A:$AD,18,FALSE) -> 43011 | AK32: =VLOOKUP($A:$A,Variables_extraites!$A:$AD,19,FALSE) -> 1 | AL32: =VLOOKUP($A:$A,Variables_extraites!$A:$AD,20,FALSE) -> 43011 | AM32: =VLOOKUP($A:$A,Variables_extraites!$A:$AD,21,FALSE) -> 20 | AN32: =VLOOKUP($A:$A,Variables_extraites!$A:$AD,22,FALSE) -> 0 | AO32: =VLOOKUP($A:$A,Variables_extraites!$A:$AD,23,FALSE) -> 43011 | AP32: =VLOOKUP($A:$A,Variables_extraites!$A:$AD,24,FALSE) -> 20 | AQ32: =VLOOKUP($A:$A,Variables_extraites!$A:$AD,25,FALSE) -> 1 | AR32: =VLOOKUP($A:$A,Variables_extraites!$A:$AD,26,FALSE) -> 43011 | AS32: =VLOOKUP($A:$A,Variables_extraites!$A:$AD,27,FALSE) -> 20 | AT32: =VLOOKUP($A:$A,Variables_extraites!$A:$AD,28,FALSE) -> 20 | AU32: =VLOOKUP($A:$A,Variables_extraites!$A:$AD,29,FALSE) -> 630 | AV32: =VLOOKUP($A:$A,Variables_extraites!$A:$AD,30,FALSE) -> -24
A33: 64 | B33: 64 | C33: 2 | D33: HFpEF | E33: 10398 | F33: YES | H33: 80 | I33: 20 | J33: 1 | K33: 2 | L33: 1 | M33: 53 | N33: 250 | O33: 3294.4008 | P33: 1218 | Q33: 40 | R33: 100.6373 | S33: 19.691358 | T33: 9 | U33: -16.906667 | V33: 52.871503 | W33: 47.11105 | X33: 35.3587 | Y33: =VLOOKUP($A:$A,Variables_extraites!$A:$AD,7,FALSE) -> 0 | Z33: =VLOOKUP($A:$A,Variables_extraites!$A:$AD,8,FALSE) -> 0 | AA33: =VLOOKUP($A:$A,Variables_extraites!$A:$AD,9,FALSE) -> 12.4 | AB33: =VLOOKUP($A:$A,Variables_extraites!$A:$AD,10,FALSE) -> 1 | AC33: =VLOOKUP($A:$A,Variables_extraites!$A:$AD,11,FALSE) -> 0 | AD33: =VLOOKUP($A:$A,Variables_extraites!$A:$AD,12,FALSE) -> 1 | AE33: =VLOOKUP($A:$A,Variables_extraites!$A:$AD,13,FALSE) -> 70.341207 | AF33: =VLOOKUP($A:$A,Variables_extraites!$A:$AD,14,FALSE) -> NA | AG33: =VLOOKUP($A:$A,Variables_extraites!$A:$AD,15,FALSE) -> 15 | AH33: =VLOOKUP($A:$A,Variables_extraites!$A:$AD,16,FALSE) -> 64 | AI33: =VLOOKUP($A:$A,Variables_extraites!$A:$AD,17,FALSE) -> 42317 | AJ33: =VLOOKUP($A:$A,Variables_extraites!$A:$AD,18,FALSE) -> 43061 | AK33: =VLOOKUP($A:$A,Variables_extraites!$A:$AD,19,FALSE) -> 0 | AL33: =VLOOKUP($A:$A,Variables_extraites!$A:$AD,20,FALSE) -> 43061 | AM33: =VLOOKUP($A:$A,Variables_extraites!$A:$AD,21,FALSE) -> 24 | AN33: =VLOOKUP($A:$A,Variables_extraites!$A:$AD,22,FALSE) -> 1 | AO33: =VLOOKUP($A:$A,Variables_extraites!$A:$AD,23,FALSE) -> 42731 | AP33: =VLOOKUP($A:$A,Variables_extraites!$A:$AD,24,FALSE) -> 14 | AQ33: =VLOOKUP($A:$A,Variables_extraites!$A:$AD,25,FALSE) -> 1 | AR33: =VLOOKUP($A:$A,Variables_extraites!$A:$AD,26,FALSE) -> 42731 | AS33: =VLOOKUP($A:$A,Variables_extraites!$A:$AD,27,FALSE) -> 14 | AT33: =VLOOKUP($A:$A,Variables_extraites!$A:$AD,28,FALSE) -> 24.46 | AU33: =VLOOKUP($A:$A,Variables_extraites!$A:$AD,29,FALSE) -> 744 | AV33: =VLOOKUP($A:$A,Variables_extraites!$A:$AD,30,FALSE) -> -18.25
A34: 66 | B34: 66 | C34: 2 | D34: HFpEF | E34: 10648 | F34: YES | H34: 79 | I34: 29.411765 | J34: 0 | K34: 2 | L34: 0 | M34: 87 | N34: 75.14 | O34: 180.14306 | P34: 727.1 | Q34: 25 | R34: 61.438741 | S34: 14.411765 | T34: 18 | U34: -11.3 | V34: 60.039515 | W34: 27.78764 | X34: 54.8559 | Y34: =VLOOKUP($A:$A,Variables_extraites!$A:$AD,7,FALSE) -> 0 | Z34: =VLOOKUP($A:$A,Variables_extraites!$A:$AD,8,FALSE) -> 0 | AA34: =VLOOKUP($A:$A,Variables_extraites!$A:$AD,9,FALSE) -> NA | AB34: =VLOOKUP($A:$A,Variables_extraites!$A:$AD,10,FALSE) -> 0 | AC34: =VLOOKUP($A:$A,Variables_extraites!$A:$AD,11,FALSE) -> 1 | AD34: =VLOOKUP($A:$A,Variables_extraites!$A:$AD,12,FALSE) -> 1 | AE34: =VLOOKUP($A:$A,Variables_extraites!$A:$AD,13,FALSE) -> 51.112706 | AF34: =VLOOKUP($A:$A,Variables_extraites!$A:$AD,14,FALSE) -> NA | AG34: =VLOOKUP($A:$A,Variables_extraites!$A:$AD,15,FALSE) -> 12 | AH34: =VLOOKUP($A:$A,Variables_extraites!$A:$AD,16,FALSE) -> 66 | AI34: =VLOOKUP($A:$A,Variables_extraites!$A:$AD,17,FALSE) -> 42247 | AJ34: =VLOOKUP($A:$A,Variables_extraites!$A:$AD,18,FALSE) -> 43517 | AK34: =VLOOKUP($A:$A,Variables_extraites!$A:$AD,19,FALSE) -> 0 | AL34: =VLOOKUP($A:$A,Variables_extraites!$A:$AD,20,FALSE) -> 43517 | AM34: =VLOOKUP($A:$A,Variables_extraites!$A:$AD,21,FALSE) -> 41 | AN34: =VLOOKUP($A:$A,Variables_extraites!$A:$AD,22,FALSE) -> 0 | AO34: =VLOOKUP($A:$A,Variables_extraites!$A:$AD,23,FALSE) -> 43517 | AP34: =VLOOKUP($A:$A,Variables_extraites!$A:$AD,24,FALSE) -> 41 | AQ34: =VLOOKUP($A:$A,Variables_extraites!$A:$AD,25,FALSE) -> 0 | AR34: =VLOOKUP($A:$A,Variables_extraites!$A:$AD,26,FALSE) -> 43517 | AS34: =VLOOKUP($A:$A,Variables_extraites!$A:$AD,27,FALSE) -> 41 | AT34: =VLOOKUP($A:$A,Variables_extraites!$A:$AD,28,FALSE) -> 41 | AU34: =VLOOKUP($A:$A,Variables_extraites!$A:$AD,29,FALSE) -> 1270 | AV34: =VLOOKUP($A:$A,Variables_extraites!$A:$AD,30,FALSE) -> -15.226667
A35: 67 | B35: 67 | C35: 2 | D35: HFpEF | E35: 10433 | F35: YES | H35: 83 | I35: 28.604765 | J35: 1 | K35: 2 | L35: 1 | M35: 41 | N35: 73.76 | O35: 5076.6272 | P35: 1013 | Q35: 35 | R35: 61.475125 | S35: 7.9322034 | T35: 39 | U35: -21.35 | V35: 51.893561 | W35: 31.976252 | X35: 59.8949 | Y35: =VLOOKUP($A:$A,Variables_extraites!$A:$AD,7,FALSE) -> 0 | Z35: =VLOOKUP($A:$A,Variables_extraites!$A:$AD,8,FALSE) -> 0 | AA35: =VLOOKUP($A:$A,Variables_extraites!$A:$AD,9,FALSE) -> 12.4 | AB35: =VLOOKUP($A:$A,Variables_extraites!$A:$AD,10,FALSE) -> 1 | AC35: =VLOOKUP($A:$A,Variables_extraites!$A:$AD,11,FALSE) -> 0 | AD35: =VLOOKUP($A:$A,Variables_extraites!$A:$AD,12,FALSE) -> 1 | AE35: =VLOOKUP($A:$A,Variables_extraites!$A:$AD,13,FALSE) -> 69.622246 | AF35: =VLOOKUP($A:$A,Variables_extraites!$A:$AD,14,FALSE) -> 1.1386861 | AG35: =VLOOKUP($A:$A,Variables_extraites!$A:$AD,15,FALSE) -> 25 | AH35: =VLOOKUP($A:$A,Variables_extraites!$A:$AD,16,FALSE) -> 67 | AI35: =VLOOKUP($A:$A,Variables_extraites!$A:$AD,17,FALSE) -> 42166 | AJ35: =VLOOKUP($A:$A,Variables_extraites!$A:$AD,18,FALSE) -> 43039 | AK35: =VLOOKUP($A:$A,Variables_extraites!$A:$AD,19,FALSE) -> 1 | AL35: =VLOOKUP($A:$A,Variables_extraites!$A:$AD,20,FALSE) -> 43039 | AM35: =VLOOKUP($A:$A,Variables_extraites!$A:$AD,21,FALSE) -> 28 | AN35: =VLOOKUP($A:$A,Variables_extraites!$A:$AD,22,FALSE) -> 1 | AO35: =VLOOKUP($A:$A,Variables_extraites!$A:$AD,23,FALSE) -> 42595 | AP35: =VLOOKUP($A:$A,Variables_extraites!$A:$AD,24,FALSE) -> 14 | AQ35: =VLOOKUP($A:$A,Variables_extraites!$A:$AD,25,FALSE) -> 1 | AR35: =VLOOKUP($A:$A,Variables_extraites!$A:$AD,26,FALSE) -> 42595 | AS35: =VLOOKUP($A:$A,Variables_extraites!$A:$AD,27,FALSE) -> 14 | AT35: =VLOOKUP($A:$A,Variables_extraites!$A:$AD,28,FALSE) -> 28 | AU35: =VLOOKUP($A:$A,Variables_extraites!$A:$AD,29,FALSE) -> 873 | AV35: =VLOOKUP($A:$A,Variables_extraites!$A:$AD,30,FALSE) -> -22.69
A36: 69 | B36: 69 | C36: 2 | D36: HFpEF | E36: 10644 | F36: YES | G36: YES | H36: 75 | I36: 27.76343 | J36: 0 | K36: 0 | L36: 0 | M36: 44 | N36: 86.71 | O36: 73.187722 | P36: 533.4 | Q36: 21 | R36: 55.197188 | S36: 14.377358 | T36: 22 | U36: -17.1 | V36: 61.873339 | W36: 26.945589 | X36: 81.3406 | Y36: =VLOOKUP($A:$A,Variables_extraites!$A:$AD,7,FALSE) -> 0 | Z36: =VLOOKUP($A:$A,Variables_extraites!$A:$AD,8,FALSE) -> 0 | AA36: =VLOOKUP($A:$A,Variables_extraites!$A:$AD,9,FALSE) -> 16.6 | AB36: =VLOOKUP($A:$A,Variables_extraites!$A:$AD,10,FALSE) -> 0 | AC36: =VLOOKUP($A:$A,Variables_extraites!$A:$AD,11,FALSE) -> 0 | AD36: =VLOOKUP($A:$A,Variables_extraites!$A:$AD,12,FALSE) -> 1 | AE36: =VLOOKUP($A:$A,Variables_extraites!$A:$AD,13,FALSE) -> 61.311953 | AF36: =VLOOKUP($A:$A,Variables_extraites!$A:$AD,14,FALSE) -> 2.0212202 | AG36: =VLOOKUP($A:$A,Variables_extraites!$A:$AD,15,FALSE) -> 29 | AH36: =VLOOKUP($A:$A,Variables_extraites!$A:$AD,16,FALSE) -> 69 | AI36: =VLOOKUP($A:$A,Variables_extraites!$A:$AD,17,FALSE) -> 42093 | AJ36: =VLOOKUP($A:$A,Variables_extraites!$A:$AD,18,FALSE) -> 43154 | AK36: =VLOOKUP($A:$A,Variables_extraites!$A:$AD,19,FALSE) -> 0 | AL36: =VLOOKUP($A:$A,Variables_extraites!$A:$AD,20,FALSE) -> 43154 | AM36: =VLOOKUP($A:$A,Variables_extraites!$A:$AD,21,FALSE) -> 34 | AN36: =VLOOKUP($A:$A,Variables_extraites!$A:$AD,22,FALSE) -> 0 | AO36: =VLOOKUP($A:$A,Variables_extraites!$A:$AD,23,FALSE) -> 43154 | AP36: =VLOOKUP($A:$A,Variables_extraites!$A:$AD,24,FALSE) -> 34 | AQ36: =VLOOKUP($A:$A,Variables_extraites!$A:$AD,25,FALSE) -> 0 | AR36: =VLOOKUP($A:$A,Variables_extraites!$A:$AD,26,FALSE) -> 43154 | AS36: =VLOOKUP($A:$A,Variables_extraites!$A:$AD,27,FALSE) -> 34 | AT36: =VLOOKUP($A:$A,Variables_extraites!$A:$AD,28,FALSE) -> 34 | AU36: =VLOOKUP($A:$A,Variables_extraites!$A:$AD,29,FALSE) -> 1061 | AV36: =VLOOKUP($A:$A,Variables_extraites!$A:$AD,30,FALSE) -> -27.22 | AW36: 8.2753796 | AX36: 7.8104431 | AY36: 5.1723275 | AZ36: 2.5260688 | BA36: 7.1602748 | BB36: 6.8563633 | BC36: 9.2410536 | BD36: 7.5451189 | BE36: 6.4170086 | BF36: 1.8599695 | BG36: 6.4180212 | BH36: 6.9804824 | BI36: 7.7715555 | BJ36: 4.457463 | BK36: 6.0467966 | BL36: 8.3626014 | BM36: 6.3724298 | BN36: 7.0003381 | BO36: 5.9380505 | BP36: 5.9733817 | BQ36: 8.2567748 | BR36: -1.9378783 | BS36: 10.359859 | BT36: 0.89530262 | BU36: 5.5619371 | BV36: 6.5245025 | BW36: 3.7344387 | BX36: 9.9778094 | BY36: 2.8439838 | BZ36: 5.7535511 | CA36: 4.0470148 | CB36: 4.2242583 | CC36: 7.4998153 | CD36: 9.4645567
A37: 70 | B37: 70 | C37: 2 | D37: HFpEF | E37: 10337 | F37: YES | G37: YES | H37: 73 | I37: 42.849723 | J37: 1 | K37: 3 | L37: 0 | M37: 61 | N37: 31.37 | O37: 71.496293 | P37: 448.6 | Q37: 18 | R37: 14.507246 | S37: 19.473684 | T37: 45 | U37: -15.9 | V37: 46.310549 | W37: 29.301986 | X37: 58.6558 | Y37: =VLOOKUP($A:$A,Variables_extraites!$A:$AD,7,FALSE) -> 0 | Z37: =VLOOKUP($A:$A,Variables_extraites!$A:$AD,8,FALSE) -> 0 | AA37: =VLOOKUP($A:$A,Variables_extraites!$A:$AD,9,FALSE) -> 13.3 | AB37: =VLOOKUP($A:$A,Variables_extraites!$A:$AD,10,FALSE) -> 1 | AC37: =VLOOKUP($A:$A,Variables_extraites!$A:$AD,11,FALSE) -> 0 | AD37: =VLOOKUP($A:$A,Variables_extraites!$A:$AD,12,FALSE) -> 0 | AE37: =VLOOKUP($A:$A,Variables_extraites!$A:$AD,13,FALSE) -> 60.757098 | AF37: =VLOOKUP($A:$A,Variables_extraites!$A:$AD,14,FALSE) -> 0.71153846 | AG37: =VLOOKUP($A:$A,Variables_extraites!$A:$AD,15,FALSE) -> 23 | AH37: =VLOOKUP($A:$A,Variables_extraites!$A:$AD,16,FALSE) -> 70 | AI37: =VLOOKUP($A:$A,Variables_extraites!$A:$AD,17,FALSE) -> 42268 | AJ37: =VLOOKUP($A:$A,Variables_extraites!$A:$AD,18,FALSE) -> 43269 | AK37: =VLOOKUP($A:$A,Variables_extraites!$A:$AD,19,FALSE) -> 0 | AL37: =VLOOKUP($A:$A,Variables_extraites!$A:$AD,20,FALSE) -> 43269 | AM37: =VLOOKUP($A:$A,Variables_extraites!$A:$AD,21,FALSE) -> 32 | AN37: =VLOOKUP($A:$A,Variables_extraites!$A:$AD,22,FALSE) -> 0 | AO37: =VLOOKUP($A:$A,Variables_extraites!$A:$AD,23,FALSE) -> 43269 | AP37: =VLOOKUP($A:$A,Variables_extraites!$A:$AD,24,FALSE) -> 32 | AQ37: =VLOOKUP($A:$A,Variables_extraites!$A:$AD,25,FALSE) -> 0 | AR37: =VLOOKUP($A:$A,Variables_extraites!$A:$AD,26,FALSE) -> 43269 | AS37: =VLOOKUP($A:$A,Variables_extraites!$A:$AD,27,FALSE) -> 32 | AT37: =VLOOKUP($A:$A,Variables_extraites!$A:$AD,28,FALSE) -> 32 | AU37: =VLOOKUP($A:$A,Variables_extraites!$A:$AD,29,FALSE) -> 1001 | AV37: =VLOOKUP($A:$A,Variables_extraites!$A:$AD,30,FALSE) -> -28.58 | AW37: 8.8919659 | AX37: 7.9992108 | AY37: 4.587965 | AZ37: 0.81885056 | BA37: 7.641546 | BB37: 7.4826063 | BC37: 8.6110248 | BD37: 7.4791335 | BE37: 6.0009014 | BF37: 1.4541759 | BG37: 6.4237462 | BH37: 6.8374387 | BI37: 7.7168537 | BJ37: 4.2218771 | BK37: 6.1199786 | BL37: 7.7330831 | BM37: 6.2605903 | BN37: 6.4073528 | BO37: 5.8828876 | BP37: 6.4287789 | BQ37: 8.0428085 | BR37: -0.029146346 | BS37: 11.481108 | BT37: 2.0461418 | BU37: 7.9008064 | BV37: 7.0394674 | BW37: 5.2207169 | BX37: 11.123721 | BY37: 3.3204847 | BZ37: 6.6948802 | CA37: 4.4282764 | CB37: 4.4288403 | CC37: 7.9299528 | CD37: 9.4349664
A38: 71 | B38: 71 | C38: 2 | D38: HFpEF | E38: 10434 | F38: YES | G38: YES | H38: 74 | I38: 36.363636 | J38: 1 | K38: 2 | L38: 1 | M38: 33 | N38: 42.48 | O38: 259.9702 | P38: 603.7 | Q38: 47 | R38: 32.528507 | S38: 19.583333 | T38: 45 | U38: -9.2666667 | V38: 65.574822 | W38: 33.593282 | X38: 84.6661 | Y38: =VLOOKUP($A:$A,Variables_extraites!$A:$AD,7,FALSE) -> 1 | Z38: =VLOOKUP($A:$A,Variables_extraites!$A:$AD,8,FALSE) -> 1 | AA38: =VLOOKUP($A:$A,Variables_extraites!$A:$AD,9,FALSE) -> 12.1 | AB38: =VLOOKUP($A:$A,Variables_extraites!$A:$AD,10,FALSE) -> 1 | AC38: =VLOOKUP($A:$A,Variables_extraites!$A:$AD,11,FALSE) -> 1 | AD38: =VLOOKUP($A:$A,Variables_extraites!$A:$AD,12,FALSE) -> 1 | AE38: =VLOOKUP($A:$A,Variables_extraites!$A:$AD,13,FALSE) -> 43.917214 | AF38: =VLOOKUP($A:$A,Variables_extraites!$A:$AD,14,FALSE) -> NA | AG38: =VLOOKUP($A:$A,Variables_extraites!$A:$AD,15,FALSE) -> 8 | AH38: =VLOOKUP($A:$A,Variables_extraites!$A:$AD,16,FALSE) -> 71 | AI38: =VLOOKUP($A:$A,Variables_extraites!$A:$AD,17,FALSE) -> 42312 | AJ38: =VLOOKUP($A:$A,Variables_extraites!$A:$AD,18,FALSE) -> 43446 | AK38: =VLOOKUP($A:$A,Variables_extraites!$A:$AD,19,FALSE) -> 0 | AL38: =VLOOKUP($A:$A,Variables_extraites!$A:$AD,20,FALSE) -> 43446 | AM38: =VLOOKUP($A:$A,Variables_extraites!$A:$AD,21,FALSE) -> 37 | AN38: =VLOOKUP($A:$A,Variables_extraites!$A:$AD,22,FALSE) -> 1 | AO38: =VLOOKUP($A:$A,Variables_extraites!$A:$AD,23,FALSE) -> 42966 | AP38: =VLOOKUP($A:$A,Variables_extraites!$A:$AD,24,FALSE) -> 21 | AQ38: =VLOOKUP($A:$A,Variables_extraites!$A:$AD,25,FALSE) -> 1 | AR38: =VLOOKUP($A:$A,Variables_extraites!$A:$AD,26,FALSE) -> 42966 | AS38: =VLOOKUP($A:$A,Variables_extraites!$A:$AD,27,FALSE) -> 21 | AT38: =VLOOKUP($A:$A,Variables_extraites!$A:$AD,28,FALSE) -> 37 | AU38: =VLOOKUP($A:$A,Variables_extraites!$A:$AD,29,FALSE) -> 1134 | AV38: =VLOOKUP($A:$A,Variables_extraites!$A:$AD,30,FALSE) -> -11.063333 | AW38: 8.8585095 | AX38: 7.1547169 | AY38: 5.3501436 | AZ38: 2.5655972 | BA38: 7.8523734 | BB38: 7.0242532 | BC38: 9.2637152 | BD38: 8.5915223 | BE38: 6.1941659 | BF38: 2.2630344 | BG38: 6.1413919 | BH38: 6.5984248 | BI38: 7.8082563 | BJ38: 4.4005379 | BK38: 5.7886857 | BL38: 8.7922372 | BM38: 6.4754092 | BN38: 6.8321305 | BO38: 5.5354309 | BP38: 5.8899602 | BQ38: 7.8757801 | BR38: 0.86393845 | BS38: 9.9137272 | BT38: 0.92599942 | BU38: 4.8145504 | BV38: 6.3391374 | BW38: 5.2723965 | BX38: 11.109374 | BY38: 3.4100697 | BZ38: 7.2023198 | CA38: 4.2234225 | CB38: 3.9070539 | CC38: 3.950612 | CD38: 8.9877278
A39: 73 | B39: 73 | C39: 2 | D39: HFpEF | E39: 10399 | F39: YES | G39: YES | H39: 70 | I39: 22.058051 | J39: 1 | K39: 2 | L39: 0 | M39: 42 | N39: 37.36 | O39: 136.58557 | P39: 1421 | Q39: 13 | R39: 31.165232 | S39: 10.055556 | T39: 21 | U39: -18.08 | V39: 73.736447 | W39: 30.056977 | X39: 56.5 | Y39: =VLOOKUP($A:$A,Variables_extraites!$A:$AD,7,FALSE) -> 0 | Z39: =VLOOKUP($A:$A,Variables_extraites!$A:$AD,8,FALSE) -> 0 | AA39: =VLOOKUP($A:$A,Variables_extraites!$A:$AD,9,FALSE) -> 12.7 | AB39: =VLOOKUP($A:$A,Variables_extraites!$A:$AD,10,FALSE) -> 0 | AC39: =VLOOKUP($A:$A,Variables_extraites!$A:$AD,11,FALSE) -> 0 | AD39: =VLOOKUP($A:$A,Variables_extraites!$A:$AD,12,FALSE) -> 1 | AE39: =VLOOKUP($A:$A,Variables_extraites!$A:$AD,13,FALSE) -> 58.237146 | AF39: =VLOOKUP($A:$A,Variables_extraites!$A:$AD,14,FALSE) -> 0.7254509 | AG39: =VLOOKUP($A:$A,Variables_extraites!$A:$AD,15,FALSE) -> 23 | AH39: =VLOOKUP($A:$A,Variables_extraites!$A:$AD,16,FALSE) -> 73 | AI39: =VLOOKUP($A:$A,Variables_extraites!$A:$AD,17,FALSE) -> 42328 | AJ39: =VLOOKUP($A:$A,Variables_extraites!$A:$AD,18,FALSE) -> 43060 | AK39: =VLOOKUP($A:$A,Variables_extraites!$A:$AD,19,FALSE) -> 0 | AL39: =VLOOKUP($A:$A,Variables_extraites!$A:$AD,20,FALSE) -> 43060 | AM39: =VLOOKUP($A:$A,Variables_extraites!$A:$AD,21,FALSE) -> 24 | AN39: =VLOOKUP($A:$A,Variables_extraites!$A:$AD,22,FALSE) -> 1 | AO39: =VLOOKUP($A:$A,Variables_extraites!$A:$AD,23,FALSE) -> 42981 | AP39: =VLOOKUP($A:$A,Variables_extraites!$A:$AD,24,FALSE) -> 21 | AQ39: =VLOOKUP($A:$A,Variables_extraites!$A:$AD,25,FALSE) -> 1 | AR39: =VLOOKUP($A:$A,Variables_extraites!$A:$AD,26,FALSE) -> 42981 | AS39: =VLOOKUP($A:$A,Variables_extraites!$A:$AD,27,FALSE) -> 21 | AT39: =VLOOKUP($A:$A,Variables_extraites!$A:$AD,28,FALSE) -> 24.07 | AU39: =VLOOKUP($A:$A,Variables_extraites!$A:$AD,29,FALSE) -> 732 | AV39: =VLOOKUP($A:$A,Variables_extraites!$A:$AD,30,FALSE) -> -28.86 | AW39: 8.2851248 | AX39: 8.1677192 | AY39: 5.2872506 | AZ39: 2.4462562 | BA39: 7.3316336 | BB39: 6.0921228 | BC39: 9.2370426 | BD39: 8.4541348 | BE39: 6.034964 | BF39: 1.1763228 | BG39: 5.9183862 | BH39: 6.2532329 | BI39: 7.3001237 | BJ39: 4.412104 | BK39: 5.746044 | BL39: 7.5273206 | BM39: 7.042316 | BN39: 6.5915597 | BO39: 5.5558162 | BP39: 5.4292812 | BQ39: 7.1907136 | BR39: -0.20091269 | BS39: 8.6537766 | BT39: 0.097610797 | BU39: 5.815063 | BV39: 6.5310695 | BW39: 4.8683905 | BX39: 11.180456 | BY39: 3.469886 | BZ39: 8.1730775 | CA39: 4.4087119 | CB39: 3.0073788 | CC39: 6.0159757 | CD39: 8.5561658
A40: 74 | B40: 74 | C40: 2 | D40: HFpEF | E40: 10569 | F40: YES | G40: YES | H40: 81 | I40: 23.243802 | J40: 0 | K40: 2 | L40: 0 | M40: 35 | N40: 61.32 | O40: 80.105472 | P40: 2025 | Q40: 35 | R40: 37.616887 | S40: 7.6190476 | T40: 25.5 | U40: -11.82 | V40: 77.607203 | W40: 29.537779 | X40: 54.6744 | Y40: =VLOOKUP($A:$A,Variables_extraites!$A:$AD,7,FALSE) -> 1 | Z40: =VLOOKUP($A:$A,Variables_extraites!$A:$AD,8,FALSE) -> 0 | AA40: =VLOOKUP($A:$A,Variables_extraites!$A:$AD,9,FALSE) -> 11.6 | AB40: =VLOOKUP($A:$A,Variables_extraites!$A:$AD,10,FALSE) -> 1 | AC40: =VLOOKUP($A:$A,Variables_extraites!$A:$AD,11,FALSE) -> 1 | AD40: =VLOOKUP($A:$A,Variables_extraites!$A:$AD,12,FALSE) -> 1 | AE40: =VLOOKUP($A:$A,Variables_extraites!$A:$AD,13,FALSE) -> 50 | AF40: =VLOOKUP($A:$A,Variables_extraites!$A:$AD,14,FALSE) -> NA | AG40: =VLOOKUP($A:$A,Variables_extraites!$A:$AD,15,FALSE) -> 17.666667 | AH40: =VLOOKUP($A:$A,Variables_extraites!$A:$AD,16,FALSE) -> 74 | AI40: =VLOOKUP($A:$A,Variables_extraites!$A:$AD,17,FALSE) -> 42087 | AJ40: =VLOOKUP($A:$A,Variables_extraites!$A:$AD,18,FALSE) -> 43333 | AK40: =VLOOKUP($A:$A,Variables_extraites!$A:$AD,19,FALSE) -> 0 | AL40: =VLOOKUP($A:$A,Variables_extraites!$A:$AD,20,FALSE) -> 43333 | AM40: =VLOOKUP($A:$A,Variables_extraites!$A:$AD,21,FALSE) -> 40 | AN40: =VLOOKUP($A:$A,Variables_extraites!$A:$AD,22,FALSE) -> 1 | AO40: =VLOOKUP($A:$A,Variables_extraites!$A:$AD,23,FALSE) -> 43244 | AP40: =VLOOKUP($A:$A,Variables_extraites!$A:$AD,24,FALSE) -> 38 | AQ40: =VLOOKUP($A:$A,Variables_extraites!$A:$AD,25,FALSE) -> 1 | AR40: =VLOOKUP($A:$A,Variables_extraites!$A:$AD,26,FALSE) -> 43244 | AS40: =VLOOKUP($A:$A,Variables_extraites!$A:$AD,27,FALSE) -> 38 | AT40: =VLOOKUP($A:$A,Variables_extraites!$A:$AD,28,FALSE) -> 40 | AU40: =VLOOKUP($A:$A,Variables_extraites!$A:$AD,29,FALSE) -> 1246 | AV40: =VLOOKUP($A:$A,Variables_extraites!$A:$AD,30,FALSE) -> NA | AW40: 7.910193 | AX40: 6.9074916 | AY40: 4.836934 | AZ40: 2.0321008 | BA40: 6.8085138 | BB40: 5.6735564 | BC40: 9.0275743 | BD40: 7.4095607 | BE40: 6.1580542 | BF40: 1.2265085 | BG40: 5.9305008 | BH40: 6.4311215 | BI40: 7.0719986 | BJ40: 4.1882427 | BK40: 5.9932215 | BL40: 7.3656226 | BM40: 6.4944156 | BN40: 6.5527459 | BO40: 5.2039842 | BP40: 6.0365033 | BQ40: 7.5428771 | BR40: 4.1333991 | BS40: 10.282486 | BT40: 2.4195389 | BU40: 6.6984963 | BV40: 6.6254166 | BW40: 4.2600257 | BX40: 10.220632 | BY40: 2.790772 | BZ40: 7.9928817 | CA40: 3.9068906 | CB40: 2.2277506 | CC40: 2.5650972 | CD40: 7.8629472
A41: 77 | B41: 77 | C41: 2 | D41: HFpEF | E41: 10545 | F41: YES | G41: YES | H41: 76 | I41: 25.142857 | J41: 0 | K41: 3 | L41: 1 | M41: 42 | N41: 65.26 | O41: 488.64176 | P41: 5592 | Q41: 56 | R41: 63.365715 | S41: 15.544554 | T41: 37.333333 | U41: -11.28 | V41: 98.205167 | W41: 39.407027 | X41: 65.2644 | Y41: =VLOOKUP($A:$A,Variables_extraites!$A:$AD,7,FALSE) -> 0 | Z41: =VLOOKUP($A:$A,Variables_extraites!$A:$AD,8,FALSE) -> 0 | AA41: =VLOOKUP($A:$A,Variables_extraites!$A:$AD,9,FALSE) -> 9.6 | AB41: =VLOOKUP($A:$A,Variables_extraites!$A:$AD,10,FALSE) -> 1 | AC41: =VLOOKUP($A:$A,Variables_extraites!$A:$AD,11,FALSE) -> 1 | AD41: =VLOOKUP($A:$A,Variables_extraites!$A:$AD,12,FALSE) -> 1 | AE41: =VLOOKUP($A:$A,Variables_extraites!$A:$AD,13,FALSE) -> 50.514626 | AF41: =VLOOKUP($A:$A,Variables_extraites!$A:$AD,14,FALSE) -> NA | AG41: =VLOOKUP($A:$A,Variables_extraites!$A:$AD,15,FALSE) -> 9.6666667 | AH41: =VLOOKUP($A:$A,Variables_extraites!$A:$AD,16,FALSE) -> 77 | AI41: =VLOOKUP($A:$A,Variables_extraites!$A:$AD,17,FALSE) -> 42185 | AJ41: =VLOOKUP($A:$A,Variables_extraites!$A:$AD,18,FALSE) -> 43118 | AK41: =VLOOKUP($A:$A,Variables_extraites!$A:$AD,19,FALSE) -> 0 | AL41: =VLOOKUP($A:$A,Variables_extraites!$A:$AD,20,FALSE) -> 43118 | AM41: =VLOOKUP($A:$A,Variables_extraites!$A:$AD,21,FALSE) -> 30 | AN41: =VLOOKUP($A:$A,Variables_extraites!$A:$AD,22,FALSE) -> 0 | AO41: =VLOOKUP($A:$A,Variables_extraites!$A:$AD,23,FALSE) -> 43118 | AP41: =VLOOKUP($A:$A,Variables_extraites!$A:$AD,24,FALSE) -> 30 | AQ41: =VLOOKUP($A:$A,Variables_extraites!$A:$AD,25,FALSE) -> 0 | AR41: =VLOOKUP($A:$A,Variables_extraites!$A:$AD,26,FALSE) -> 43118 | AS41: =VLOOKUP($A:$A,Variables_extraites!$A:$AD,27,FALSE) -> 30 | AT41: =VLOOKUP($A:$A,Variables_extraites!$A:$AD,28,FALSE) -> 30 | AU41: =VLOOKUP($A:$A,Variables_extraites!$A:$AD,29,FALSE) -> 933 | AV41: =VLOOKUP($A:$A,Variables_extraites!$A:$AD,30,FALSE) -> -18.51 | AW41: 8.1079494 | AX41: 7.5320831 | AY41: 5.1055943 | AZ41: 1.2630344 | BA41: 7.8050344 | BB41: 4.7718856 | BC41: 9.0860566 | BD41: 7.1634987 | BE41: 5.9316831 | BF41: 1.989139 | BG41: 6.7487296 | BH41: 6.939109 | BI41: 7.4443523 | BJ41: 4.5728897 | BK41: 6.1018181 | BL41: 7.318588 | BM41: 6.3362834 | BN41: 6.8701181 | BO41: 6.1751253 | BP41: 6.5439598 | BQ41: 8.057342 | BR41: 4.5813512 | BS41: 10.13895 | BT41: 2.469886 | BU41: 5.5816525 | BV41: 6.8763942 | BW41: 4.6524865 | BX41: 10.001042 | BY41: 2.6803244 | BZ41: 8.0611822 | CA41: 3.7344387 | CB41: 1.93986 | CC41: 1.0003013 | CD41: 7.6690641
A42: 78 | B42: 78 | C42: 2 | D42: HFpEF | E42: 10338 | F42: YES | G42: YES | H42: 79 | I42: 37.109375 | J42: 1 | K42: 3 | L42: 0 | M42: 36 | N42: 73.4 | O42: 242.75023 | P42: 2385 | Q42: 12 | R42: 62.78195 | S42: 20.15625 | T42: 23.333333 | U42: -11.856667 | X42: 83.559 | Y42: =VLOOKUP($A:$A,Variables_extraites!$A:$AD,7,FALSE) -> 0 | Z42: =VLOOKUP($A:$A,Variables_extraites!$A:$AD,8,FALSE) -> 0 | AA42: =VLOOKUP($A:$A,Variables_extraites!$A:$AD,9,FALSE) -> 13.5 | AB42: =VLOOKUP($A:$A,Variables_extraites!$A:$AD,10,FALSE) -> 1 | AC42: =VLOOKUP($A:$A,Variables_extraites!$A:$AD,11,FALSE) -> 0 | AD42: =VLOOKUP($A:$A,Variables_extraites!$A:$AD,12,FALSE) -> 1 | AE42: =VLOOKUP($A:$A,Variables_extraites!$A:$AD,13,FALSE) -> 50.109987 | AF42: =VLOOKUP($A:$A,Variables_extraites!$A:$AD,14,FALSE) -> NA | AG42: =VLOOKUP($A:$A,Variables_extraites!$A:$AD,15,FALSE) -> 18 | AH42: =VLOOKUP($A:$A,Variables_extraites!$A:$AD,16,FALSE) -> 78 | AI42: =VLOOKUP($A:$A,Variables_extraites!$A:$AD,17,FALSE) -> 42179 | AJ42: =VLOOKUP($A:$A,Variables_extraites!$A:$AD,18,FALSE) -> 43053 | AK42: =VLOOKUP($A:$A,Variables_extraites!$A:$AD,19,FALSE) -> 0 | AL42: =VLOOKUP($A:$A,Variables_extraites!$A:$AD,20,FALSE) -> 43053 | AM42: =VLOOKUP($A:$A,Variables_extraites!$A:$AD,21,FALSE) -> 29 | AN42: =VLOOKUP($A:$A,Variables_extraites!$A:$AD,22,FALSE) -> 1 | AO42: =VLOOKUP($A:$A,Variables_extraites!$A:$AD,23,FALSE) -> 42675 | AP42: =VLOOKUP($A:$A,Variables_extraites!$A:$AD,24,FALSE) -> 16 | AQ42: =VLOOKUP($A:$A,Variables_extraites!$A:$AD,25,FALSE) -> 1 | AR42: =VLOOKUP($A:$A,Variables_extraites!$A:$AD,26,FALSE) -> 42675 | AS42: =VLOOKUP($A:$A,Variables_extraites!$A:$AD,27,FALSE) -> 16 | AT42: =VLOOKUP($A:$A,Variables_extraites!$A:$AD,28,FALSE) -> 28.7 | AU42: =VLOOKUP($A:$A,Variables_extraites!$A:$AD,29,FALSE) -> 874 | AV42: =VLOOKUP($A:$A,Variables_extraites!$A:$AD,30,FALSE) -> -18.923333 | AW42: 8.3746918 | AX42: 7.5414064 | AY42: 4.6701605 | AZ42: 2.0976108 | BA42: 7.6562818 | BB42: 7.3328869 | BC42: 8.7960072 | BD42: 7.7884247 | BE42: 5.9274224 | BF42: 1.0703893 | BG42: 5.822985 | BH42: 6.3881895 | BI42: 7.2846622 | BJ42: 4.0669502 | BK42: 5.8858184 | BL42: 7.4623796 | BM42: 6.0950805 | BN42: 6.3852585 | BO42: 5.722466 | BP42: 5.8356715 | BQ42: 7.6380738 | BR42: -0.83650127 | BS42: 9.6508184 | BT42: 1.3391374 | BU42: 6.7516779 | BV42: 7.3177744 | BW42: 5.6427016 | BX42: 10.008947 | BY42: 2.9467309 | BZ42: 6.7958449 | CA42: 4.4854268 | CB42: 3.2131019 | CC42: 7.5881792 | CD42: 8.311681
A43: 81 | B43: 81 | C43: 2 | D43: HFpEF | E43: 10367 | F43: YES | H43: 83 | I43: 21.786492 | J43: 1 | K43: 3 | L43: 0 | M43: 38 | N43: 34.5 | O43: 66.524206 | P43: 1280 | Q43: 31 | R43: 13.920192 | S43: 13 | T43: 24 | U43: -12.98 | V43: 77.485656 | W43: 27.801532 | X43: 33.5764 | Y43: =VLOOKUP($A:$A,Variables_extraites!$A:$AD,7,FALSE) -> 0 | Z43: =VLOOKUP($A:$A,Variables_extraites!$A:$AD,8,FALSE) -> 0 | AA43: =VLOOKUP($A:$A,Variables_extraites!$A:$AD,9,FALSE) -> 10.7 | AB43: =VLOOKUP($A:$A,Variables_extraites!$A:$AD,10,FALSE) -> 0 | AC43: =VLOOKUP($A:$A,Variables_extraites!$A:$AD,11,FALSE) -> 1 | AD43: =VLOOKUP($A:$A,Variables_extraites!$A:$AD,12,FALSE) -> 0 | AE43: =VLOOKUP($A:$A,Variables_extraites!$A:$AD,13,FALSE) -> 58.894646 | AF43: =VLOOKUP($A:$A,Variables_extraites!$A:$AD,14,FALSE) -> 0.43820225 | AG43: =VLOOKUP($A:$A,Variables_extraites!$A:$AD,15,FALSE) -> 13 | AH43: =VLOOKUP($A:$A,Variables_extraites!$A:$AD,16,FALSE) -> 81 | AI43: =VLOOKUP($A:$A,Variables_extraites!$A:$AD,17,FALSE) -> 42170 | AJ43: =VLOOKUP($A:$A,Variables_extraites!$A:$AD,18,FALSE) -> 42943 | AK43: =VLOOKUP($A:$A,Variables_extraites!$A:$AD,19,FALSE) -> 1 | AL43: =VLOOKUP($A:$A,Variables_extraites!$A:$AD,20,FALSE) -> 42943 | AM43: =VLOOKUP($A:$A,Variables_extraites!$A:$AD,21,FALSE) -> 25 | AN43: =VLOOKUP($A:$A,Variables_extraites!$A:$AD,22,FALSE) -> 1 | AO43: =VLOOKUP($A:$A,Variables_extraites!$A:$AD,23,FALSE) -> 42640 | AP43: =VLOOKUP($A:$A,Variables_extraites!$A:$AD,24,FALSE) -> 15 | AQ43: =VLOOKUP($A:$A,Variables_extraites!$A:$AD,25,FALSE) -> 1 | AR43: =VLOOKUP($A:$A,Variables_extraites!$A:$AD,26,FALSE) -> 42640 | AS43: =VLOOKUP($A:$A,Variables_extraites!$A:$AD,27,FALSE) -> 15 | AT43: =VLOOKUP($A:$A,Variables_extraites!$A:$AD,28,FALSE) -> 25 | AU43: =VLOOKUP($A:$A,Variables_extraites!$A:$AD,29,FALSE) -> 773 | AV43: =VLOOKUP($A:$A,Variables_extraites!$A:$AD,30,FALSE) -> -23.81
A44: 85 | B44: 85 | C44: 2 | D44: HFpEF | E44: 10368 | F44: YES | G44: YES | H44: 82 | I44: 29.384757 | J44: 1 | K44: 4 | L44: 1 | M44: 72 | N44: 54.61 | O44: 47.784566 | P44: 291.3 | Q44: 15 | R44: 47.829393 | S44: 29.137931 | T44: 39 | U44: -16.1 | V44: 68.636155 | W44: 26.782428 | X44: 41.9723 | Y44: =VLOOKUP($A:$A,Variables_extraites!$A:$AD,7,FALSE) -> 0 | Z44: =VLOOKUP($A:$A,Variables_extraites!$A:$AD,8,FALSE) -> 0 | AA44: =VLOOKUP($A:$A,Variables_extraites!$A:$AD,9,FALSE) -> 11.8 | AB44: =VLOOKUP($A:$A,Variables_extraites!$A:$AD,10,FALSE) -> 1 | AC44: =VLOOKUP($A:$A,Variables_extraites!$A:$AD,11,FALSE) -> 1 | AD44: =VLOOKUP($A:$A,Variables_extraites!$A:$AD,12,FALSE) -> 0 | AE44: =VLOOKUP($A:$A,Variables_extraites!$A:$AD,13,FALSE) -> 54.680665 | AF44: =VLOOKUP($A:$A,Variables_extraites!$A:$AD,14,FALSE) -> 2.4635569 | AG44: =VLOOKUP($A:$A,Variables_extraites!$A:$AD,15,FALSE) -> 10 | AH44: =VLOOKUP($A:$A,Variables_extraites!$A:$AD,16,FALSE) -> 85 | AI44: =VLOOKUP($A:$A,Variables_extraites!$A:$AD,17,FALSE) -> 42332 | AJ44: =VLOOKUP($A:$A,Variables_extraites!$A:$AD,18,FALSE) -> 43544 | AK44: =VLOOKUP($A:$A,Variables_extraites!$A:$AD,19,FALSE) -> 0 | AL44: =VLOOKUP($A:$A,Variables_extraites!$A:$AD,20,FALSE) -> 43544 | AM44: =VLOOKUP($A:$A,Variables_extraites!$A:$AD,21,FALSE) -> 39 | AN44: =VLOOKUP($A:$A,Variables_extraites!$A:$AD,22,FALSE) -> 0 | AO44: =VLOOKUP($A:$A,Variables_extraites!$A:$AD,23,FALSE) -> 43544 | AP44: =VLOOKUP($A:$A,Variables_extraites!$A:$AD,24,FALSE) -> 39 | AQ44: =VLOOKUP($A:$A,Variables_extraites!$A:$AD,25,FALSE) -> 0 | AR44: =VLOOKUP($A:$A,Variables_extraites!$A:$AD,26,FALSE) -> 43544 | AS44: =VLOOKUP($A:$A,Variables_extraites!$A:$AD,27,FALSE) -> 39 | AT44: =VLOOKUP($A:$A,Variables_extraites!$A:$AD,28,FALSE) -> 39 | AU44: =VLOOKUP($A:$A,Variables_extraites!$A:$AD,29,FALSE) -> 1212 | AV44: =VLOOKUP($A:$A,Variables_extraites!$A:$AD,30,FALSE) -> -24.91 | AW44: 8.6818358 | AX44: 7.0825749 | AY44: 5.4597595 | AZ44: 3.0891591 | BA44: 7.2317012 | BB44: 6.8576078 | BC44: 8.791749 | BD44: 7.3409183 | BE44: 6.1805059 | BF44: 1.2141248 | BG44: 6.1872531 | BH44: 6.8609628 | BI44: 7.6149306 | BJ44: 4.6741216 | BK44: 6.3719073 | BL44: 7.6959242 | BM44: 6.4475792 | BN44: 6.7191834 | BO44: 5.9150428 | BP44: 6.3647475 | BQ44: 7.9480752 | BR44: -0.78587519 | BS44: 10.009311 | BT44: 1.3103401 | BU44: 3.2479275 | BV44: 5.8158316 | BW44: 5.5689441 | BX44: 11.851714 | BY44: 3.0408924 | BZ44: 8.2507248 | CA44: 4.3362834 | CB44: 3.6009891 | CC44: 4.0338027 | CD44: 8.6989707
A45: 87 | B45: 87 | C45: 2 | D45: HFpEF | E45: 10508 | F45: YES | G45: YES | H45: 80 | I45: 29.802776 | J45: 0 | K45: 2 | L45: 0 | M45: 47 | N45: 49.9 | O45: 144.75966 | P45: 1393 | Q45: 29 | R45: 67.604547 | S45: 23.693333 | T45: 40.333333 | U45: -15.876667 | V45: 56.752276 | W45: 28.96704 | X45: 89.214 | Y45: =VLOOKUP($A:$A,Variables_extraites!$A:$AD,7,FALSE) -> 1 | Z45: =VLOOKUP($A:$A,Variables_extraites!$A:$AD,8,FALSE) -> 0 | AA45: =VLOOKUP($A:$A,Variables_extraites!$A:$AD,9,FALSE) -> 12.1 | AB45: =VLOOKUP($A:$A,Variables_extraites!$A:$AD,10,FALSE) -> 1 | AC45: =VLOOKUP($A:$A,Variables_extraites!$A:$AD,11,FALSE) -> 0 | AD45: =VLOOKUP($A:$A,Variables_extraites!$A:$AD,12,FALSE) -> 1 | AE45: =VLOOKUP($A:$A,Variables_extraites!$A:$AD,13,FALSE) -> 66.976127 | AF45: =VLOOKUP($A:$A,Variables_extraites!$A:$AD,14,FALSE) -> NA | AG45: =VLOOKUP($A:$A,Variables_extraites!$A:$AD,15,FALSE) -> 18.333333 | AH45: =VLOOKUP($A:$A,Variables_extraites!$A:$AD,16,FALSE) -> 87 | AI45: =VLOOKUP($A:$A,Variables_extraites!$A:$AD,17,FALSE) -> 42104 | AJ45: =VLOOKUP($A:$A,Variables_extraites!$A:$AD,18,FALSE) -> 43118 | AK45: =VLOOKUP($A:$A,Variables_extraites!$A:$AD,19,FALSE) -> 0 | AL45: =VLOOKUP($A:$A,Variables_extraites!$A:$AD,20,FALSE) -> 43118 | AM45: =VLOOKUP($A:$A,Variables_extraites!$A:$AD,21,FALSE) -> 33 | AN45: =VLOOKUP($A:$A,Variables_extraites!$A:$AD,22,FALSE) -> 0 | AO45: =VLOOKUP($A:$A,Variables_extraites!$A:$AD,23,FALSE) -> 43118 | AP45: =VLOOKUP($A:$A,Variables_extraites!$A:$AD,24,FALSE) -> 33 | AQ45: =VLOOKUP($A:$A,Variables_extraites!$A:$AD,25,FALSE) -> 0 | AR45: =VLOOKUP($A:$A,Variables_extraites!$A:$AD,26,FALSE) -> 43118 | AS45: =VLOOKUP($A:$A,Variables_extraites!$A:$AD,27,FALSE) -> 33 | AT45: =VLOOKUP($A:$A,Variables_extraites!$A:$AD,28,FALSE) -> 33 | AU45: =VLOOKUP($A:$A,Variables_extraites!$A:$AD,29,FALSE) -> 1014 | AV45: =VLOOKUP($A:$A,Variables_extraites!$A:$AD,30,FALSE) -> -23.736667 | AW45: 8.6017708 | AX45: 7.1719274 | AY45: 4.9040023 | AZ45: 2.6252705 | BA45: 7.1756244 | BB45: 6.8960296 | BC45: 9.2160668 | BD45: 7.3735612 | BE45: 6.2127639 | BF45: 1.2630344 | BG45: 6.6016965 | BH45: 7.0047261 | BI45: 7.5572722 | BJ45: 4.5527459 | BK45: 6.1864609 | BL45: 8.0905888 | BM45: 5.7235586 | BN45: 6.2315092 | BO45: 5.864929 | BP45: 6.5444236 | BQ45: 7.972348 | BR45: 1.7484612 | BS45: 11.4813 | BT45: 2.304511 | BU45: 7.148324 | BV45: 6.8469947 | BW45: 5.6208796 | BX45: 11.485744 | BY45: 4.5903625 | BZ45: 8.153552 | CA45: 4.0660892 | CB45: 3.3321918 | CC45: 5.3998628 | CD45: 9.1767889
A46: 89 | B46: 89 | C46: 2 | D46: HFpEF | E46: 10369 | F46: YES | G46: YES | H46: 73 | I46: 38.855953 | J46: 1 | K46: 3 | L46: 1 | M46: 25 | N46: 58.71 | O46: 332.88609 | P46: 3643 | Q46: 224 | R46: 35.381278 | S46: 27.105263 | T46: 43 | U46: -16.9 | V46: 63.914566 | W46: 28.278156 | X46: 90.062 | Y46: =VLOOKUP($A:$A,Variables_extraites!$A:$AD,7,FALSE) -> 0 | Z46: =VLOOKUP($A:$A,Variables_extraites!$A:$AD,8,FALSE) -> suspect | AA46: =VLOOKUP($A:$A,Variables_extraites!$A:$AD,9,FALSE) -> 12.8 | AB46: =VLOOKUP($A:$A,Variables_extraites!$A:$AD,10,FALSE) -> 1 | AC46: =VLOOKUP($A:$A,Variables_extraites!$A:$AD,11,FALSE) -> 1 | AD46: =VLOOKUP($A:$A,Variables_extraites!$A:$AD,12,FALSE) -> 0 | AE46: =VLOOKUP($A:$A,Variables_extraites!$A:$AD,13,FALSE) -> 61.182033 | AF46: =VLOOKUP($A:$A,Variables_extraites!$A:$AD,14,FALSE) -> 1.8761384 | AG46: =VLOOKUP($A:$A,Variables_extraites!$A:$AD,15,FALSE) -> 17 | AH46: =VLOOKUP($A:$A,Variables_extraites!$A:$AD,16,FALSE) -> 89 | AI46: =VLOOKUP($A:$A,Variables_extraites!$A:$AD,17,FALSE) -> 42108 | AJ46: =VLOOKUP($A:$A,Variables_extraites!$A:$AD,18,FALSE) -> 43424 | AK46: =VLOOKUP($A:$A,Variables_extraites!$A:$AD,19,FALSE) -> 0 | AL46: =VLOOKUP($A:$A,Variables_extraites!$A:$AD,20,FALSE) -> 43424 | AM46: =VLOOKUP($A:$A,Variables_extraites!$A:$AD,21,FALSE) -> 43 | AN46: =VLOOKUP($A:$A,Variables_extraites!$A:$AD,22,FALSE) -> 1 | AO46: =VLOOKUP($A:$A,Variables_extraites!$A:$AD,23,FALSE) -> 42473 | AP46: =VLOOKUP($A:$A,Variables_extraites!$A:$AD,24,FALSE) -> 11 | AQ46: =VLOOKUP($A:$A,Variables_extraites!$A:$AD,25,FALSE) -> 1 | AR46: =VLOOKUP($A:$A,Variables_extraites!$A:$AD,26,FALSE) -> 42473 | AS46: =VLOOKUP($A:$A,Variables_extraites!$A:$AD,27,FALSE) -> 11 | AT46: =VLOOKUP($A:$A,Variables_extraites!$A:$AD,28,FALSE) -> 43 | AU46: =VLOOKUP($A:$A,Variables_extraites!$A:$AD,29,FALSE) -> 1316 | AV46: =VLOOKUP($A:$A,Variables_extraites!$A:$AD,30,FALSE) -> -14.73 | AW46: 8.3827537 | AX46: 9.2006289 | AY46: 5.5310695 | AZ46: 1.6276068 | BA46: 8.4352535 | BB46: 4.7158934 | BC46: 9.1955691 | BD46: 8.5604857 | BE46: 6.0656585 | BF46: 2.0285692 | BG46: 5.4860707 | BH46: 5.7750505 | BI46: 7.4075227 | BJ46: 4.7114949 | BK46: 6.0533286 | BL46: 7.3703387 | BM46: 6.5623951 | BN46: 7.2211037 | BO46: 6.0232554 | BP46: 5.7758407 | BQ46: 7.1231902 | BR46: 5.9411063 | BS46: 10.764656 | BT46: 2.4382929 | BU46: 7.0552824 | BV46: 7.2042777 | BW46: 5.1026581 | BX46: 10.469123 | BY46: 3.2187812 | BZ46: 8.3230097 | CA46: 4.582556 | CB46: 2.1461131 | CC46: 1.1141761 | CD46: 8.3263631
A47: 90 | B47: 90 | C47: 2 | D47: HFpEF | E47: 10511 | F47: YES | G47: YES | H47: 66 | I47: 24.6755 | J47: 0 | K47: 2 | L47: 0 | M47: 47 | N47: 62.19 | O47: 134.20356 | P47: 311.9 | Q47: 16 | R47: 27.772376 | S47: 9.2 | T47: 30 | U47: -20.59 | V47: 75.70571 | W47: 29.366442 | X47: 66.6348 | Y47: =VLOOKUP($A:$A,Variables_extraites!$A:$AD,7,FALSE) -> 0 | Z47: =VLOOKUP($A:$A,Variables_extraites!$A:$AD,8,FALSE) -> 0 | AA47: =VLOOKUP($A:$A,Variables_extraites!$A:$AD,9,FALSE) -> 7.3 | AB47: =VLOOKUP($A:$A,Variables_extraites!$A:$AD,10,FALSE) -> 1 | AC47: =VLOOKUP($A:$A,Variables_extraites!$A:$AD,11,FALSE) -> 0 | AD47: =VLOOKUP($A:$A,Variables_extraites!$A:$AD,12,FALSE) -> 0 | AE47: =VLOOKUP($A:$A,Variables_extraites!$A:$AD,13,FALSE) -> 67.038671 | AF47: =VLOOKUP($A:$A,Variables_extraites!$A:$AD,14,FALSE) -> 1.1925926 | AG47: =VLOOKUP($A:$A,Variables_extraites!$A:$AD,15,FALSE) -> 25 | AH47: =VLOOKUP($A:$A,Variables_extraites!$A:$AD,16,FALSE) -> 90 | AI47: =VLOOKUP($A:$A,Variables_extraites!$A:$AD,17,FALSE) -> 42198 | AJ47: =VLOOKUP($A:$A,Variables_extraites!$A:$AD,18,FALSE) -> 42281 | AK47: =VLOOKUP($A:$A,Variables_extraites!$A:$AD,19,FALSE) -> 1 | AL47: =VLOOKUP($A:$A,Variables_extraites!$A:$AD,20,FALSE) -> 42281 | AM47: =VLOOKUP($A:$A,Variables_extraites!$A:$AD,21,FALSE) -> 3 | AN47: =VLOOKUP($A:$A,Variables_extraites!$A:$AD,22,FALSE) -> 1 | AO47: =VLOOKUP($A:$A,Variables_extraites!$A:$AD,23,FALSE) -> 42205 | AP47: =VLOOKUP($A:$A,Variables_extraites!$A:$AD,24,FALSE) -> 0 | AQ47: =VLOOKUP($A:$A,Variables_extraites!$A:$AD,25,FALSE) -> 1 | AR47: =VLOOKUP($A:$A,Variables_extraites!$A:$AD,26,FALSE) -> 42205 | AS47: =VLOOKUP($A:$A,Variables_extraites!$A:$AD,27,FALSE) -> 0 | AT47: =VLOOKUP($A:$A,Variables_extraites!$A:$AD,28,FALSE) -> 2.7 | AU47: =VLOOKUP($A:$A,Variables_extraites!$A:$AD,29,FALSE) -> 83 | AV47: =VLOOKUP($A:$A,Variables_extraites!$A:$AD,30,FALSE) -> -23.26 | AW47: 8.5590329 | AX47: 7.2205234 | AY47: 4.5229346 | AZ47: 1.5058909 | BA47: 6.7281926 | BB47: 5.033423 | BC47: 9.3734525 | BD47: 7.6881804 | BE47: 6.1896269 | BF47: 1.4750849 | BG47: 6.1026581 | BH47: 6.5252859 | BI47: 6.2861419 | BJ47: 4.1626934 | BK47: 5.7219194 | BL47: 7.3907708 | BM47: 6.4213916 | BN47: 6.0844895 | BO47: 4.6322682 | BP47: 5.8972404 | BQ47: 7.604442 | BR47: 3.5447327 | BS47: 10.55526 | BT47: 2.2387869 | BU47: 5.1763228 | BV47: 7.3454496 | BW47: 5.0049508 | BX47: 11.309448 | BY47: 3.6690268 | BZ47: 9.0069431 | CA47: 4.0643655 | CB47: 2.3025048 | CC47: 1.6315901 | CD47: 8.3164733
A48: 92 | B48: 92 | C48: 2 | D48: HFpEF | E48: 10607 | F48: YES | G48: YES | H48: 80 | I48: 31.444048 | J48: 0 | K48: 4 | L48: 1 | M48: 41 | N48: 35.42 | O48: 1543.0627 | P48: 1120 | Q48: 32 | R48: 38.666568 | S48: 12.292553 | T48: 38 | U48: -18.363333 | V48: 86.759235 | W48: 34.641399 | X48: 99.2941 | Y48: =VLOOKUP($A:$A,Variables_extraites!$A:$AD,7,FALSE) -> 0 | Z48: =VLOOKUP($A:$A,Variables_extraites!$A:$AD,8,FALSE) -> 1 | AA48: =VLOOKUP($A:$A,Variables_extraites!$A:$AD,9,FALSE) -> 10.5 | AB48: =VLOOKUP($A:$A,Variables_extraites!$A:$AD,10,FALSE) -> 0 | AC48: =VLOOKUP($A:$A,Variables_extraites!$A:$AD,11,FALSE) -> 1 | AD48: =VLOOKUP($A:$A,Variables_extraites!$A:$AD,12,FALSE) -> 1 | AE48: =VLOOKUP($A:$A,Variables_extraites!$A:$AD,13,FALSE) -> 65.333333 | AF48: =VLOOKUP($A:$A,Variables_extraites!$A:$AD,14,FALSE) -> NA | AG48: =VLOOKUP($A:$A,Variables_extraites!$A:$AD,15,FALSE) -> 18 | AH48: =VLOOKUP($A:$A,Variables_extraites!$A:$AD,16,FALSE) -> 92 | AI48: =VLOOKUP($A:$A,Variables_extraites!$A:$AD,17,FALSE) -> 42153 | AJ48: =VLOOKUP($A:$A,Variables_extraites!$A:$AD,18,FALSE) -> 43518 | AK48: =VLOOKUP($A:$A,Variables_extraites!$A:$AD,19,FALSE) -> 0 | AL48: =VLOOKUP($A:$A,Variables_extraites!$A:$AD,20,FALSE) -> 43518 | AM48: =VLOOKUP($A:$A,Variables_extraites!$A:$AD,21,FALSE) -> 44 | AN48: =VLOOKUP($A:$A,Variables_extraites!$A:$AD,22,FALSE) -> 1 | AO48: =VLOOKUP($A:$A,Variables_extraites!$A:$AD,23,FALSE) -> 43513 | AP48: =VLOOKUP($A:$A,Variables_extraites!$A:$AD,24,FALSE) -> 44 | AQ48: =VLOOKUP($A:$A,Variables_extraites!$A:$AD,25,FALSE) -> 1 | AR48: =VLOOKUP($A:$A,Variables_extraites!$A:$AD,26,FALSE) -> 43513 | AS48: =VLOOKUP($A:$A,Variables_extraites!$A:$AD,27,FALSE) -> 44 | AT48: =VLOOKUP($A:$A,Variables_extraites!$A:$AD,28,FALSE) -> 44 | AU48: =VLOOKUP($A:$A,Variables_extraites!$A:$AD,29,FALSE) -> 1365 | AV48: =VLOOKUP($A:$A,Variables_extraites!$A:$AD,30,FALSE) -> -22.766667 | AW48: 6.5096958 | AX48: 8.4771916 | AY48: 5.1497471 | AZ48: 1.6690268 | BA48: 9.1335019 | BB48: 6.3731262 | BC48: 9.0626938 | BD48: 7.7663964 | BE48: 6.0236989 | BF48: 1.5260688 | BG48: 5.2152903 | BH48: 5.7330831 | BI48: 7.2301646 | BJ48: 4.6507646 | BK48: 6.1683211 | BL48: 7.2525708 | BM48: 6.1729275 | BN48: 6.7273759 | BO48: 5.6698772 | BP48: 6.1578522 | BQ48: 6.9920886 | BR48: 6.3991711 | BS48: 11.547463 | BT48: 3.2464081 | BU48: 7.6914644 | BV48: 6.8875253 | BW48: 6.0254718 | BX48: 9.9949615 | BY48: 3.5310695 | BZ48: 7.781622 | CA48: 4.1018181 | CB48: 2.2133395 | CC48: 1.2922933 | CD48: 8.3010552
A49: 93 | B49: 93 | C49: 2 | D49: HFpEF | E49: 10435 | F49: YES | G49: YES | H49: 68 | I49: 34.707761 | J49: 1 | K49: 3 | L49: 1 | M49: 23 | N49: 226.6 | O49: 983.56521 | P49: 7015 | Q49: 34 | R49: 63.768817 | S49: 35.75 | T49: 38 | U49: -20.7 | V49: 75.127358 | X49: 205.2948 | Y49: =VLOOKUP($A:$A,Variables_extraites!$A:$AD,7,FALSE) -> 0 | Z49: =VLOOKUP($A:$A,Variables_extraites!$A:$AD,8,FALSE) -> 0 | AA49: =VLOOKUP($A:$A,Variables_extraites!$A:$AD,9,FALSE) -> 9.4 | AB49: =VLOOKUP($A:$A,Variables_extraites!$A:$AD,10,FALSE) -> 1 | AC49: =VLOOKUP($A:$A,Variables_extraites!$A:$AD,11,FALSE) -> 0 | AD49: =VLOOKUP($A:$A,Variables_extraites!$A:$AD,12,FALSE) -> 0 | AE49: =VLOOKUP($A:$A,Variables_extraites!$A:$AD,13,FALSE) -> 65.045704 | AF49: =VLOOKUP($A:$A,Variables_extraites!$A:$AD,14,FALSE) -> 1.8239796 | AG49: =VLOOKUP($A:$A,Variables_extraites!$A:$AD,15,FALSE) -> 30 | AH49: =VLOOKUP($A:$A,Variables_extraites!$A:$AD,16,FALSE) -> 93 | AI49: =VLOOKUP($A:$A,Variables_extraites!$A:$AD,17,FALSE) -> 42353 | AJ49: =VLOOKUP($A:$A,Variables_extraites!$A:$AD,18,FALSE) -> 43399 | AK49: =VLOOKUP($A:$A,Variables_extraites!$A:$AD,19,FALSE) -> 0 | AL49: =VLOOKUP($A:$A,Variables_extraites!$A:$AD,20,FALSE) -> 43399 | AM49: =VLOOKUP($A:$A,Variables_extraites!$A:$AD,21,FALSE) -> 34 | AN49: =VLOOKUP($A:$A,Variables_extraites!$A:$AD,22,FALSE) -> 1 | AO49: =VLOOKUP($A:$A,Variables_extraites!$A:$AD,23,FALSE) -> 42370 | AP49: =VLOOKUP($A:$A,Variables_extraites!$A:$AD,24,FALSE) -> 1 | AQ49: =VLOOKUP($A:$A,Variables_extraites!$A:$AD,25,FALSE) -> 1 | AR49: =VLOOKUP($A:$A,Variables_extraites!$A:$AD,26,FALSE) -> 42370 | AS49: =VLOOKUP($A:$A,Variables_extraites!$A:$AD,27,FALSE) -> 1 | AT49: =VLOOKUP($A:$A,Variables_extraites!$A:$AD,28,FALSE) -> 34 | AU49: =VLOOKUP($A:$A,Variables_extraites!$A:$AD,29,FALSE) -> 1046 | AV49: =VLOOKUP($A:$A,Variables_extraites!$A:$AD,30,FALSE) -> -15.15 | AW49: 8.191306 | AX49: 7.0749977 | AY49: 5.2776129 | AZ49: 3.2078929 | BA49: 7.3442071 | BB49: 6.9064096 | BC49: 9.1333221 | BD49: 8.5163304 | BE49: 5.8936049 | BF49: 3.2125693 | BG49: 6.0212576 | BH49: 6.4444352 | BI49: 6.7683167 | BJ49: 3.8489984 | BK49: 5.6536333 | BL49: 8.3530586 | BM49: 7.1459831 | BN49: 6.5731927 | BO49: 3.945795 | BP49: 5.3441183 | BQ49: 7.2476427 | BR49: 1.3504972 | BS49: 9.2589429 | BT49: -0.71311885 | BU49: 6.5939513 | BV49: 6.4342946 | BW49: 5.0802313 | BX49: 12.220514 | BY49: 3.8399596 | BZ49: 6.990728 | CA49: 4.1432301 | CB49: 5.2297864 | CC49: 5.243454 | CD49: 9.9720617
A50: 95 | B50: 95 | C50: 2 | D50: HFpEF | E50: 10610 | F50: YES | G50: YES | H50: 80 | I50: 26.59267 | J50: 0 | K50: 2 | L50: 0 | M50: 82 | N50: 31.78 | O50: 60.364392 | P50: 734 | Q50: 12 | R50: 40.192355 | S50: 12.609819 | T50: 23.5 | U50: -17.763333 | V50: 59.959443 | W50: 29.373802 | X50: 54.5528 | Y50: =VLOOKUP($A:$A,Variables_extraites!$A:$AD,7,FALSE) -> 0 | Z50: =VLOOKUP($A:$A,Variables_extraites!$A:$AD,8,FALSE) -> 0 | AA50: =VLOOKUP($A:$A,Variables_extraites!$A:$AD,9,FALSE) -> 13.3 | AB50: =VLOOKUP($A:$A,Variables_extraites!$A:$AD,10,FALSE) -> 0 | AC50: =VLOOKUP($A:$A,Variables_extraites!$A:$AD,11,FALSE) -> 0 | AD50: =VLOOKUP($A:$A,Variables_extraites!$A:$AD,12,FALSE) -> 0 | AE50: =VLOOKUP($A:$A,Variables_extraites!$A:$AD,13,FALSE) -> 70.439129 | AF50: =VLOOKUP($A:$A,Variables_extraites!$A:$AD,14,FALSE) -> NA | AG50: =VLOOKUP($A:$A,Variables_extraites!$A:$AD,15,FALSE) -> 24 | AH50: =VLOOKUP($A:$A,Variables_extraites!$A:$AD,16,FALSE) -> 95 | AI50: =VLOOKUP($A:$A,Variables_extraites!$A:$AD,17,FALSE) -> 42401 | AJ50: =VLOOKUP($A:$A,Variables_extraites!$A:$AD,18,FALSE) -> 43480 | AK50: =VLOOKUP($A:$A,Variables_extraites!$A:$AD,19,FALSE) -> 0 | AL50: =VLOOKUP($A:$A,Variables_extraites!$A:$AD,20,FALSE) -> 43480 | AM50: =VLOOKUP($A:$A,Variables_extraites!$A:$AD,21,FALSE) -> 35 | AN50: =VLOOKUP($A:$A,Variables_extraites!$A:$AD,22,FALSE) -> 0 | AO50: =VLOOKUP($A:$A,Variables_extraites!$A:$AD,23,FALSE) -> 43480 | AP50: =VLOOKUP($A:$A,Variables_extraites!$A:$AD,24,FALSE) -> 35 | AQ50: =VLOOKUP($A:$A,Variables_extraites!$A:$AD,25,FALSE) -> 0 | AR50: =VLOOKUP($A:$A,Variables_extraites!$A:$AD,26,FALSE) -> 43480 | AS50: =VLOOKUP($A:$A,Variables_extraites!$A:$AD,27,FALSE) -> 35 | AT50: =VLOOKUP($A:$A,Variables_extraites!$A:$AD,28,FALSE) -> 35 | AU50: =VLOOKUP($A:$A,Variables_extraites!$A:$AD,29,FALSE) -> 1079 | AV50: =VLOOKUP($A:$A,Variables_extraites!$A:$AD,30,FALSE) -> -22.206667 | AW50: 8.40612 | AX50: 7.7936358 | AY50: 5.4558204 | AZ50: 2.0908534 | BA50: 7.6707271 | BB50: 5.8799508 | BC50: 9.1791129 | BD50: 7.9720608 | BE50: 6.139756 | BF50: 0.91838623 | BG50: 6.6395216 | BH50: 7.0491951 | BI50: 7.7128021 | BJ50: 4.5843613 | BK50: 6.3722556 | BL50: 7.8015467 | BM50: 6.3619438 | BN50: 6.9752175 | BO50: 6.2641611 | BP50: 6.5581145 | BQ50: 8.0370527 | BR50: 1.3617684 | BS50: 10.032211 | BT50: 1.4276062 | BU50: 4.9791108 | BV50: 6.4444352 | BW50: 4.6351739 | BX50: 11.074857 | BY50: 2.8894735 | BZ50: 8.4230318 | CA50: 4.0179219 | CB50: 2.6518254 | CC50: 3.6173424 | CD50: 8.6046049
A51: 96 | B51: 96 | C51: 2 | D51: HFpEF | E51: 10400 | F51: YES | G51: YES | H51: 80 | I51: 26.479182 | J51: 1 | K51: 2 | L51: 0 | M51: 67 | N51: 79.03 | O51: 47.205279 | P51: 647.9 | Q51: 10 | R51: 47.286728 | S51: 10.650794 | T51: 29 | U51: -13.26 | V51: 67.505197 | W51: 32.747232 | X51: 35.2584 | Y51: =VLOOKUP($A:$A,Variables_extraites!$A:$AD,7,FALSE) -> 0 | Z51: =VLOOKUP($A:$A,Variables_extraites!$A:$AD,8,FALSE) -> 0 | AA51: =VLOOKUP($A:$A,Variables_extraites!$A:$AD,9,FALSE) -> 8.8 | AB51: =VLOOKUP($A:$A,Variables_extraites!$A:$AD,10,FALSE) -> 0 | AC51: =VLOOKUP($A:$A,Variables_extraites!$A:$AD,11,FALSE) -> 1 | AD51: =VLOOKUP($A:$A,Variables_extraites!$A:$AD,12,FALSE) -> 0 | AE51: =VLOOKUP($A:$A,Variables_extraites!$A:$AD,13,FALSE) -> 68.032787 | AF51: =VLOOKUP($A:$A,Variables_extraites!$A:$AD,14,FALSE) -> 0.70409234 | AG51: =VLOOKUP($A:$A,Variables_extraites!$A:$AD,15,FALSE) -> 17 | AH51: =VLOOKUP($A:$A,Variables_extraites!$A:$AD,16,FALSE) -> 96 | AI51: =VLOOKUP($A:$A,Variables_extraites!$A:$AD,17,FALSE) -> 42373 | AJ51: =VLOOKUP($A:$A,Variables_extraites!$A:$AD,18,FALSE) -> 43404 | AK51: =VLOOKUP($A:$A,Variables_extraites!$A:$AD,19,FALSE) -> 0 | AL51: =VLOOKUP($A:$A,Variables_extraites!$A:$AD,20,FALSE) -> 43404 | AM51: =VLOOKUP($A:$A,Variables_extraites!$A:$AD,21,FALSE) -> 33 | AN51: =VLOOKUP($A:$A,Variables_extraites!$A:$AD,22,FALSE) -> 0 | AO51: =VLOOKUP($A:$A,Variables_extraites!$A:$AD,23,FALSE) -> 43404 | AP51: =VLOOKUP($A:$A,Variables_extraites!$A:$AD,24,FALSE) -> 33 | AQ51: =VLOOKUP($A:$A,Variables_extraites!$A:$AD,25,FALSE) -> 0 | AR51: =VLOOKUP($A:$A,Variables_extraites!$A:$AD,26,FALSE) -> 43404 | AS51: =VLOOKUP($A:$A,Variables_extraites!$A:$AD,27,FALSE) -> 33 | AT51: =VLOOKUP($A:$A,Variables_extraites!$A:$AD,28,FALSE) -> 33 | AU51: =VLOOKUP($A:$A,Variables_extraites!$A:$AD,29,FALSE) -> 1031 | AV51: =VLOOKUP($A:$A,Variables_extraites!$A:$AD,30,FALSE) -> -27.36 | AW51: 8.4963745 | AX51: 7.8252768 | AY51: 5.0417686 | AZ51: 1.8836208 | BA51: 7.3169603 | BB51: 5.8522486 | BC51: 9.1108748 | BD51: 7.6146362 | BE51: 5.8140376 | BF51: 1.0285692 | BG51: 5.9827655 | BH51: 6.2679103 | BI51: 7.198003 | BJ51: 4.1060132 | BK51: 5.7782086 | BL51: 7.5056528 | BM51: 6.4531883 | BN51: 7.1528932 | BO51: 5.0596149 | BP51: 6.0143553 | BQ51: 7.6478182 | BR51: 2.3504972 | BS51: 10.200764 | BT51: 2.2660369 | BU51: 6.3145153 | BV51: 7.0224788 | BW51: 4.6461627 | BX51: 10.096636 | BY51: 3.0250288 | BZ51: 7.9169543 | CA51: 4.1226727 | CB51: 2.1796818 | CC51: 3.964018 | CD51: 7.9347269
A52: 99 | B52: 99 | C52: 2 | D52: HFpEF | E52: 10642 | F52: YES | G52: YES | H52: 66 | I52: 36.50622 | J52: 0 | K52: 2 | L52: 0 | M52: 54 | N52: 80.26 | O52: 199.40723 | P52: 1994 | Q52: 44 | R52: 42.698247 | S52: 16.919192 | T52: 35.5 | U52: -21.45 | V52: 62.763105 | W52: 30.343162 | X52: 62.1321 | Y52: =VLOOKUP($A:$A,Variables_extraites!$A:$AD,7,FALSE) -> 0 | Z52: =VLOOKUP($A:$A,Variables_extraites!$A:$AD,8,FALSE) -> 1 | AA52: =VLOOKUP($A:$A,Variables_extraites!$A:$AD,9,FALSE) -> 12.1 | AB52: =VLOOKUP($A:$A,Variables_extraites!$A:$AD,10,FALSE) -> 1 | AC52: =VLOOKUP($A:$A,Variables_extraites!$A:$AD,11,FALSE) -> 0 | AD52: =VLOOKUP($A:$A,Variables_extraites!$A:$AD,12,FALSE) -> 1 | AE52: =VLOOKUP($A:$A,Variables_extraites!$A:$AD,13,FALSE) -> 59.524607 | AF52: =VLOOKUP($A:$A,Variables_extraites!$A:$AD,14,FALSE) -> NA | AG52: =VLOOKUP($A:$A,Variables_extraites!$A:$AD,15,FALSE) -> 16.666667 | AH52: =VLOOKUP($A:$A,Variables_extraites!$A:$AD,16,FALSE) -> 99 | AI52: =VLOOKUP($A:$A,Variables_extraites!$A:$AD,17,FALSE) -> 42409 | AJ52: =VLOOKUP($A:$A,Variables_extraites!$A:$AD,18,FALSE) -> 43481 | AK52: =VLOOKUP($A:$A,Variables_extraites!$A:$AD,19,FALSE) -> 0 | AL52: =VLOOKUP($A:$A,Variables_extraites!$A:$AD,20,FALSE) -> 43481 | AM52: =VLOOKUP($A:$A,Variables_extraites!$A:$AD,21,FALSE) -> 35 | AN52: =VLOOKUP($A:$A,Variables_extraites!$A:$AD,22,FALSE) -> 0 | AO52: =VLOOKUP($A:$A,Variables_extraites!$A:$AD,23,FALSE) -> 43481 | AP52: =VLOOKUP($A:$A,Variables_extraites!$A:$AD,24,FALSE) -> 35 | AQ52: =VLOOKUP($A:$A,Variables_extraites!$A:$AD,25,FALSE) -> 0 | AR52: =VLOOKUP($A:$A,Variables_extraites!$A:$AD,26,FALSE) -> 43481 | AS52: =VLOOKUP($A:$A,Variables_extraites!$A:$AD,27,FALSE) -> 35 | AT52: =VLOOKUP($A:$A,Variables_extraites!$A:$AD,28,FALSE) -> 35 | AU52: =VLOOKUP($A:$A,Variables_extraites!$A:$AD,29,FALSE) -> 1072 | AV52: =VLOOKUP($A:$A,Variables_extraites!$A:$AD,30,FALSE) -> -22.336667 | AW52: 7.7012718 | AX52: 8.1065368 | AY52: 5.1711267 | AZ52: 2.1890338 | BA52: 7.8420989 | BB52: 6.0853397 | BC52: 8.9734678 | BD52: 7.6058499 | BE52: 5.9576825 | BF52: 1.5310695 | BG52: 7.1083154 | BH52: 7.2801212 | BI52: 7.8126907 | BJ52: 4.7803101 | BK52: 6.3050585 | BL52: 7.7944809 | BM52: 6.0895829 | BN52: 6.5179056 | BO52: 5.7043187 | BP52: 6.4075227 | BQ52: 8.2115477 | BR52: 6.6758159 | BS52: 11.423468 | BT52: 3.6496155 | BU52: 7.6829244 | BV52: 6.5402443 | BW52: 4.4114262 | BX52: 9.3682445 | BY52: 3.117695 | BZ52: 7.8146145 | CA52: 3.8855744 | CB52: 1.55363 | CC52: 1.0071084 | CD52: 7.7738524
A53: 101 | B53: 101 | C53: 2 | D53: HFpEF | E53: 10513 | F53: YES | G53: YES | H53: 81 | I53: 21.91358 | J53: 0 | K53: 3 | L53: 0 | M53: 59 | N53: 63.57 | O53: 142.47508 | P53: 1056 | Q53: 28 | R53: 56.042023 | S53: 41.296296 | T53: 41 | V53: 94.628085 | W53: 39.033982 | X53: 66.1067 | Y53: =VLOOKUP($A:$A,Variables_extraites!$A:$AD,7,FALSE) -> 0 | Z53: =VLOOKUP($A:$A,Variables_extraites!$A:$AD,8,FALSE) -> 0 | AA53: =VLOOKUP($A:$A,Variables_extraites!$A:$AD,9,FALSE) -> 14.4 | AB53: =VLOOKUP($A:$A,Variables_extraites!$A:$AD,10,FALSE) -> 1 | AC53: =VLOOKUP($A:$A,Variables_extraites!$A:$AD,11,FALSE) -> 0 | AD53: =VLOOKUP($A:$A,Variables_extraites!$A:$AD,12,FALSE) -> 1 | AE53: =VLOOKUP($A:$A,Variables_extraites!$A:$AD,13,FALSE) -> 54.863356 | AF53: =VLOOKUP($A:$A,Variables_extraites!$A:$AD,14,FALSE) -> NA | AG53: =VLOOKUP($A:$A,Variables_extraites!$A:$AD,15,FALSE) -> 12.333333 | AH53: =VLOOKUP($A:$A,Variables_extraites!$A:$AD,16,FALSE) -> NA | AI53: =VLOOKUP($A:$A,Variables_extraites!$A:$AD,17,FALSE) -> 42390 | AJ53: =VLOOKUP($A:$A,Variables_extraites!$A:$AD,18,FALSE) -> 43486 | AK53: =VLOOKUP($A:$A,Variables_extraites!$A:$AD,19,FALSE) -> 1 | AL53: =VLOOKUP($A:$A,Variables_extraites!$A:$AD,20,FALSE) -> 43486 | AM53: =VLOOKUP($A:$A,Variables_extraites!$A:$AD,21,FALSE) -> 36 | AN53: =VLOOKUP($A:$A,Variables_extraites!$A:$AD,22,FALSE) -> 0 | AO53: =VLOOKUP($A:$A,Variables_extraites!$A:$AD,23,FALSE) -> 43486 | AP53: =VLOOKUP($A:$A,Variables_extraites!$A:$AD,24,FALSE) -> 36 | AQ53: =VLOOKUP($A:$A,Variables_extraites!$A:$AD,25,FALSE) -> 1 | AR53: =VLOOKUP($A:$A,Variables_extraites!$A:$AD,26,FALSE) -> 43486 | AS53: =VLOOKUP($A:$A,Variables_extraites!$A:$AD,27,FALSE) -> 36 | AT53: =VLOOKUP($A:$A,Variables_extraites!$A:$AD,28,FALSE) -> 36 | AU53: =VLOOKUP($A:$A,Variables_extraites!$A:$AD,29,FALSE) -> 1096 | AV53: =VLOOKUP($A:$A,Variables_extraites!$A:$AD,30,FALSE) -> NA | AW53: 8.7971751 | AX53: 8.211645 | AY53: 5.77426 | AZ53: 2.6780719 | BA53: 7.2061353 | BB53: 6.1811026 | BC53: 9.2474529 | BD53: 8.1092038 | BE53: 6.5145957 | BF53: 2.3362834 | BG53: 6.8582297 | BH53: 7.2061353 | BI53: 7.9550686 | BJ53: 5.2467881 | BK53: 6.5957423 | BL53: 7.982138 | BM53: 6.6872007 | BN53: 7.7992816 | BO53: 6.9932215 | BP53: 7.2014378 | BQ53: 8.2829957 | BR53: 3.082362 | BS53: 9.6466127 | BT53: 1.7484612 | BU53: 4.5975312 | BV53: 6.6049609 | BW53: 4.2555007 | BX53: 10.291355 | BY53: 3.0071955 | BZ53: 8.1024482 | CA53: 4.1051752 | CB53: 2.1889067 | CC53: 1.5151692 | CD53: 7.8981515
A54: 103 | B54: 103 | C54: 2 | D54: HFpEF | E54: 10437 | F54: YES | H54: 83 | I54: 39.958377 | J54: 1 | K54: 3 | L54: 0 | M54: 67 | N54: 44 | O54: 284.66347 | P54: 2219 | Q54: 38 | R54: 36.758081 | S54: 20.348837 | T54: 38 | U54: -16.85 | X54: 37.652 | Y54: =VLOOKUP($A:$A,Variables_extraites!$A:$AD,7,FALSE) -> 0 | Z54: =VLOOKUP($A:$A,Variables_extraites!$A:$AD,8,FALSE) -> 0 | AA54: =VLOOKUP($A:$A,Variables_extraites!$A:$AD,9,FALSE) -> 13.1 | AB54: =VLOOKUP($A:$A,Variables_extraites!$A:$AD,10,FALSE) -> 1 | AC54: =VLOOKUP($A:$A,Variables_extraites!$A:$AD,11,FALSE) -> 0 | AD54: =VLOOKUP($A:$A,Variables_extraites!$A:$AD,12,FALSE) -> 1 | AE54: =VLOOKUP($A:$A,Variables_extraites!$A:$AD,13,FALSE) -> 54.083485 | AF54: =VLOOKUP($A:$A,Variables_extraites!$A:$AD,14,FALSE) -> 1.8004115 | AG54: =VLOOKUP($A:$A,Variables_extraites!$A:$AD,15,FALSE) -> 16.5 | AH54: =VLOOKUP($A:$A,Variables_extraites!$A:$AD,16,FALSE) -> 103 | AI54: =VLOOKUP($A:$A,Variables_extraites!$A:$AD,17,FALSE) -> 42389 | AJ54: =VLOOKUP($A:$A,Variables_extraites!$A:$AD,18,FALSE) -> 42858 | AK54: =VLOOKUP($A:$A,Variables_extraites!$A:$AD,19,FALSE) -> 0 | AL54: =VLOOKUP($A:$A,Variables_extraites!$A:$AD,20,FALSE) -> 42858 | AM54: =VLOOKUP($A:$A,Variables_extraites!$A:$AD,21,FALSE) -> 15 | AN54: =VLOOKUP($A:$A,Variables_extraites!$A:$AD,22,FALSE) -> 0 | AO54: =VLOOKUP($A:$A,Variables_extraites!$A:$AD,23,FALSE) -> 42858 | AP54: =VLOOKUP($A:$A,Variables_extraites!$A:$AD,24,FALSE) -> 15 | AQ54: =VLOOKUP($A:$A,Variables_extraites!$A:$AD,25,FALSE) -> 0 | AR54: =VLOOKUP($A:$A,Variables_extraites!$A:$AD,26,FALSE) -> 42858 | AS54: =VLOOKUP($A:$A,Variables_extraites!$A:$AD,27,FALSE) -> 15 | AT54: =VLOOKUP($A:$A,Variables_extraites!$A:$AD,28,FALSE) -> 15.42 | AU54: =VLOOKUP($A:$A,Variables_extraites!$A:$AD,29,FALSE) -> 469 | AV54: =VLOOKUP($A:$A,Variables_extraites!$A:$AD,30,FALSE) -> -12.42
A55: 107 | B55: 107 | C55: 2 | D55: HFpEF | E55: 10551 | F55: YES | H55: 83 | I55: 26.54321 | J55: 0 | K55: 2 | L55: 0 | M55: 64 | N55: 32.2 | O55: 45.793893 | P55: 749.7 | Q55: 30 | R55: 49.302088 | S55: 25.578947 | T55: 25 | U55: -19.17 | V55: 94.735439 | W55: 29.262239 | X55: 90.0559 | Y55: =VLOOKUP($A:$A,Variables_extraites!$A:$AD,7,FALSE) -> 0 | Z55: =VLOOKUP($A:$A,Variables_extraites!$A:$AD,8,FALSE) -> 0 | AA55: =VLOOKUP($A:$A,Variables_extraites!$A:$AD,9,FALSE) -> 12.1 | AB55: =VLOOKUP($A:$A,Variables_extraites!$A:$AD,10,FALSE) -> NA | AC55: =VLOOKUP($A:$A,Variables_extraites!$A:$AD,11,FALSE) -> 0 | AD55: =VLOOKUP($A:$A,Variables_extraites!$A:$AD,12,FALSE) -> 1 | AE55: =VLOOKUP($A:$A,Variables_extraites!$A:$AD,13,FALSE) -> 64.242771 | AF55: =VLOOKUP($A:$A,Variables_extraites!$A:$AD,14,FALSE) -> 1.5379747 | AG55: =VLOOKUP($A:$A,Variables_extraites!$A:$AD,15,FALSE) -> 20 | AH55: =VLOOKUP($A:$A,Variables_extraites!$A:$AD,16,FALSE) -> 107 | AI55: =VLOOKUP($A:$A,Variables_extraites!$A:$AD,17,FALSE) -> 42465 | AJ55: =VLOOKUP($A:$A,Variables_extraites!$A:$AD,18,FALSE) -> 43290 | AK55: =VLOOKUP($A:$A,Variables_extraites!$A:$AD,19,FALSE) -> 0 | AL55: =VLOOKUP($A:$A,Variables_extraites!$A:$AD,20,FALSE) -> 43290 | AM55: =VLOOKUP($A:$A,Variables_extraites!$A:$AD,21,FALSE) -> 27 | AN55: =VLOOKUP($A:$A,Variables_extraites!$A:$AD,22,FALSE) -> 0 | AO55: =VLOOKUP($A:$A,Variables_extraites!$A:$AD,23,FALSE) -> 43290 | AP55: =VLOOKUP($A:$A,Variables_extraites!$A:$AD,24,FALSE) -> 27 | AQ55: =VLOOKUP($A:$A,Variables_extraites!$A:$AD,25,FALSE) -> 0 | AR55: =VLOOKUP($A:$A,Variables_extraites!$A:$AD,26,FALSE) -> 43290 | AS55: =VLOOKUP($A:$A,Variables_extraites!$A:$AD,27,FALSE) -> 27 | AT55: =VLOOKUP($A:$A,Variables_extraites!$A:$AD,28,FALSE) -> 27 | AU55: =VLOOKUP($A:$A,Variables_extraites!$A:$AD,29,FALSE) -> 825 | AV55: =VLOOKUP($A:$A,Variables_extraites!$A:$AD,30,FALSE) -> -29.28
A56: 109 | B56: 109 | C56: 2 | D56: HFpEF | E56: 10475 | F56: YES | G56: YES | H56: 75 | I56: 25.711662 | J56: 0 | K56: 3 | L56: 0 | M56: 67 | N56: 26.13 | O56: 98.988132 | P56: 887.1 | Q56: 31 | R56: 127.02147 | T56: 41 | U56: -15.69 | V56: 108.41575 | W56: 26.517297 | X56: 48.8422 | Y56: =VLOOKUP($A:$A,Variables_extraites!$A:$AD,7,FALSE) -> 0 | Z56: =VLOOKUP($A:$A,Variables_extraites!$A:$AD,8,FALSE) -> 0 | AA56: =VLOOKUP($A:$A,Variables_extraites!$A:$AD,9,FALSE) -> 12 | AB56: =VLOOKUP($A:$A,Variables_extraites!$A:$AD,10,FALSE) -> 1 | AC56: =VLOOKUP($A:$A,Variables_extraites!$A:$AD,11,FALSE) -> 1 | AD56: =VLOOKUP($A:$A,Variables_extraites!$A:$AD,12,FALSE) -> 1 | AE56: =VLOOKUP($A:$A,Variables_extraites!$A:$AD,13,FALSE) -> 71.462264 | AF56: =VLOOKUP($A:$A,Variables_extraites!$A:$AD,14,FALSE) -> NA | AG56: =VLOOKUP($A:$A,Variables_extraites!$A:$AD,15,FALSE) -> 16.5 | AH56: =VLOOKUP($A:$A,Variables_extraites!$A:$AD,16,FALSE) -> 109 | AI56: =VLOOKUP($A:$A,Variables_extraites!$A:$AD,17,FALSE) -> 42411 | AJ56: =VLOOKUP($A:$A,Variables_extraites!$A:$AD,18,FALSE) -> 43060 | AK56: =VLOOKUP($A:$A,Variables_extraites!$A:$AD,19,FALSE) -> 0 | AL56: =VLOOKUP($A:$A,Variables_extraites!$A:$AD,20,FALSE) -> 43060 | AM56: =VLOOKUP($A:$A,Variables_extraites!$A:$AD,21,FALSE) -> 21 | AN56: =VLOOKUP($A:$A,Variables_extraites!$A:$AD,22,FALSE) -> 0 | AO56: =VLOOKUP($A:$A,Variables_extraites!$A:$AD,23,FALSE) -> 43060 | AP56: =VLOOKUP($A:$A,Variables_extraites!$A:$AD,24,FALSE) -> 21 | AQ56: =VLOOKUP($A:$A,Variables_extraites!$A:$AD,25,FALSE) -> 0 | AR56: =VLOOKUP($A:$A,Variables_extraites!$A:$AD,26,FALSE) -> 43060 | AS56: =VLOOKUP($A:$A,Variables_extraites!$A:$AD,27,FALSE) -> 21 | AT56: =VLOOKUP($A:$A,Variables_extraites!$A:$AD,28,FALSE) -> 21.3 | AU56: =VLOOKUP($A:$A,Variables_extraites!$A:$AD,29,FALSE) -> 649 | AV56: =VLOOKUP($A:$A,Variables_extraites!$A:$AD,30,FALSE) -> -24.623333 | AW56: 8.8367447 | AX56: 7.390083 | AY56: 5.457463 | AZ56: 1.3504972 | BA56: 6.9734965 | BB56: 5.4005379 | BC56: 9.3665626 | BD56: 8.1678697 | BE56: 6.3988292 | BF56: 0.66902677 | BG56: 5.4336272 | BH56: 6.6315409 | BI56: 7.8644957 | BJ56: 4.3694665 | BK56: 5.844235 | BL56: 8.6817655 | BM56: 5.9406366 | BN56: 6.7165794 | BO56: 5.5366746 | BP56: 5.7395781 | BQ56: 7.949068 | BR56: 2.4462562 | BS56: 10.642819 | BT56: 3.9560567 | BU56: 4.6604951 | BV56: 6.1303131 | BW56: 4.6299394 | BX56: 10.714623 | BY56: 2.8559897 | BZ56: 9.1021857 | CA56: 3.8688843 | CB56: 1.6124376 | CC56: 2.2142389 | CD56: 6.6867622
A57: 110 | B57: 110 | C57: 2 | D57: HFpEF | E57: 10438 | F57: YES | G57: YES | H57: 74 | I57: 23.140496 | J57: 1 | K57: 2 | L57: 0 | M57: 53 | N57: 12.15 | O57: 306.41537 | P57: 1201 | Q57: 20 | R57: 42.51778 | S57: 11.213873 | T57: 24 | U57: -17.046667 | V57: 52.382605 | W57: 29.485004 | X57: 54.3255 | Y57: =VLOOKUP($A:$A,Variables_extraites!$A:$AD,7,FALSE) -> 0 | Z57: =VLOOKUP($A:$A,Variables_extraites!$A:$AD,8,FALSE) -> 0 | AA57: =VLOOKUP($A:$A,Variables_extraites!$A:$AD,9,FALSE) -> 11.2 | AB57: =VLOOKUP($A:$A,Variables_extraites!$A:$AD,10,FALSE) -> 1 | AC57: =VLOOKUP($A:$A,Variables_extraites!$A:$AD,11,FALSE) -> 0 | AD57: =VLOOKUP($A:$A,Variables_extraites!$A:$AD,12,FALSE) -> 1 | AE57: =VLOOKUP($A:$A,Variables_extraites!$A:$AD,13,FALSE) -> 66.685052 | AF57: =VLOOKUP($A:$A,Variables_extraites!$A:$AD,14,FALSE) -> NA | AG57: =VLOOKUP($A:$A,Variables_extraites!$A:$AD,15,FALSE) -> 19 | AH57: =VLOOKUP($A:$A,Variables_extraites!$A:$AD,16,FALSE) -> 110 | AI57: =VLOOKUP($A:$A,Variables_extraites!$A:$AD,17,FALSE) -> 42423 | AJ57: =VLOOKUP($A:$A,Variables_extraites!$A:$AD,18,FALSE) -> 43517 | AK57: =VLOOKUP($A:$A,Variables_extraites!$A:$AD,19,FALSE) -> 0 | AL57: =VLOOKUP($A:$A,Variables_extraites!$A:$AD,20,FALSE) -> 43517 | AM57: =VLOOKUP($A:$A,Variables_extraites!$A:$AD,21,FALSE) -> 35 | AN57: =VLOOKUP($A:$A,Variables_extraites!$A:$AD,22,FALSE) -> 1 | AO57: =VLOOKUP($A:$A,Variables_extraites!$A:$AD,23,FALSE) -> 42798 | AP57: =VLOOKUP($A:$A,Variables_extraites!$A:$AD,24,FALSE) -> 12 | AQ57: =VLOOKUP($A:$A,Variables_extraites!$A:$AD,25,FALSE) -> 1 | AR57: =VLOOKUP($A:$A,Variables_extraites!$A:$AD,26,FALSE) -> 42798 | AS57: =VLOOKUP($A:$A,Variables_extraites!$A:$AD,27,FALSE) -> 12 | AT57: =VLOOKUP($A:$A,Variables_extraites!$A:$AD,28,FALSE) -> 35 | AU57: =VLOOKUP($A:$A,Variables_extraites!$A:$AD,29,FALSE) -> 1094 | AV57: =VLOOKUP($A:$A,Variables_extraites!$A:$AD,30,FALSE) -> -27.223333 | AW57: 8.0645811 | AX57: 7.8171116 | AY57: 5.3230097 | AZ57: 2.2448871 | BA57: 6.8330166 | BB57: 6.4784865 | BC57: 8.9853296 | BD57: 7.8171755 | BE57: 6.2313172 | BF57: 0.90303827 | BG57: 5.7546203 | BH57: 6.7608862 | BI57: 7.3029587 | BJ57: 4.0461418 | BK57: 6.0318804 | BL57: 8.0045014 | BM57: 6.3596617 | BN57: 6.6751102 | BO57: 5.4518705 | BP57: 5.5564294 | BQ57: 7.8544944 | BR57: -0.13606155 | BS57: 10.466342 | BT57: 2.0143553 | BU57: 7.4418652 | BV57: 6.8858184 | BW57: 4.9791108 | BX57: 10.218745 | BY57: 3.3204847 | BZ57: 7.5134907 | CA57: 4.0780974 | CB57: 2.7052541 | CC57: 7.5779268 | CD57: 8.4519863
A58: 111 | B58: 111 | C58: 2 | D58: HFpEF | E58: 10339 | F58: YES | H58: 85 | I58: 25.605536 | J58: 1 | K58: 2 | L58: 1 | M58: 32 | N58: 250 | O58: 330.49724 | P58: 2701 | Q58: 18 | S58: 17.04 | T58: 24 | U58: -19.136667 | V58: 63.084994 | W58: 33.250836 | X58: 204.4937 | Y58: =VLOOKUP($A:$A,Variables_extraites!$A:$AD,7,FALSE) -> 0 | Z58: =VLOOKUP($A:$A,Variables_extraites!$A:$AD,8,FALSE) -> 0 | AA58: =VLOOKUP($A:$A,Variables_extraites!$A:$AD,9,FALSE) -> 13.3 | AB58: =VLOOKUP($A:$A,Variables_extraites!$A:$AD,10,FALSE) -> 1 | AC58: =VLOOKUP($A:$A,Variables_extraites!$A:$AD,11,FALSE) -> 0 | AD58: =VLOOKUP($A:$A,Variables_extraites!$A:$AD,12,FALSE) -> 1 | AE58: =VLOOKUP($A:$A,Variables_extraites!$A:$AD,13,FALSE) -> 77.704722 | AF58: =VLOOKUP($A:$A,Variables_extraites!$A:$AD,14,FALSE) -> NA | AG58: =VLOOKUP($A:$A,Variables_extraites!$A:$AD,15,FALSE) -> 26 | AH58: =VLOOKUP($A:$A,Variables_extraites!$A:$AD,16,FALSE) -> 111 | AI58: =VLOOKUP($A:$A,Variables_extraites!$A:$AD,17,FALSE) -> 42430 | AJ58: =VLOOKUP($A:$A,Variables_extraites!$A:$AD,18,FALSE) -> 42511 | AK58: =VLOOKUP($A:$A,Variables_extraites!$A:$AD,19,FALSE) -> 1 | AL58: =VLOOKUP($A:$A,Variables_extraites!$A:$AD,20,FALSE) -> 42511 | AM58: =VLOOKUP($A:$A,Variables_extraites!$A:$AD,21,FALSE) -> 3 | AN58: =VLOOKUP($A:$A,Variables_extraites!$A:$AD,22,FALSE) -> 0 | AO58: =VLOOKUP($A:$A,Variables_extraites!$A:$AD,23,FALSE) -> 42511 | AP58: =VLOOKUP($A:$A,Variables_extraites!$A:$AD,24,FALSE) -> 2 | AQ58: =VLOOKUP($A:$A,Variables_extraites!$A:$AD,25,FALSE) -> 1 | AR58: =VLOOKUP($A:$A,Variables_extraites!$A:$AD,26,FALSE) -> 42511 | AS58: =VLOOKUP($A:$A,Variables_extraites!$A:$AD,27,FALSE) -> 2 | AT58: =VLOOKUP($A:$A,Variables_extraites!$A:$AD,28,FALSE) -> 2.5 | AU58: =VLOOKUP($A:$A,Variables_extraites!$A:$AD,29,FALSE) -> 81 | AV58: =VLOOKUP($A:$A,Variables_extraites!$A:$AD,30,FALSE) -> NA
A59: 115 | B59: 115 | C59: 2 | D59: HFpEF | E59: 10439 | F59: YES | G59: YES | H59: 84 | I59: 42.165627 | J59: 1 | K59: 3 | L59: 0 | M59: 37 | N59: 35.81 | O59: 207.21747 | P59: 203.3 | Q59: 11 | R59: 24.052646 | S59: 14.625 | T59: 47 | U59: -18.73 | V59: 59.68525 | W59: 24.36603 | X59: 89.8196 | Y59: =VLOOKUP($A:$A,Variables_extraites!$A:$AD,7,FALSE) -> 0 | Z59: =VLOOKUP($A:$A,Variables_extraites!$A:$AD,8,FALSE) -> 1 | AA59: =VLOOKUP($A:$A,Variables_extraites!$A:$AD,9,FALSE) -> 11.9 | AB59: =VLOOKUP($A:$A,Variables_extraites!$A:$AD,10,FALSE) -> 1 | AC59: =VLOOKUP($A:$A,Variables_extraites!$A:$AD,11,FALSE) -> 0 | AD59: =VLOOKUP($A:$A,Variables_extraites!$A:$AD,12,FALSE) -> 0 | AE59: =VLOOKUP($A:$A,Variables_extraites!$A:$AD,13,FALSE) -> 67.038148 | AF59: =VLOOKUP($A:$A,Variables_extraites!$A:$AD,14,FALSE) -> 0.86666667 | AG59: =VLOOKUP($A:$A,Variables_extraites!$A:$AD,15,FALSE) -> 22 | AH59: =VLOOKUP($A:$A,Variables_extraites!$A:$AD,16,FALSE) -> 115 | AI59: =VLOOKUP($A:$A,Variables_extraites!$A:$AD,17,FALSE) -> 42443 | AJ59: =VLOOKUP($A:$A,Variables_extraites!$A:$AD,18,FALSE) -> 43478 | AK59: =VLOOKUP($A:$A,Variables_extraites!$A:$AD,19,FALSE) -> 0 | AL59: =VLOOKUP($A:$A,Variables_extraites!$A:$AD,20,FALSE) -> 43478 | AM59: =VLOOKUP($A:$A,Variables_extraites!$A:$AD,21,FALSE) -> 33 | AN59: =VLOOKUP($A:$A,Variables_extraites!$A:$AD,22,FALSE) -> 0 | AO59: =VLOOKUP($A:$A,Variables_extraites!$A:$AD,23,FALSE) -> 43478 | AP59: =VLOOKUP($A:$A,Variables_extraites!$A:$AD,24,FALSE) -> 33 | AQ59: =VLOOKUP($A:$A,Variables_extraites!$A:$AD,25,FALSE) -> 0 | AR59: =VLOOKUP($A:$A,Variables_extraites!$A:$AD,26,FALSE) -> 43478 | AS59: =VLOOKUP($A:$A,Variables_extraites!$A:$AD,27,FALSE) -> 33 | AT59: =VLOOKUP($A:$A,Variables_extraites!$A:$AD,28,FALSE) -> 33 | AU59: =VLOOKUP($A:$A,Variables_extraites!$A:$AD,29,FALSE) -> 1035 | AV59: =VLOOKUP($A:$A,Variables_extraites!$A:$AD,30,FALSE) -> -22.12 | AW59: 9.1041007 | AX59: 7.7338966 | AY59: 5.6345933 | AZ59: 2.929791 | BA59: 7.3779046 | BB59: 6.6293566 | BC59: 9.0747837 | BD59: 7.9968971 | BE59: 6.3895668 | BF59: 1.3785116 | BG59: 7.1344263 | BH59: 7.4510462 | BI59: 8.2167944 | BJ59: 5.412104 | BK59: 6.3504972 | BL59: 8.4211391 | BM59: 6.3517343 | BN59: 7.2667865 | BO59: 6.1775192 | BP59: 6.6380738 | BQ59: 8.501479 | BR59: 1.9781956 | BS59: 11.131137 | BT59: 2.3645724 | BU59: 4.6088092 | BV59: 6.3971184 | BW59: 5.1679199 | BX59: 10.833278 | BY59: 3.5570424 | BZ59: 8.4232 | CA59: 4.2913089 | CB59: 2.4100776 | CC59: 2.6306136 | CD59: 8.7665643
A60: 118 | B60: 118 | C60: 2 | D60: HFpEF | E60: 10370 | F60: YES | G60: YES | H60: 72 | I60: 49.947971 | J60: 1 | K60: 3 | L60: 1 | M60: 37 | N60: 94.49 | O60: 154.62813 | P60: 1046 | Q60: 34 | R60: 33.079872 | S60: 20.14 | T60: 22 | U60: -14.45 | V60: 77.530951 | W60: 32.827471 | X60: 107.0717 | Y60: =VLOOKUP($A:$A,Variables_extraites!$A:$AD,7,FALSE) -> 0 | Z60: =VLOOKUP($A:$A,Variables_extraites!$A:$AD,8,FALSE) -> 0 | AA60: =VLOOKUP($A:$A,Variables_extraites!$A:$AD,9,FALSE) -> 11.4 | AB60: =VLOOKUP($A:$A,Variables_extraites!$A:$AD,10,FALSE) -> 1 | AC60: =VLOOKUP($A:$A,Variables_extraites!$A:$AD,11,FALSE) -> 0 | AD60: =VLOOKUP($A:$A,Variables_extraites!$A:$AD,12,FALSE) -> 1 | AE60: =VLOOKUP($A:$A,Variables_extraites!$A:$AD,13,FALSE) -> 56.108949 | AF60: =VLOOKUP($A:$A,Variables_extraites!$A:$AD,14,FALSE) -> 0.86437768 | AG60: =VLOOKUP($A:$A,Variables_extraites!$A:$AD,15,FALSE) -> 20 | AH60: =VLOOKUP($A:$A,Variables_extraites!$A:$AD,16,FALSE) -> 118 | AI60: =VLOOKUP($A:$A,Variables_extraites!$A:$AD,17,FALSE) -> 42458 | AJ60: =VLOOKUP($A:$A,Variables_extraites!$A:$AD,18,FALSE) -> 43318 | AK60: =VLOOKUP($A:$A,Variables_extraites!$A:$AD,19,FALSE) -> 0 | AL60: =VLOOKUP($A:$A,Variables_extraites!$A:$AD,20,FALSE) -> 43318 | AM60: =VLOOKUP($A:$A,Variables_extraites!$A:$AD,21,FALSE) -> 28 | AN60: =VLOOKUP($A:$A,Variables_extraites!$A:$AD,22,FALSE) -> 1 | AO60: =VLOOKUP($A:$A,Variables_extraites!$A:$AD,23,FALSE) -> 42714 | AP60: =VLOOKUP($A:$A,Variables_extraites!$A:$AD,24,FALSE) -> 8 | AQ60: =VLOOKUP($A:$A,Variables_extraites!$A:$AD,25,FALSE) -> 1 | AR60: =VLOOKUP($A:$A,Variables_extraites!$A:$AD,26,FALSE) -> 42714 | AS60: =VLOOKUP($A:$A,Variables_extraites!$A:$AD,27,FALSE) -> 8 | AT60: =VLOOKUP($A:$A,Variables_extraites!$A:$AD,28,FALSE) -> 28 | AU60: =VLOOKUP($A:$A,Variables_extraites!$A:$AD,29,FALSE) -> 860 | AV60: =VLOOKUP($A:$A,Variables_extraites!$A:$AD,30,FALSE) -> -17.96 | AW60: 8.4540113 | AX60: 6.2366839 | AY60: 4.9020736 | AZ60: 1.7092906 | BA60: 7.5662063 | BB60: 5.815063 | BC60: 8.7181218 | BD60: 7.2973749 | BE60: 5.6965503 | BF60: 2.2839218 | BG60: 6.2671612 | BH60: 6.5686402 | BI60: 7.4407031 | BJ60: 4.0452682 | BK60: 5.3981451 | BL60: 7.5717526 | BM60: 5.582556 | BN60: 6.3296618 | BO60: 5.3359262 | BP60: 5.3561438 | BQ60: 8.0148574 | BR60: 2.5459684 | BS60: 11.481794 | BT60: 2.8217102 | BU60: 6.0123452 | BV60: 6.5122269 | BW60: 4.5631581 | BX60: 10.41311 | BY60: 3.2433644 | BZ60: 7.8745511 | CA60: 4.0152478 | CB60: 2.5385585 | CC60: 3.4663768 | CD60: 8.6600842
A61: 120 | B61: 120 | C61: 2 | D61: HFpEF | E61: 10302 | F61: YES | G61: YES | H61: 69 | I61: 25.631167 | J61: 1 | K61: 2 | L61: 0 | M61: 92 | N61: 17.98 | O61: 116.58162 | P61: 56.6 | Q61: 5 | R61: 35.216261 | S61: 13.56338 | T61: 28 | U61: -20.65 | V61: 45.143298 | W61: 31.793278 | X61: 9.2449 | Y61: =VLOOKUP($A:$A,Variables_extraites!$A:$AD,7,FALSE) -> 0 | Z61: =VLOOKUP($A:$A,Variables_extraites!$A:$AD,8,FALSE) -> 0 | AA61: =VLOOKUP($A:$A,Variables_extraites!$A:$AD,9,FALSE) -> 11.6 | AB61: =VLOOKUP($A:$A,Variables_extraites!$A:$AD,10,FALSE) -> 0 | AC61: =VLOOKUP($A:$A,Variables_extraites!$A:$AD,11,FALSE) -> 1 | AD61: =VLOOKUP($A:$A,Variables_extraites!$A:$AD,12,FALSE) -> 1 | AE61: =VLOOKUP($A:$A,Variables_extraites!$A:$AD,13,FALSE) -> 68.432432 | AF61: =VLOOKUP($A:$A,Variables_extraites!$A:$AD,14,FALSE) -> 1.2377892 | AG61: =VLOOKUP($A:$A,Variables_extraites!$A:$AD,15,FALSE) -> 27 | AH61: =VLOOKUP($A:$A,Variables_extraites!$A:$AD,16,FALSE) -> 120 | AI61: =VLOOKUP($A:$A,Variables_extraites!$A:$AD,17,FALSE) -> 42472 | AJ61: =VLOOKUP($A:$A,Variables_extraites!$A:$AD,18,FALSE) -> 43493 | AK61: =VLOOKUP($A:$A,Variables_extraites!$A:$AD,19,FALSE) -> 0 | AL61: =VLOOKUP($A:$A,Variables_extraites!$A:$AD,20,FALSE) -> 43493 | AM61: =VLOOKUP($A:$A,Variables_extraites!$A:$AD,21,FALSE) -> 33 | AN61: =VLOOKUP($A:$A,Variables_extraites!$A:$AD,22,FALSE) -> 0 | AO61: =VLOOKUP($A:$A,Variables_extraites!$A:$AD,23,FALSE) -> 43493 | AP61: =VLOOKUP($A:$A,Variables_extraites!$A:$AD,24,FALSE) -> 33 | AQ61: =VLOOKUP($A:$A,Variables_extraites!$A:$AD,25,FALSE) -> 0 | AR61: =VLOOKUP($A:$A,Variables_extraites!$A:$AD,26,FALSE) -> 43493 | AS61: =VLOOKUP($A:$A,Variables_extraites!$A:$AD,27,FALSE) -> 33 | AT61: =VLOOKUP($A:$A,Variables_extraites!$A:$AD,28,FALSE) -> 33 | AU61: =VLOOKUP($A:$A,Variables_extraites!$A:$AD,29,FALSE) -> 1021 | AV61: =VLOOKUP($A:$A,Variables_extraites!$A:$AD,30,FALSE) -> -27.88 | AW61: 7.8489984 | AX61: 7.7354545 | AY61: 4.9823091 | AZ61: 1.0840643 | BA61: 7.6634869 | BB61: 5.5188498 | BC61: 9.0502024 | BD61: 7.2697812 | BE61: 6.3275077 | BF61: 0.61353165 | BG61: 5.4931349 | BH61: 5.9852727 | BI61: 7.3420747 | BJ61: 4.1301072 | BK61: 5.600805 | BL61: 6.7121831 | BM61: 5.924575 | BN61: 7.1628948 | BO61: 5.6892992 | BP61: 5.4737869 | BQ61: 7.2762175 | BR61: 3.3146965 | BS61: 9.2103791 | BT61: 1.7570232 | BU61: 6.8618313 | BV61: 6.6435676 | BW61: 5.4087119 | BX61: 10.10397 | BY61: 2.8479969 | BZ61: 8.299437 | CA61: 4.5801455 | CB61: 1.8045326 | CC61: 3.5471348 | CD61: 7.4533559
A62: 122 | B62: 122 | C62: 2 | D62: HFpEF | E62: 10303 | F62: YES | G62: YES | H62: 73 | I62: 29.270994 | J62: 1 | K62: 2 | L62: 0 | M62: 66 | N62: 19.28 | O62: 797.58038 | P62: 718.9 | Q62: 10 | R62: 51.09799 | S62: 29.470199 | T62: 25 | U62: -19.533333 | V62: 54.38367 | W62: 35.066669 | X62: 56.5195 | Y62: =VLOOKUP($A:$A,Variables_extraites!$A:$AD,7,FALSE) -> 0 | Z62: =VLOOKUP($A:$A,Variables_extraites!$A:$AD,8,FALSE) -> 0 | AA62: =VLOOKUP($A:$A,Variables_extraites!$A:$AD,9,FALSE) -> 11.2 | AB62: =VLOOKUP($A:$A,Variables_extraites!$A:$AD,10,FALSE) -> 1 | AC62: =VLOOKUP($A:$A,Variables_extraites!$A:$AD,11,FALSE) -> 1 | AD62: =VLOOKUP($A:$A,Variables_extraites!$A:$AD,12,FALSE) -> 1 | AE62: =VLOOKUP($A:$A,Variables_extraites!$A:$AD,13,FALSE) -> 71.006944 | AF62: =VLOOKUP($A:$A,Variables_extraites!$A:$AD,14,FALSE) -> NA | AG62: =VLOOKUP($A:$A,Variables_extraites!$A:$AD,15,FALSE) -> 11.333333 | AH62: =VLOOKUP($A:$A,Variables_extraites!$A:$AD,16,FALSE) -> 122 | AI62: =VLOOKUP($A:$A,Variables_extraites!$A:$AD,17,FALSE) -> 42471 | AJ62: =VLOOKUP($A:$A,Variables_extraites!$A:$AD,18,FALSE) -> 43493 | AK62: =VLOOKUP($A:$A,Variables_extraites!$A:$AD,19,FALSE) -> 0 | AL62: =VLOOKUP($A:$A,Variables_extraites!$A:$AD,20,FALSE) -> 43493 | AM62: =VLOOKUP($A:$A,Variables_extraites!$A:$AD,21,FALSE) -> 33 | AN62: =VLOOKUP($A:$A,Variables_extraites!$A:$AD,22,FALSE) -> 1 | AO62: =VLOOKUP($A:$A,Variables_extraites!$A:$AD,23,FALSE) -> 42494 | AP62: =VLOOKUP($A:$A,Variables_extraites!$A:$AD,24,FALSE) -> 1 | AQ62: =VLOOKUP($A:$A,Variables_extraites!$A:$AD,25,FALSE) -> 1 | AR62: =VLOOKUP($A:$A,Variables_extraites!$A:$AD,26,FALSE) -> 42494 | AS62: =VLOOKUP($A:$A,Variables_extraites!$A:$AD,27,FALSE) -> 1 | AT62: =VLOOKUP($A:$A,Variables_extraites!$A:$AD,28,FALSE) -> 33 | AU62: =VLOOKUP($A:$A,Variables_extraites!$A:$AD,29,FALSE) -> 1022 | AV62: =VLOOKUP($A:$A,Variables_extraites!$A:$AD,30,FALSE) -> -21.733333 | AW62: 8.6455864 | AX62: 7.3977174 | AY62: 5.7479244 | AZ62: 2.3305584 | BA62: 7.9708537 | BB62: 6.704457 | BC62: 9.3608032 | BD62: 8.0032649 | BE62: 6.2609666 | BF62: 0.92599942 | BG62: 6.1925887 | BH62: 6.8139094 | BI62: 7.8447999 | BJ62: 4.6898582 | BK62: 6.1039172 | BL62: 8.0901124 | BM62: 6.7536848 | BN62: 7.9459705 | BO62: 5.9784245 | BP62: 6.1965284 | BQ62: 8.1938703 | BR62: 3.4918531 | BS62: 11.121391 | BT62: 1.8639385 | BU62: 6.5318493 | BV62: 6.6834157 | BW62: 6.0332027 | BX62: 11.011318 | BY62: 3.1521834 | BZ62: 7.9362257 | CA62: 4.0959244 | CB62: 3.0750924 | CC62: 3.0399962 | CD62: 9.2574526
A63: 123 | B63: 123 | C63: 2 | D63: HFpEF | E63: 10304 | F63: YES | G63: YES | H63: 81 | I63: 33.203125 | J63: 1 | K63: 4 | L63: 0 | M63: 49 | N63: 29.97 | O63: 140.82468 | P63: 581.4 | Q63: 24 | R63: 31.421805 | S63: 11.262443 | T63: 28 | U63: -17.623333 | V63: 52.438667 | W63: 26.131677 | X63: 48.2814 | Y63: =VLOOKUP($A:$A,Variables_extraites!$A:$AD,7,FALSE) -> 0 | Z63: =VLOOKUP($A:$A,Variables_extraites!$A:$AD,8,FALSE) -> 1 | AA63: =VLOOKUP($A:$A,Variables_extraites!$A:$AD,9,FALSE) -> 13.2 | AB63: =VLOOKUP($A:$A,Variables_extraites!$A:$AD,10,FALSE) -> 0 | AC63: =VLOOKUP($A:$A,Variables_extraites!$A:$AD,11,FALSE) -> 0 | AD63: =VLOOKUP($A:$A,Variables_extraites!$A:$AD,12,FALSE) -> 1 | AE63: =VLOOKUP($A:$A,Variables_extraites!$A:$AD,13,FALSE) -> 56.786102 | AF63: =VLOOKUP($A:$A,Variables_extraites!$A:$AD,14,FALSE) -> NA | AG63: =VLOOKUP($A:$A,Variables_extraites!$A:$AD,15,FALSE) -> 16.666667 | AH63: =VLOOKUP($A:$A,Variables_extraites!$A:$AD,16,FALSE) -> 123 | AI63: =VLOOKUP($A:$A,Variables_extraites!$A:$AD,17,FALSE) -> 42471 | AJ63: =VLOOKUP($A:$A,Variables_extraites!$A:$AD,18,FALSE) -> 43409 | AK63: =VLOOKUP($A:$A,Variables_extraites!$A:$AD,19,FALSE) -> 0 | AL63: =VLOOKUP($A:$A,Variables_extraites!$A:$AD,20,FALSE) -> 43409 | AM63: =VLOOKUP($A:$A,Variables_extraites!$A:$AD,21,FALSE) -> 30 | AN63: =VLOOKUP($A:$A,Variables_extraites!$A:$AD,22,FALSE) -> 1 | AO63: =VLOOKUP($A:$A,Variables_extraites!$A:$AD,23,FALSE) -> 43348 | AP63: =VLOOKUP($A:$A,Variables_extraites!$A:$AD,24,FALSE) -> 28 | AQ63: =VLOOKUP($A:$A,Variables_extraites!$A:$AD,25,FALSE) -> 1 | AR63: =VLOOKUP($A:$A,Variables_extraites!$A:$AD,26,FALSE) -> 43348 | AS63: =VLOOKUP($A:$A,Variables_extraites!$A:$AD,27,FALSE) -> 28 | AT63: =VLOOKUP($A:$A,Variables_extraites!$A:$AD,28,FALSE) -> 30 | AU63: =VLOOKUP($A:$A,Variables_extraites!$A:$AD,29,FALSE) -> 938 | AV63: =VLOOKUP($A:$A,Variables_extraites!$A:$AD,30,FALSE) -> -20.246667 | AW63: 8.5208151 | AX63: 7.1649069 | AY63: 5.5659018 | AZ63: 2.0806577 | BA63: 8.1113444 | BB63: 6.0127921 | BC63: 9.3269238 | BD63: 7.4771106 | BE63: 6.2935176 | BF63: 1 | BG63: 6.5191644 | BH63: 7.3660599 | BI63: 8.02597 | BJ63: 4.892391 | BK63: 6.4538468 | BL63: 8.3526173 | BM63: 6.4492312 | BN63: 7.2368752 | BO63: 5.8833764 | BP63: 6.3489052 | BQ63: 8.4122311 | BR63: 4.4679315 | BS63: 11.036922 | BT63: 2.2448871 | BU63: 6.9328643 | BV63: 6.4075227 | BW63: 5.4495614 | BX63: 10.910853 | BY63: 3.0054 | BZ63: 8.1272721 | CA63: 4.2024177 | CB63: 2.7835804 | CC63: 2.4649328 | CD63: 8.7920352
A64: 124 | B64: 124 | C64: 2 | D64: HFpEF | E64: 10476 | F64: YES | G64: YES | H64: 85 | I64: 27.131412 | J64: 0 | K64: 3 | L64: 0 | M64: 66 | N64: 10.4 | O64: 330.51024 | P64: 915.7 | Q64: 28 | R64: 57.567311 | S64: 16.517045 | T64: 26 | U64: -21.543333 | V64: 79.289685 | W64: 30.38674 | X64: 40.4585 | Y64: =VLOOKUP($A:$A,Variables_extraites!$A:$AD,7,FALSE) -> 0 | Z64: =VLOOKUP($A:$A,Variables_extraites!$A:$AD,8,FALSE) -> 1 | AA64: =VLOOKUP($A:$A,Variables_extraites!$A:$AD,9,FALSE) -> 10.7 | AB64: =VLOOKUP($A:$A,Variables_extraites!$A:$AD,10,FALSE) -> 1 | AC64: =VLOOKUP($A:$A,Variables_extraites!$A:$AD,11,FALSE) -> 1 | AD64: =VLOOKUP($A:$A,Variables_extraites!$A:$AD,12,FALSE) -> 1 | AE64: =VLOOKUP($A:$A,Variables_extraites!$A:$AD,13,FALSE) -> 71.586826 | AF64: =VLOOKUP($A:$A,Variables_extraites!$A:$AD,14,FALSE) -> NA | AG64: =VLOOKUP($A:$A,Variables_extraites!$A:$AD,15,FALSE) -> 14.333333 | AH64: =VLOOKUP($A:$A,Variables_extraites!$A:$AD,16,FALSE) -> 124 | AI64: =VLOOKUP($A:$A,Variables_extraites!$A:$AD,17,FALSE) -> 42467 | AJ64: =VLOOKUP($A:$A,Variables_extraites!$A:$AD,18,FALSE) -> 43507 | AK64: =VLOOKUP($A:$A,Variables_extraites!$A:$AD,19,FALSE) -> 0 | AL64: =VLOOKUP($A:$A,Variables_extraites!$A:$AD,20,FALSE) -> 43507 | AM64: =VLOOKUP($A:$A,Variables_extraites!$A:$AD,21,FALSE) -> 34 | AN64: =VLOOKUP($A:$A,Variables_extraites!$A:$AD,22,FALSE) -> 1 | AO64: =VLOOKUP($A:$A,Variables_extraites!$A:$AD,23,FALSE) -> 42583 | AP64: =VLOOKUP($A:$A,Variables_extraites!$A:$AD,24,FALSE) -> 3 | AQ64: =VLOOKUP($A:$A,Variables_extraites!$A:$AD,25,FALSE) -> 1 | AR64: =VLOOKUP($A:$A,Variables_extraites!$A:$AD,26,FALSE) -> 42583 | AS64: =VLOOKUP($A:$A,Variables_extraites!$A:$AD,27,FALSE) -> 3 | AT64: =VLOOKUP($A:$A,Variables_extraites!$A:$AD,28,FALSE) -> 34 | AU64: =VLOOKUP($A:$A,Variables_extraites!$A:$AD,29,FALSE) -> 1040 | AV64: =VLOOKUP($A:$A,Variables_extraites!$A:$AD,30,FALSE) -> -19.853333 | AW64: 8.182146 | AX64: 7.8674641 | AY64: 5.2384047 | AZ64: 3.1538053 | BA64: 7.3889644 | BB64: 8.8701489 | BC64: 7.2500141 | BD64: 7.6590683 | BE64: 6.3136087 | BF64: 2.4515408 | BG64: 7.7094974 | BH64: 8.0554451 | BI64: 8.5319272 | BJ64: 5.6322682 | BK64: 6.684398 | BL64: 7.7270355 | BM64: 6.7835876 | BN64: 7.2266049 | BO64: 6.8213276 | BP64: 7.0989795 | BQ64: 8.9001121 | BR64: -1.9378783 | BS64: 9.9481482 | BT64: 2.5680321 | BU64: 5.5993178 | BV64: 6.2412682 | BW64: 4.3132459 | BX64: 9.5911483 | BY64: 2.5704629 | BZ64: 6.5707665 | CA64: 4.1921942 | CB64: 3.0203818 | CC64: 7.5371961 | CD64: 7.3801161
A65: 125 | B65: 125 | C65: 2 | D65: HFpEF | E65: 10548 | F65: YES | G65: YES | H65: 79 | I65: 29.065927 | J65: 0 | K65: 2 | L65: 1 | M65: 32 | N65: 34.07 | O65: 296.62473 | P65: 721.5 | Q65: 66 | R65: 24.328621 | S65: 33.824 | T65: 25.666667 | U65: -10.266667 | V65: 82.680427 | W65: 32.93913 | X65: 131.6439 | Y65: =VLOOKUP($A:$A,Variables_extraites!$A:$AD,7,FALSE) -> 0 | Z65: =VLOOKUP($A:$A,Variables_extraites!$A:$AD,8,FALSE) -> 0 | AA65: =VLOOKUP($A:$A,Variables_extraites!$A:$AD,9,FALSE) -> 13.2 | AB65: =VLOOKUP($A:$A,Variables_extraites!$A:$AD,10,FALSE) -> 0 | AC65: =VLOOKUP($A:$A,Variables_extraites!$A:$AD,11,FALSE) -> 1 | AD65: =VLOOKUP($A:$A,Variables_extraites!$A:$AD,12,FALSE) -> 0 | AE65: =VLOOKUP($A:$A,Variables_extraites!$A:$AD,13,FALSE) -> 62.546957 | AF65: =VLOOKUP($A:$A,Variables_extraites!$A:$AD,14,FALSE) -> 1.6777778 | AG65: =VLOOKUP($A:$A,Variables_extraites!$A:$AD,15,FALSE) -> 13.333333 | AH65: =VLOOKUP($A:$A,Variables_extraites!$A:$AD,16,FALSE) -> 125 | AI65: =VLOOKUP($A:$A,Variables_extraites!$A:$AD,17,FALSE) -> 42476 | AJ65: =VLOOKUP($A:$A,Variables_extraites!$A:$AD,18,FALSE) -> 43059 | AK65: =VLOOKUP($A:$A,Variables_extraites!$A:$AD,19,FALSE) -> 1 | AL65: =VLOOKUP($A:$A,Variables_extraites!$A:$AD,20,FALSE) -> 43059 | AM65: =VLOOKUP($A:$A,Variables_extraites!$A:$AD,21,FALSE) -> 19 | AN65: =VLOOKUP($A:$A,Variables_extraites!$A:$AD,22,FALSE) -> 1 | AO65: =VLOOKUP($A:$A,Variables_extraites!$A:$AD,23,FALSE) -> 42884 | AP65: =VLOOKUP($A:$A,Variables_extraites!$A:$AD,24,FALSE) -> 13 | AQ65: =VLOOKUP($A:$A,Variables_extraites!$A:$AD,25,FALSE) -> 1 | AR65: =VLOOKUP($A:$A,Variables_extraites!$A:$AD,26,FALSE) -> 42884 | AS65: =VLOOKUP($A:$A,Variables_extraites!$A:$AD,27,FALSE) -> 13 | AT65: =VLOOKUP($A:$A,Variables_extraites!$A:$AD,28,FALSE) -> 19 | AU65: =VLOOKUP($A:$A,Variables_extraites!$A:$AD,29,FALSE) -> 583 | AV65: =VLOOKUP($A:$A,Variables_extraites!$A:$AD,30,FALSE) -> -12.97 | AW65: 8.5252076 | AX65: 7.4500565 | AY65: 5.4950555 | AZ65: 0.81885056 | BA65: 6.7284648 | BB65: 5.308157 | BC65: 9.1654598 | BD65: 7.2945289 | BE65: 6.0931798 | BF65: 0.59454855 | BG65: 7.0901124 | BH65: 7.4887239 | BI65: 8.0842238 | BJ65: 4.8782349 | BK65: 6.3030501 | BL65: 8.2484494 | BM65: 5.785289 | BN65: 7.082362 | BO65: 6.0763881 | BP65: 6.5637683 | BQ65: 8.5930549 | BR65: 1.7355222 | BS65: 10.665727 | BT65: 3.1407787 | BU65: 5.4741115 | BV65: 6.2033969 | BW65: 4.7009945 | BX65: 10.583694 | BY65: 2.9781956 | BZ65: 8.7105654 | CA65: 3.7516779 | CB65: 1.8731286 | CC65: 3.7385893 | CD65: 7.5249481
A66: 126 | B66: 126 | C66: 2 | D66: HFpEF | E66: 10440 | F66: YES | H66: 67 | I66: 36.730946 | J66: 1 | K66: 2 | L66: 1 | M66: 64 | N66: 83.18 | O66: 842.48885 | P66: 189.8 | Q66: 23 | R66: 41.269778 | S66: 11.246696 | T66: 20.666667 | U66: -16.25 | X66: 90.0948 | Y66: =VLOOKUP($A:$A,Variables_extraites!$A:$AD,7,FALSE) -> 0 | Z66: =VLOOKUP($A:$A,Variables_extraites!$A:$AD,8,FALSE) -> 1, àconfirmer | AA66: =VLOOKUP($A:$A,Variables_extraites!$A:$AD,9,FALSE) -> 13.8 | AB66: =VLOOKUP($A:$A,Variables_extraites!$A:$AD,10,FALSE) -> 1 | AC66: =VLOOKUP($A:$A,Variables_extraites!$A:$AD,11,FALSE) -> 0 | AD66: =VLOOKUP($A:$A,Variables_extraites!$A:$AD,12,FALSE) -> 1 | AE66: =VLOOKUP($A:$A,Variables_extraites!$A:$AD,13,FALSE) -> 66.688633 | AF66: =VLOOKUP($A:$A,Variables_extraites!$A:$AD,14,FALSE) -> NA | AG66: =VLOOKUP($A:$A,Variables_extraites!$A:$AD,15,FALSE) -> 15.333333 | AH66: =VLOOKUP($A:$A,Variables_extraites!$A:$AD,16,FALSE) -> 126 | AI66: =VLOOKUP($A:$A,Variables_extraites!$A:$AD,17,FALSE) -> 42474 | AJ66: =VLOOKUP($A:$A,Variables_extraites!$A:$AD,18,FALSE) -> 42490 | AK66: =VLOOKUP($A:$A,Variables_extraites!$A:$AD,19,FALSE) -> 1 | AL66: =VLOOKUP($A:$A,Variables_extraites!$A:$AD,20,FALSE) -> 42490 | AM66: =VLOOKUP($A:$A,Variables_extraites!$A:$AD,21,FALSE) -> 1 | AN66: =VLOOKUP($A:$A,Variables_extraites!$A:$AD,22,FALSE) -> 0 | AO66: =VLOOKUP($A:$A,Variables_extraites!$A:$AD,23,FALSE) -> 42490 | AP66: =VLOOKUP($A:$A,Variables_extraites!$A:$AD,24,FALSE) -> 1 | AQ66: =VLOOKUP($A:$A,Variables_extraites!$A:$AD,25,FALSE) -> 1 | AR66: =VLOOKUP($A:$A,Variables_extraites!$A:$AD,26,FALSE) -> 42490 | AS66: =VLOOKUP($A:$A,Variables_extraites!$A:$AD,27,FALSE) -> 1 | AT66: =VLOOKUP($A:$A,Variables_extraites!$A:$AD,28,FALSE) -> 0.5 | AU66: =VLOOKUP($A:$A,Variables_extraites!$A:$AD,29,FALSE) -> 16 | AV66: =VLOOKUP($A:$A,Variables_extraites!$A:$AD,30,FALSE) -> -16.826667
A67: 128 | B67: 128 | C67: 2 | D67: HFpEF | E67: 10643 | F67: YES | G67: YES | H67: 82 | I67: 45.703125 | J67: 0 | K67: 2 | L67: 1 | M67: 47 | N67: 32.41 | O67: 134.59751 | P67: 1066 | Q67: 90 | R67: 36.366935 | S67: 21.320755 | T67: 42 | U67: -13.28 | V67: 67.39699 | W67: 36.781746 | X67: 83.2236 | Y67: =VLOOKUP($A:$A,Variables_extraites!$A:$AD,7,FALSE) -> 0 | Z67: =VLOOKUP($A:$A,Variables_extraites!$A:$AD,8,FALSE) -> 1 | AA67: =VLOOKUP($A:$A,Variables_extraites!$A:$AD,9,FALSE) -> 15.6 | AB67: =VLOOKUP($A:$A,Variables_extraites!$A:$AD,10,FALSE) -> 1 | AC67: =VLOOKUP($A:$A,Variables_extraites!$A:$AD,11,FALSE) -> 1 | AD67: =VLOOKUP($A:$A,Variables_extraites!$A:$AD,12,FALSE) -> 0 | AE67: =VLOOKUP($A:$A,Variables_extraites!$A:$AD,13,FALSE) -> 61.294261 | AF67: =VLOOKUP($A:$A,Variables_extraites!$A:$AD,14,FALSE) -> 3.7792642 | AG67: =VLOOKUP($A:$A,Variables_extraites!$A:$AD,15,FALSE) -> 19 | AH67: =VLOOKUP($A:$A,Variables_extraites!$A:$AD,16,FALSE) -> 128 | AI67: =VLOOKUP($A:$A,Variables_extraites!$A:$AD,17,FALSE) -> 42400 | AJ67: =VLOOKUP($A:$A,Variables_extraites!$A:$AD,18,FALSE) -> 43517 | AK67: =VLOOKUP($A:$A,Variables_extraites!$A:$AD,19,FALSE) -> 0 | AL67: =VLOOKUP($A:$A,Variables_extraites!$A:$AD,20,FALSE) -> 43517 | AM67: =VLOOKUP($A:$A,Variables_extraites!$A:$AD,21,FALSE) -> 36 | AN67: =VLOOKUP($A:$A,Variables_extraites!$A:$AD,22,FALSE) -> 1 | AO67: =VLOOKUP($A:$A,Variables_extraites!$A:$AD,23,FALSE) -> 42458 | AP67: =VLOOKUP($A:$A,Variables_extraites!$A:$AD,24,FALSE) -> 2 | AQ67: =VLOOKUP($A:$A,Variables_extraites!$A:$AD,25,FALSE) -> 1 | AR67: =VLOOKUP($A:$A,Variables_extraites!$A:$AD,26,FALSE) -> 42458 | AS67: =VLOOKUP($A:$A,Variables_extraites!$A:$AD,27,FALSE) -> 2 | AT67: =VLOOKUP($A:$A,Variables_extraites!$A:$AD,28,FALSE) -> 36 | AU67: =VLOOKUP($A:$A,Variables_extraites!$A:$AD,29,FALSE) -> 1117 | AV67: =VLOOKUP($A:$A,Variables_extraites!$A:$AD,30,FALSE) -> -22.46 | AW67: 8.0123452 | AX67: 7.5647592 | AY67: 5.0245856 | AZ67: 1.9107327 | BA67: 7.4522824 | BB67: 5.5719801 | BC67: 9.1600731 | BD67: 7.8489984 | BE67: 6.0071955 | BF67: 1.448901 | BG67: 6.5226208 | BH67: 6.9487176 | BI67: 7.5197935 | BJ67: 4.3950628 | BK67: 5.8422246 | BL67: 7.6197798 | BM67: 6.6058499 | BN67: 6.5390037 | BO67: 5.4076926 | BP67: 5.512543 | BQ67: 8.0482144 | BR67: 5.0793781 | BS67: 10.564664 | BT67: 2.707083 | BU67: 8.7267631 | BV67: 6.9691275 | BW67: 4.6707271 | BX67: 10.386897 | BY67: 2.9183862 | BZ67: 7.6727789 | CA67: 3.5147535 | CB67: 2.7141182 | CC67: 3.647385 | CD67: 7.857581
A68: 130 | B68: 130 | C68: 2 | D68: HFpEF | E68: 10371 | F68: YES | G68: YES | H68: 84 | I68: 28.400548 | J68: 1 | K68: 2 | L68: 0 | M68: 60 | N68: 38.53 | O68: 273.93778 | P68: 1714 | Q68: 10 | R68: 38.207307 | S68: 12.972376 | T68: 35.666667 | U68: -16.1 | V68: 49.44562 | W68: 27.970209 | X68: 114.2347 | Y68: =VLOOKUP($A:$A,Variables_extraites!$A:$AD,7,FALSE) -> 1 | Z68: =VLOOKUP($A:$A,Variables_extraites!$A:$AD,8,FALSE) -> 0 | AA68: =VLOOKUP($A:$A,Variables_extraites!$A:$AD,9,FALSE) -> 13.2 | AB68: =VLOOKUP($A:$A,Variables_extraites!$A:$AD,10,FALSE) -> 1 | AC68: =VLOOKUP($A:$A,Variables_extraites!$A:$AD,11,FALSE) -> 0 | AD68: =VLOOKUP($A:$A,Variables_extraites!$A:$AD,12,FALSE) -> 1 | AE68: =VLOOKUP($A:$A,Variables_extraites!$A:$AD,13,FALSE) -> 66.120482 | AF68: =VLOOKUP($A:$A,Variables_extraites!$A:$AD,14,FALSE) -> NA | AG68: =VLOOKUP($A:$A,Variables_extraites!$A:$AD,15,FALSE) -> 16 | AH68: =VLOOKUP($A:$A,Variables_extraites!$A:$AD,16,FALSE) -> 130 | AI68: =VLOOKUP($A:$A,Variables_extraites!$A:$AD,17,FALSE) -> 42492 | AJ68: =VLOOKUP($A:$A,Variables_extraites!$A:$AD,18,FALSE) -> 43054 | AK68: =VLOOKUP($A:$A,Variables_extraites!$A:$AD,19,FALSE) -> 0 | AL68: =VLOOKUP($A:$A,Variables_extraites!$A:$AD,20,FALSE) -> 43054 | AM68: =VLOOKUP($A:$A,Variables_extraites!$A:$AD,21,FALSE) -> 18 | AN68: =VLOOKUP($A:$A,Variables_extraites!$A:$AD,22,FALSE) -> 0 | AO68: =VLOOKUP($A:$A,Variables_extraites!$A:$AD,23,FALSE) -> 43054 | AP68: =VLOOKUP($A:$A,Variables_extraites!$A:$AD,24,FALSE) -> 18 | AQ68: =VLOOKUP($A:$A,Variables_extraites!$A:$AD,25,FALSE) -> 0 | AR68: =VLOOKUP($A:$A,Variables_extraites!$A:$AD,26,FALSE) -> 43054 | AS68: =VLOOKUP($A:$A,Variables_extraites!$A:$AD,27,FALSE) -> 18 | AT68: =VLOOKUP($A:$A,Variables_extraites!$A:$AD,28,FALSE) -> 18.5 | AU68: =VLOOKUP($A:$A,Variables_extraites!$A:$AD,29,FALSE) -> 562 | AV68: =VLOOKUP($A:$A,Variables_extraites!$A:$AD,30,FALSE) -> -19.776667 | AW68: 8.6014365 | AX68: 7.9803681 | AY68: 5.4455943 | AZ68: 1.6915342 | BA68: 7.5551259 | BB68: 5.8262942 | BC68: 9.2214421 | BD68: 7.6932779 | BE68: 6.0891591 | BF68: 1.2570106 | BG68: 6.2768688 | BH68: 6.5690961 | BI68: 7.9639942 | BJ68: 4.8323837 | BK68: 6.1544131 | BL68: 7.4748416 | BM68: 6.3110671 | BN68: 6.9137272 | BO68: 6.1253618 | BP68: 6.5816525 | BQ68: 7.9752175 | BR68: 3.5109619 | BS68: 10.903234 | BT68: 2.9164766 | BU68: 6.5576552 | BV68: 6.8133964 | BW68: 5.8686374 | BX68: 10.494306 | BY68: 3.1407787 | BZ68: 8.1560325 | CA68: 4.3074285 | CB68: 2.3382731 | CC68: 3.0466932 | CD68: 7.9867575
A69: 131 | B69: 131 | C69: 2 | D69: HFpEF | E69: 10608 | F69: YES | G69: YES | H69: 67 | I69: 28.735632 | J69: 0 | K69: 4 | L69: 1 | M69: 58 | N69: 73.98 | O69: 124.09539 | P69: 7884 | Q69: 26 | R69: 47.432779 | S69: 19.311475 | T69: 23.333333 | U69: -7.1166667 | V69: 93.27744 | W69: 29.722648 | X69: 57.0734 | Y69: =VLOOKUP($A:$A,Variables_extraites!$A:$AD,7,FALSE) -> 0 | Z69: =VLOOKUP($A:$A,Variables_extraites!$A:$AD,8,FALSE) -> 0 | AA69: =VLOOKUP($A:$A,Variables_extraites!$A:$AD,9,FALSE) -> 15.2 | AB69: =VLOOKUP($A:$A,Variables_extraites!$A:$AD,10,FALSE) -> 1 | AC69: =VLOOKUP($A:$A,Variables_extraites!$A:$AD,11,FALSE) -> 1 | AD69: =VLOOKUP($A:$A,Variables_extraites!$A:$AD,12,FALSE) -> 0 | AE69: =VLOOKUP($A:$A,Variables_extraites!$A:$AD,13,FALSE) -> 48.070495 | AF69: =VLOOKUP($A:$A,Variables_extraites!$A:$AD,14,FALSE) -> NA | AG69: =VLOOKUP($A:$A,Variables_extraites!$A:$AD,15,FALSE) -> 15.666667 | AH69: =VLOOKUP($A:$A,Variables_extraites!$A:$AD,16,FALSE) -> 131 | AI69: =VLOOKUP($A:$A,Variables_extraites!$A:$AD,17,FALSE) -> 42492 | AJ69: =VLOOKUP($A:$A,Variables_extraites!$A:$AD,18,FALSE) -> NA | AK69: =VLOOKUP($A:$A,Variables_extraites!$A:$AD,19,FALSE) -> NA | AL69: =VLOOKUP($A:$A,Variables_extraites!$A:$AD,20,FALSE) -> NA | AM69: =VLOOKUP($A:$A,Variables_extraites!$A:$AD,21,FALSE) -> NA | AN69: =VLOOKUP($A:$A,Variables_extraites!$A:$AD,22,FALSE) -> NA | AO69: =VLOOKUP($A:$A,Variables_extraites!$A:$AD,23,FALSE) -> NA | AP69: =VLOOKUP($A:$A,Variables_extraites!$A:$AD,24,FALSE) -> NA | AQ69: =VLOOKUP($A:$A,Variables_extraites!$A:$AD,25,FALSE) -> NA | AR69: =VLOOKUP($A:$A,Variables_extraites!$A:$AD,26,FALSE) -> NA | AS69: =VLOOKUP($A:$A,Variables_extraites!$A:$AD,27,FALSE) -> NA | AT69: =VLOOKUP($A:$A,Variables_extraites!$A:$AD,28,FALSE) -> NA | AU69: =VLOOKUP($A:$A,Variables_extraites!$A:$AD,29,FALSE) -> NA | AV69: =VLOOKUP($A:$A,Variables_extraites!$A:$AD,30,FALSE) -> -17.83 | AW69: 7.8782349 | AX69: 7.2225534 | AY69: 4.2979251 | AZ69: 3.0874628 | BA69: 7.4116805 | BB69: 7.3912866 | BC69: 8.0161954 | BD69: 7.3772973 | BE69: 5.0878871 | BF69: 0.43295941 | BG69: 6.6447215 | BH69: 7.1984942 | BI69: 6.9559405 | BJ69: 4.0925457 | BK69: 5.7703005 | BL69: 7.0197019 | BM69: 6.0181445 | BN69: 6.1548181 | BO69: 5.3805909 | BP69: 5.5232483 | BQ69: 8.0970313 | BR69: -1.9378783 | BS69: 10.771721 | BT69: 1.6959938 | BU69: 5.7889467 | BV69: 5.1424134 | BW69: 3.3391374 | BX69: 10.177706 | BY69: 2.5993178 | BZ69: 6.2968245 | CA69: 3.7634116 | CB69: 3.8808816 | CC69: 7.726825 | CD69: 9.0757267
A70: 132 | B70: 132 | C70: 2 | D70: HFpEF | E70: 10647 | F70: YES | G70: YES | H70: 78 | I70: 26.149277 | J70: 0 | K70: 3 | L70: 0 | M70: 71 | N70: 20.9 | O70: 1109.2871 | P70: 2643 | Q70: 34 | R70: 58.722105 | S70: 23.875 | T70: 24 | U70: -18.2 | V70: 65.128105 | W70: 32.940969 | X70: 30.3105 | Y70: =VLOOKUP($A:$A,Variables_extraites!$A:$AD,7,FALSE) -> 1 | Z70: =VLOOKUP($A:$A,Variables_extraites!$A:$AD,8,FALSE) -> 0 | AA70: =VLOOKUP($A:$A,Variables_extraites!$A:$AD,9,FALSE) -> 8.7 | AB70: =VLOOKUP($A:$A,Variables_extraites!$A:$AD,10,FALSE) -> 1 | AC70: =VLOOKUP($A:$A,Variables_extraites!$A:$AD,11,FALSE) -> 1 | AD70: =VLOOKUP($A:$A,Variables_extraites!$A:$AD,12,FALSE) -> 1 | AE70: =VLOOKUP($A:$A,Variables_extraites!$A:$AD,13,FALSE) -> 73.51168 | AF70: =VLOOKUP($A:$A,Variables_extraites!$A:$AD,14,FALSE) -> NA | AG70: =VLOOKUP($A:$A,Variables_extraites!$A:$AD,15,FALSE) -> 10.666667 | AH70: =VLOOKUP($A:$A,Variables_extraites!$A:$AD,16,FALSE) -> 132 | AI70: =VLOOKUP($A:$A,Variables_extraites!$A:$AD,17,FALSE) -> 42493 | AJ70: =VLOOKUP($A:$A,Variables_extraites!$A:$AD,18,FALSE) -> 43455 | AK70: =VLOOKUP($A:$A,Variables_extraites!$A:$AD,19,FALSE) -> 0 | AL70: =VLOOKUP($A:$A,Variables_extraites!$A:$AD,20,FALSE) -> 43455 | AM70: =VLOOKUP($A:$A,Variables_extraites!$A:$AD,21,FALSE) -> 31 | AN70: =VLOOKUP($A:$A,Variables_extraites!$A:$AD,22,FALSE) -> 1 | AO70: =VLOOKUP($A:$A,Variables_extraites!$A:$AD,23,FALSE) -> 42821 | AP70: =VLOOKUP($A:$A,Variables_extraites!$A:$AD,24,FALSE) -> 10 | AQ70: =VLOOKUP($A:$A,Variables_extraites!$A:$AD,25,FALSE) -> 1 | AR70: =VLOOKUP($A:$A,Variables_extraites!$A:$AD,26,FALSE) -> 42821 | AS70: =VLOOKUP($A:$A,Variables_extraites!$A:$AD,27,FALSE) -> 10 | AT70: =VLOOKUP($A:$A,Variables_extraites!$A:$AD,28,FALSE) -> 31 | AU70: =VLOOKUP($A:$A,Variables_extraites!$A:$AD,29,FALSE) -> 962 | AV70: =VLOOKUP($A:$A,Variables_extraites!$A:$AD,30,FALSE) -> -18.393333 | AW70: 8.5348087 | AX70: 7.7643408 | AY70: 5.2517191 | AZ70: 2.2600257 | BA70: 7.5796176 | BB70: 6.1179028 | BC70: 9.2747509 | BD70: 7.3844816 | BE70: 6.2437452 | BF70: 0.91838623 | BG70: 6.3403842 | BH70: 6.9680908 | BI70: 7.3047848 | BJ70: 4.4053117 | BK70: 5.8419731 | BL70: 7.4472486 | BM70: 6.178117 | BN70: 6.6646251 | BO70: 5.5223069 | BP70: 6.3524407 | BQ70: 8.1755246 | BR70: 3.5008021 | BS70: 11.137926 | BT70: 2.7697717 | BU70: 9.1760235 | BV70: 7.0082045 | BW70: 5 | BX70: 10.589202 | BY70: 3.4815573 | BZ70: 8.6266947 | CA70: 3.9671686 | CB70: 1.962507 | CC70: 5.6752215 | CD70: 8.3681544
A71: 134 | B71: 134 | C71: 2 | D71: HFpEF | E71: 10305 | F71: YES | H71: 70 | I71: 40.903686 | J71: 1 | K71: 3 | L71: 1 | M71: 26 | N71: 12.5 | O71: 1812.6841 | R71: 40.255005 | S71: 13.611111 | T71: 20 | U71: -21.76 | V71: 51.020126 | W71: 39.677445 | X71: 107.6013 | Y71: =VLOOKUP($A:$A,Variables_extraites!$A:$AD,7,FALSE) -> 0 | Z71: =VLOOKUP($A:$A,Variables_extraites!$A:$AD,8,FALSE) -> 0 | AA71: =VLOOKUP($A:$A,Variables_extraites!$A:$AD,9,FALSE) -> 9.5 | AB71: =VLOOKUP($A:$A,Variables_extraites!$A:$AD,10,FALSE) -> 1 | AC71: =VLOOKUP($A:$A,Variables_extraites!$A:$AD,11,FALSE) -> 1 | AD71: =VLOOKUP($A:$A,Variables_extraites!$A:$AD,12,FALSE) -> 1 | AE71: =VLOOKUP($A:$A,Variables_extraites!$A:$AD,13,FALSE) -> 67.25537 | AF71: =VLOOKUP($A:$A,Variables_extraites!$A:$AD,14,FALSE) -> 0.75230297 | AG71: =VLOOKUP($A:$A,Variables_extraites!$A:$AD,15,FALSE) -> 20 | AH71: =VLOOKUP($A:$A,Variables_extraites!$A:$AD,16,FALSE) -> 134 | AI71: =VLOOKUP($A:$A,Variables_extraites!$A:$AD,17,FALSE) -> 42500 | AJ71: =VLOOKUP($A:$A,Variables_extraites!$A:$AD,18,FALSE) -> 43262 | AK71: =VLOOKUP($A:$A,Variables_extraites!$A:$AD,19,FALSE) -> 0 | AL71: =VLOOKUP($A:$A,Variables_extraites!$A:$AD,20,FALSE) -> 43262 | AM71: =VLOOKUP($A:$A,Variables_extraites!$A:$AD,21,FALSE) -> 25 | AN71: =VLOOKUP($A:$A,Variables_extraites!$A:$AD,22,FALSE) -> 1 | AO71: =VLOOKUP($A:$A,Variables_extraites!$A:$AD,23,FALSE) -> 42541 | AP71: =VLOOKUP($A:$A,Variables_extraites!$A:$AD,24,FALSE) -> 1 | AQ71: =VLOOKUP($A:$A,Variables_extraites!$A:$AD,25,FALSE) -> 1 | AR71: =VLOOKUP($A:$A,Variables_extraites!$A:$AD,26,FALSE) -> 42541 | AS71: =VLOOKUP($A:$A,Variables_extraites!$A:$AD,27,FALSE) -> 1 | AT71: =VLOOKUP($A:$A,Variables_extraites!$A:$AD,28,FALSE) -> 25 | AU71: =VLOOKUP($A:$A,Variables_extraites!$A:$AD,29,FALSE) -> 762 | AV71: =VLOOKUP($A:$A,Variables_extraites!$A:$AD,30,FALSE) -> -21.96
A72: 135 | B72: 135 | C72: 2 | D72: HFpEF | E72: 10306 | F72: YES | H72: 70 | I72: 25.558846 | J72: 1 | K72: 3 | L72: 0 | M72: 24 | N72: 57.98 | O72: 2277.3307 | P72: 8610 | Q72: 47 | R72: 39.180202 | S72: 27.415094 | T72: 52 | U72: -13.233333 | X72: 87.4148 | Y72: =VLOOKUP($A:$A,Variables_extraites!$A:$AD,7,FALSE) -> 0 | Z72: =VLOOKUP($A:$A,Variables_extraites!$A:$AD,8,FALSE) -> 0 | AA72: =VLOOKUP($A:$A,Variables_extraites!$A:$AD,9,FALSE) -> 10.5 | AB72: =VLOOKUP($A:$A,Variables_extraites!$A:$AD,10,FALSE) -> 1 | AC72: =VLOOKUP($A:$A,Variables_extraites!$A:$AD,11,FALSE) -> 0 | AD72: =VLOOKUP($A:$A,Variables_extraites!$A:$AD,12,FALSE) -> 1 | AE72: =VLOOKUP($A:$A,Variables_extraites!$A:$AD,13,FALSE) -> 73.278939 | AF72: =VLOOKUP($A:$A,Variables_extraites!$A:$AD,14,FALSE) -> 2.977459 | AG72: =VLOOKUP($A:$A,Variables_extraites!$A:$AD,15,FALSE) -> 22 | AH72: =VLOOKUP($A:$A,Variables_extraites!$A:$AD,16,FALSE) -> 135 | AI72: =VLOOKUP($A:$A,Variables_extraites!$A:$AD,17,FALSE) -> 42501 | AJ72: =VLOOKUP($A:$A,Variables_extraites!$A:$AD,18,FALSE) -> 42625 | AK72: =VLOOKUP($A:$A,Variables_extraites!$A:$AD,19,FALSE) -> 1 | AL72: =VLOOKUP($A:$A,Variables_extraites!$A:$AD,20,FALSE) -> 42625 | AM72: =VLOOKUP($A:$A,Variables_extraites!$A:$AD,21,FALSE) -> 4 | AN72: =VLOOKUP($A:$A,Variables_extraites!$A:$AD,22,FALSE) -> 1 | AO72: =VLOOKUP($A:$A,Variables_extraites!$A:$AD,23,FALSE) -> 42594 | AP72: =VLOOKUP($A:$A,Variables_extraites!$A:$AD,24,FALSE) -> 3 | AQ72: =VLOOKUP($A:$A,Variables_extraites!$A:$AD,25,FALSE) -> 1 | AR72: =VLOOKUP($A:$A,Variables_extraites!$A:$AD,26,FALSE) -> 42594 | AS72: =VLOOKUP($A:$A,Variables_extraites!$A:$AD,27,FALSE) -> 3 | AT72: =VLOOKUP($A:$A,Variables_extraites!$A:$AD,28,FALSE) -> 4 | AU72: =VLOOKUP($A:$A,Variables_extraites!$A:$AD,29,FALSE) -> 124 | AV72: =VLOOKUP($A:$A,Variables_extraites!$A:$AD,30,FALSE) -> -12.68
A73: 136 | B73: 136 | C73: 2 | D73: HFpEF | E73: 10401 | F73: YES | H73: 79 | I73: 21.829952 | J73: 1 | K73: 3 | L73: 0 | M73: 33 | N73: 40.55 | O73: 647.4192 | P73: 3178 | Q73: 19 | R73: 43.318946 | S73: 16.421965 | T73: 37.666667 | U73: -15.82 | V73: 65.057624 | W73: 33.200667 | X73: 79.3862 | Y73: =VLOOKUP($A:$A,Variables_extraites!$A:$AD,7,FALSE) -> 0 | Z73: =VLOOKUP($A:$A,Variables_extraites!$A:$AD,8,FALSE) -> 0 | AA73: =VLOOKUP($A:$A,Variables_extraites!$A:$AD,9,FALSE) -> 13.5 | AB73: =VLOOKUP($A:$A,Variables_extraites!$A:$AD,10,FALSE) -> 1 | AC73: =VLOOKUP($A:$A,Variables_extraites!$A:$AD,11,FALSE) -> 0 | AD73: =VLOOKUP($A:$A,Variables_extraites!$A:$AD,12,FALSE) -> 1 | AE73: =VLOOKUP($A:$A,Variables_extraites!$A:$AD,13,FALSE) -> 60.808709 | AF73: =VLOOKUP($A:$A,Variables_extraites!$A:$AD,14,FALSE) -> NA | AG73: =VLOOKUP($A:$A,Variables_extraites!$A:$AD,15,FALSE) -> 13.333333 | AH73: =VLOOKUP($A:$A,Variables_extraites!$A:$AD,16,FALSE) -> 136 | AI73: =VLOOKUP($A:$A,Variables_extraites!$A:$AD,17,FALSE) -> 42508 | AJ73: =VLOOKUP($A:$A,Variables_extraites!$A:$AD,18,FALSE) -> 43235 | AK73: =VLOOKUP($A:$A,Variables_extraites!$A:$AD,19,FALSE) -> 0 | AL73: =VLOOKUP($A:$A,Variables_extraites!$A:$AD,20,FALSE) -> 43235 | AM73: =VLOOKUP($A:$A,Variables_extraites!$A:$AD,21,FALSE) -> 23 | AN73: =VLOOKUP($A:$A,Variables_extraites!$A:$AD,22,FALSE) -> 1 | AO73: =VLOOKUP($A:$A,Variables_extraites!$A:$AD,23,FALSE) -> 43216 | AP73: =VLOOKUP($A:$A,Variables_extraites!$A:$AD,24,FALSE) -> 23 | AQ73: =VLOOKUP($A:$A,Variables_extraites!$A:$AD,25,FALSE) -> 1 | AR73: =VLOOKUP($A:$A,Variables_extraites!$A:$AD,26,FALSE) -> 43216 | AS73: =VLOOKUP($A:$A,Variables_extraites!$A:$AD,27,FALSE) -> 23 | AT73: =VLOOKUP($A:$A,Variables_extraites!$A:$AD,28,FALSE) -> 23 | AU73: =VLOOKUP($A:$A,Variables_extraites!$A:$AD,29,FALSE) -> 727 | AV73: =VLOOKUP($A:$A,Variables_extraites!$A:$AD,30,FALSE) -> -19.873333
A74: 137 | B74: 137 | C74: 2 | D74: HFpEF | E74: 10402 | F74: YES | G74: YES | H74: 74 | I74: 29.752066 | J74: 1 | K74: 2 | L74: 0 | M74: 64 | N74: 20.21 | O74: 570.52775 | P74: 183.9 | Q74: 5 | R74: 40.06809 | S74: 13.538462 | T74: 27 | U74: -16.45 | V74: 46.811374 | W74: 32.483142 | X74: 72.9672 | Y74: =VLOOKUP($A:$A,Variables_extraites!$A:$AD,7,FALSE) -> 0 | Z74: =VLOOKUP($A:$A,Variables_extraites!$A:$AD,8,FALSE) -> 0 | AA74: =VLOOKUP($A:$A,Variables_extraites!$A:$AD,9,FALSE) -> 11.2 | AB74: =VLOOKUP($A:$A,Variables_extraites!$A:$AD,10,FALSE) -> 1 | AC74: =VLOOKUP($A:$A,Variables_extraites!$A:$AD,11,FALSE) -> 0 | AD74: =VLOOKUP($A:$A,Variables_extraites!$A:$AD,12,FALSE) -> 1 | AE74: =VLOOKUP($A:$A,Variables_extraites!$A:$AD,13,FALSE) -> 61.370124 | AF74: =VLOOKUP($A:$A,Variables_extraites!$A:$AD,14,FALSE) -> 0.79398496 | AG74: =VLOOKUP($A:$A,Variables_extraites!$A:$AD,15,FALSE) -> 27 | AH74: =VLOOKUP($A:$A,Variables_extraites!$A:$AD,16,FALSE) -> 137 | AI74: =VLOOKUP($A:$A,Variables_extraites!$A:$AD,17,FALSE) -> 42513 | AJ74: =VLOOKUP($A:$A,Variables_extraites!$A:$AD,18,FALSE) -> 43228 | AK74: =VLOOKUP($A:$A,Variables_extraites!$A:$AD,19,FALSE) -> 0 | AL74: =VLOOKUP($A:$A,Variables_extraites!$A:$AD,20,FALSE) -> 43228 | AM74: =VLOOKUP($A:$A,Variables_extraites!$A:$AD,21,FALSE) -> 23 | AN74: =VLOOKUP($A:$A,Variables_extraites!$A:$AD,22,FALSE) -> 0 | AO74: =VLOOKUP($A:$A,Variables_extraites!$A:$AD,23,FALSE) -> 43228 | AP74: =VLOOKUP($A:$A,Variables_extraites!$A:$AD,24,FALSE) -> 23 | AQ74: =VLOOKUP($A:$A,Variables_extraites!$A:$AD,25,FALSE) -> 0 | AR74: =VLOOKUP($A:$A,Variables_extraites!$A:$AD,26,FALSE) -> 43228 | AS74: =VLOOKUP($A:$A,Variables_extraites!$A:$AD,27,FALSE) -> 23 | AT74: =VLOOKUP($A:$A,Variables_extraites!$A:$AD,28,FALSE) -> 23 | AU74: =VLOOKUP($A:$A,Variables_extraites!$A:$AD,29,FALSE) -> 715 | AV74: =VLOOKUP($A:$A,Variables_extraites!$A:$AD,30,FALSE) -> -29.12 | AW74: 8.4908509 | AX74: 7.6712226 | AY74: 5.2573878 | AZ74: 2.0461418 | BA74: 7.8189656 | BB74: 6.3936908 | BC74: 9.3597715 | BD74: 7.8911761 | BE74: 6.1912073 | BF74: 1.0976108 | BG74: 6.3184976 | BH74: 6.8373126 | BI74: 7.3655351 | BJ74: 4.6141209 | BK74: 6.0172538 | BL74: 8.2411728 | BM74: 6.2152903 | BN74: 7.1089426 | BO74: 6.0069712 | BP74: 6.452859 | BQ74: 7.7625481 | BR74: 3.6667566 | BS74: 9.3087941 | BT74: 1.7697717 | BU74: 4.7902507 | BV74: 6.4402878 | BW74: 5.312883 | BX74: 10.066493 | BY74: 3.3950628 | BZ74: 8.1352989 | CA74: 4.3645724 | CB74: 1.931194 | CC74: 1.1234941 | CD74: 7.5390223
A75: 138 | B75: 138 | C75: 2 | D75: HFpEF | E75: 10515 | F75: YES | H75: 72 | I75: 27.76343 | J75: 0 | K75: 2 | L75: 1 | M75: 57 | N75: 32.57 | O75: 152.58367 | P75: 1187 | Q75: 29 | R75: 90.053373 | S75: 13.413043 | T75: 34 | U75: -14.41 | V75: 77.338065 | W75: 31.867241 | X75: 53.5991 | Y75: =VLOOKUP($A:$A,Variables_extraites!$A:$AD,7,FALSE) -> 0 | Z75: =VLOOKUP($A:$A,Variables_extraites!$A:$AD,8,FALSE) -> 0 | AA75: =VLOOKUP($A:$A,Variables_extraites!$A:$AD,9,FALSE) -> 12.2 | AB75: =VLOOKUP($A:$A,Variables_extraites!$A:$AD,10,FALSE) -> 1 | AC75: =VLOOKUP($A:$A,Variables_extraites!$A:$AD,11,FALSE) -> 0 | AD75: =VLOOKUP($A:$A,Variables_extraites!$A:$AD,12,FALSE) -> 1 | AE75: =VLOOKUP($A:$A,Variables_extraites!$A:$AD,13,FALSE) -> 50.930333 | AF75: =VLOOKUP($A:$A,Variables_extraites!$A:$AD,14,FALSE) -> 3.3351351 | AG75: =VLOOKUP($A:$A,Variables_extraites!$A:$AD,15,FALSE) -> 13 | AH75: =VLOOKUP($A:$A,Variables_extraites!$A:$AD,16,FALSE) -> 138 | AI75: =VLOOKUP($A:$A,Variables_extraites!$A:$AD,17,FALSE) -> 42527 | AJ75: =VLOOKUP($A:$A,Variables_extraites!$A:$AD,18,FALSE) -> 43480 | AK75: =VLOOKUP($A:$A,Variables_extraites!$A:$AD,19,FALSE) -> 1 | AL75: =VLOOKUP($A:$A,Variables_extraites!$A:$AD,20,FALSE) -> 43480 | AM75: =VLOOKUP($A:$A,Variables_extraites!$A:$AD,21,FALSE) -> 31 | AN75: =VLOOKUP($A:$A,Variables_extraites!$A:$AD,22,FALSE) -> 0 | AO75: =VLOOKUP($A:$A,Variables_extraites!$A:$AD,23,FALSE) -> 43480 | AP75: =VLOOKUP($A:$A,Variables_extraites!$A:$AD,24,FALSE) -> 31 | AQ75: =VLOOKUP($A:$A,Variables_extraites!$A:$AD,25,FALSE) -> 1 | AR75: =VLOOKUP($A:$A,Variables_extraites!$A:$AD,26,FALSE) -> 43480 | AS75: =VLOOKUP($A:$A,Variables_extraites!$A:$AD,27,FALSE) -> 31 | AT75: =VLOOKUP($A:$A,Variables_extraites!$A:$AD,28,FALSE) -> 31 | AU75: =VLOOKUP($A:$A,Variables_extraites!$A:$AD,29,FALSE) -> 953 | AV75: =VLOOKUP($A:$A,Variables_extraites!$A:$AD,30,FALSE) -> -13.06
A76: 139 | B76: 139 | C76: 2 | D76: HFpEF | E76: 10605 | F76: YES | G76: YES | H76: 73 | I76: 36.848073 | J76: 0 | K76: 2 | L76: 1 | M76: 64 | N76: 25.03 | O76: 37.559964 | P76: 563.1 | Q76: 6 | R76: 36.245484 | S76: 19.444444 | T76: 37 | U76: -17.12 | V76: 76.389687 | W76: 26.087935 | X76: 30.9297 | Y76: =VLOOKUP($A:$A,Variables_extraites!$A:$AD,7,FALSE) -> 0 | Z76: =VLOOKUP($A:$A,Variables_extraites!$A:$AD,8,FALSE) -> 0 | AA76: =VLOOKUP($A:$A,Variables_extraites!$A:$AD,9,FALSE) -> 13.9 | AB76: =VLOOKUP($A:$A,Variables_extraites!$A:$AD,10,FALSE) -> 0 | AC76: =VLOOKUP($A:$A,Variables_extraites!$A:$AD,11,FALSE) -> 1 | AD76: =VLOOKUP($A:$A,Variables_extraites!$A:$AD,12,FALSE) -> 0 | AE76: =VLOOKUP($A:$A,Variables_extraites!$A:$AD,13,FALSE) -> 60.164344 | AF76: =VLOOKUP($A:$A,Variables_extraites!$A:$AD,14,FALSE) -> 0.875 | AG76: =VLOOKUP($A:$A,Variables_extraites!$A:$AD,15,FALSE) -> 15 | AH76: =VLOOKUP($A:$A,Variables_extraites!$A:$AD,16,FALSE) -> 139 | AI76: =VLOOKUP($A:$A,Variables_extraites!$A:$AD,17,FALSE) -> 42487 | AJ76: =VLOOKUP($A:$A,Variables_extraites!$A:$AD,18,FALSE) -> 43544 | AK76: =VLOOKUP($A:$A,Variables_extraites!$A:$AD,19,FALSE) -> 0 | AL76: =VLOOKUP($A:$A,Variables_extraites!$A:$AD,20,FALSE) -> 43544 | AM76: =VLOOKUP($A:$A,Variables_extraites!$A:$AD,21,FALSE) -> 34 | AN76: =VLOOKUP($A:$A,Variables_extraites!$A:$AD,22,FALSE) -> 0 | AO76: =VLOOKUP($A:$A,Variables_extraites!$A:$AD,23,FALSE) -> 43544 | AP76: =VLOOKUP($A:$A,Variables_extraites!$A:$AD,24,FALSE) -> 34 | AQ76: =VLOOKUP($A:$A,Variables_extraites!$A:$AD,25,FALSE) -> 0 | AR76: =VLOOKUP($A:$A,Variables_extraites!$A:$AD,26,FALSE) -> 43544 | AS76: =VLOOKUP($A:$A,Variables_extraites!$A:$AD,27,FALSE) -> 34 | AT76: =VLOOKUP($A:$A,Variables_extraites!$A:$AD,28,FALSE) -> 34 | AU76: =VLOOKUP($A:$A,Variables_extraites!$A:$AD,29,FALSE) -> 1057 | AV76: =VLOOKUP($A:$A,Variables_extraites!$A:$AD,30,FALSE) -> -14.78 | AW76: 8.0913296 | AX76: 7.7786685 | AY76: 5.2883586 | AZ76: 1.4646683 | BA76: 8.3037351 | BB76: 4.8514992 | BC76: 9.3020905 | BD76: 7.469072 | BE76: 6.0946583 | BF76: 1.3561438 | BG76: 5.9212459 | BH76: 6.4899282 | BI76: 7.3745179 | BJ76: 4.3561438 | BK76: 6.0419876 | BL76: 8.1272206 | BM76: 6.1206008 | BN76: 6.8284539 | BO76: 5.7384976 | BP76: 6.0234772 | BQ76: 7.7921396 | BR76: 5.309249 | BS76: 10.386132 | BT76: 2.2387869 | BU76: 6.8375649 | BV76: 6.9670533 | BW76: 4.9703935 | BX76: 9.780835 | BY76: 2.9240999 | BZ76: 7.6544212 | CA76: 3.8237494 | CB76: 2.1264138 | CC76: 1.5283159 | CD76: 8.1473451
A77: 140 | B77: 140 | C77: 2 | D77: HFpEF | E77: 10403 | F77: YES | H77: 75 | I77: 19.031142 | J77: 1 | K77: 2 | L77: 0 | M77: 71 | N77: 34.07 | O77: 340.98005 | P77: 2097 | Q77: 29 | R77: 28.559836 | S77: 12.977273 | T77: 20.4 | U77: -16.6 | V77: 99.447256 | W77: 32.934444 | X77: 78.3551 | Y77: =VLOOKUP($A:$A,Variables_extraites!$A:$AD,7,FALSE) -> 0 | Z77: =VLOOKUP($A:$A,Variables_extraites!$A:$AD,8,FALSE) -> 0 | AA77: =VLOOKUP($A:$A,Variables_extraites!$A:$AD,9,FALSE) -> 9 | AB77: =VLOOKUP($A:$A,Variables_extraites!$A:$AD,10,FALSE) -> 0 | AC77: =VLOOKUP($A:$A,Variables_extraites!$A:$AD,11,FALSE) -> 0 | AD77: =VLOOKUP($A:$A,Variables_extraites!$A:$AD,12,FALSE) -> 0 | AE77: =VLOOKUP($A:$A,Variables_extraites!$A:$AD,13,FALSE) -> 57.861401 | AF77: =VLOOKUP($A:$A,Variables_extraites!$A:$AD,14,FALSE) -> 0.62200436 | AG77: =VLOOKUP($A:$A,Variables_extraites!$A:$AD,15,FALSE) -> 18 | AH77: =VLOOKUP($A:$A,Variables_extraites!$A:$AD,16,FALSE) -> 140 | AI77: =VLOOKUP($A:$A,Variables_extraites!$A:$AD,17,FALSE) -> 42514 | AJ77: =VLOOKUP($A:$A,Variables_extraites!$A:$AD,18,FALSE) -> 43070 | AK77: =VLOOKUP($A:$A,Variables_extraites!$A:$AD,19,FALSE) -> 1 | AL77: =VLOOKUP($A:$A,Variables_extraites!$A:$AD,20,FALSE) -> 43070 | AM77: =VLOOKUP($A:$A,Variables_extraites!$A:$AD,21,FALSE) -> 18 | AN77: =VLOOKUP($A:$A,Variables_extraites!$A:$AD,22,FALSE) -> 1 | AO77: =VLOOKUP($A:$A,Variables_extraites!$A:$AD,23,FALSE) -> 42563 | AP77: =VLOOKUP($A:$A,Variables_extraites!$A:$AD,24,FALSE) -> 2 | AQ77: =VLOOKUP($A:$A,Variables_extraites!$A:$AD,25,FALSE) -> 1 | AR77: =VLOOKUP($A:$A,Variables_extraites!$A:$AD,26,FALSE) -> 42563 | AS77: =VLOOKUP($A:$A,Variables_extraites!$A:$AD,27,FALSE) -> 2 | AT77: =VLOOKUP($A:$A,Variables_extraites!$A:$AD,28,FALSE) -> 18 | AU77: =VLOOKUP($A:$A,Variables_extraites!$A:$AD,29,FALSE) -> 556 | AV77: =VLOOKUP($A:$A,Variables_extraites!$A:$AD,30,FALSE) -> -16.69
A78: 141 | B78: 141 | C78: 2 | D78: HFpEF | E78: 10340 | F78: YES | H78: 81 | I78: 17.578125 | J78: 1 | K78: 3 | L78: 0 | M78: 67 | N78: 36.5 | O78: 760.87754 | P78: 3310 | Q78: 32 | R78: 60.889555 | S78: 10.666667 | T78: 29 | U78: -16.286667 | X78: 60.6907 | Y78: =VLOOKUP($A:$A,Variables_extraites!$A:$AD,7,FALSE) -> 0 | Z78: =VLOOKUP($A:$A,Variables_extraites!$A:$AD,8,FALSE) -> 0 | AA78: =VLOOKUP($A:$A,Variables_extraites!$A:$AD,9,FALSE) -> 12.7 | AB78: =VLOOKUP($A:$A,Variables_extraites!$A:$AD,10,FALSE) -> 0 | AC78: =VLOOKUP($A:$A,Variables_extraites!$A:$AD,11,FALSE) -> 0 | AD78: =VLOOKUP($A:$A,Variables_extraites!$A:$AD,12,FALSE) -> 1 | AE78: =VLOOKUP($A:$A,Variables_extraites!$A:$AD,13,FALSE) -> 51.015474 | AF78: =VLOOKUP($A:$A,Variables_extraites!$A:$AD,14,FALSE) -> NA | AG78: =VLOOKUP($A:$A,Variables_extraites!$A:$AD,15,FALSE) -> 16 | AH78: =VLOOKUP($A:$A,Variables_extraites!$A:$AD,16,FALSE) -> 141 | AI78: =VLOOKUP($A:$A,Variables_extraites!$A:$AD,17,FALSE) -> 42509 | AJ78: =VLOOKUP($A:$A,Variables_extraites!$A:$AD,18,FALSE) -> 43054 | AK78: =VLOOKUP($A:$A,Variables_extraites!$A:$AD,19,FALSE) -> 0 | AL78: =VLOOKUP($A:$A,Variables_extraites!$A:$AD,20,FALSE) -> 43054 | AM78: =VLOOKUP($A:$A,Variables_extraites!$A:$AD,21,FALSE) -> 18 | AN78: =VLOOKUP($A:$A,Variables_extraites!$A:$AD,22,FALSE) -> 0 | AO78: =VLOOKUP($A:$A,Variables_extraites!$A:$AD,23,FALSE) -> 43054 | AP78: =VLOOKUP($A:$A,Variables_extraites!$A:$AD,24,FALSE) -> 18 | AQ78: =VLOOKUP($A:$A,Variables_extraites!$A:$AD,25,FALSE) -> 0 | AR78: =VLOOKUP($A:$A,Variables_extraites!$A:$AD,26,FALSE) -> 43054 | AS78: =VLOOKUP($A:$A,Variables_extraites!$A:$AD,27,FALSE) -> 18 | AT78: =VLOOKUP($A:$A,Variables_extraites!$A:$AD,28,FALSE) -> 17.9 | AU78: =VLOOKUP($A:$A,Variables_extraites!$A:$AD,29,FALSE) -> 545 | AV78: =VLOOKUP($A:$A,Variables_extraites!$A:$AD,30,FALSE) -> -15.9
A79: 143 | B79: 143 | C79: 2 | D79: HFpEF | E79: 10404 | F79: YES | G79: YES | H79: 83 | I79: 22.491349 | J79: 1 | K79: 4 | L79: 1 | M79: 27 | N79: 42.37 | O79: 489.76582 | P79: 3728 | Q79: 35 | R79: 41.029935 | S79: 13.877551 | T79: 35 | U79: -20.49 | V79: 94.660382 | W79: 30.356879 | X79: 89.73 | Y79: =VLOOKUP($A:$A,Variables_extraites!$A:$AD,7,FALSE) -> 0 | Z79: =VLOOKUP($A:$A,Variables_extraites!$A:$AD,8,FALSE) -> 0 | AA79: =VLOOKUP($A:$A,Variables_extraites!$A:$AD,9,FALSE) -> 10.5 | AB79: =VLOOKUP($A:$A,Variables_extraites!$A:$AD,10,FALSE) -> 0 | AC79: =VLOOKUP($A:$A,Variables_extraites!$A:$AD,11,FALSE) -> 0 | AD79: =VLOOKUP($A:$A,Variables_extraites!$A:$AD,12,FALSE) -> 1 | AE79: =VLOOKUP($A:$A,Variables_extraites!$A:$AD,13,FALSE) -> 64.544205 | AF79: =VLOOKUP($A:$A,Variables_extraites!$A:$AD,14,FALSE) -> 0.8 | AG79: =VLOOKUP($A:$A,Variables_extraites!$A:$AD,15,FALSE) -> 26 | AH79: =VLOOKUP($A:$A,Variables_extraites!$A:$AD,16,FALSE) -> 143 | AI79: =VLOOKUP($A:$A,Variables_extraites!$A:$AD,17,FALSE) -> 42517 | AJ79: =VLOOKUP($A:$A,Variables_extraites!$A:$AD,18,FALSE) -> 43291 | AK79: =VLOOKUP($A:$A,Variables_extraites!$A:$AD,19,FALSE) -> 0 | AL79: =VLOOKUP($A:$A,Variables_extraites!$A:$AD,20,FALSE) -> 43291 | AM79: =VLOOKUP($A:$A,Variables_extraites!$A:$AD,21,FALSE) -> 25 | AN79: =VLOOKUP($A:$A,Variables_extraites!$A:$AD,22,FALSE) -> 1 | AO79: =VLOOKUP($A:$A,Variables_extraites!$A:$AD,23,FALSE) -> 43037 | AP79: =VLOOKUP($A:$A,Variables_extraites!$A:$AD,24,FALSE) -> 17 | AQ79: =VLOOKUP($A:$A,Variables_extraites!$A:$AD,25,FALSE) -> 1 | AR79: =VLOOKUP($A:$A,Variables_extraites!$A:$AD,26,FALSE) -> 43037 | AS79: =VLOOKUP($A:$A,Variables_extraites!$A:$AD,27,FALSE) -> 17 | AT79: =VLOOKUP($A:$A,Variables_extraites!$A:$AD,28,FALSE) -> 25 | AU79: =VLOOKUP($A:$A,Variables_extraites!$A:$AD,29,FALSE) -> 774 | AV79: =VLOOKUP($A:$A,Variables_extraites!$A:$AD,30,FALSE) -> -28.18 | AW79: 7.3947199 | AX79: 7.2851248 | AY79: 4.523562 | AZ79: 1.422233 | BA79: 8.1508135 | BB79: 5.4352952 | BC79: 8.9478707 | BD79: 6.888378 | BE79: 5.8792156 | BF79: 0.86393845 | BG79: 5.7161678 | BH79: 6.5698556 | BI79: 7.0124569 | BJ79: 3.65306 | BK79: 6.1878469 | BL79: 6.9366379 | BM79: 5.587665 | BN79: 5.5043026 | BO79: 4.9749881 | BP79: 5.4591037 | BQ79: 7.8342814 | BR79: 3.4956952 | BS79: 9.6304128 | BT79: 1.9259994 | BU79: 3.8639385 | BV79: 5.335569 | BW79: 4.5229346 | BX79: 9.900414 | BY79: 2.8953026 | BZ79: 7.9409889 | CA79: 4.1489341 | CB79: 1.9594251 | CC79: 0.36824329 | CD79: 7.7044133
A80: 144 | B80: 144 | C80: 2 | D80: HFpEF | E80: 10405 | F80: YES | H80: 73 | I80: 36.558841 | J80: 1 | K80: 4 | L80: 1 | M80: 79 | N80: 37.59 | O80: 1071.9608 | P80: 192.8 | Q80: 18 | R80: 43.129584 | S80: 17.105263 | T80: 20 | U80: -13.1 | V80: 79.50667 | W80: 30.979958 | X80: 53.6272 | Y80: =VLOOKUP($A:$A,Variables_extraites!$A:$AD,7,FALSE) -> 0 | Z80: =VLOOKUP($A:$A,Variables_extraites!$A:$AD,8,FALSE) -> 0 | AA80: =VLOOKUP($A:$A,Variables_extraites!$A:$AD,9,FALSE) -> 12.5 | AB80: =VLOOKUP($A:$A,Variables_extraites!$A:$AD,10,FALSE) -> 0 | AC80: =VLOOKUP($A:$A,Variables_extraites!$A:$AD,11,FALSE) -> 1 | AD80: =VLOOKUP($A:$A,Variables_extraites!$A:$AD,12,FALSE) -> 0 | AE80: =VLOOKUP($A:$A,Variables_extraites!$A:$AD,13,FALSE) -> 54.523312 | AF80: =VLOOKUP($A:$A,Variables_extraites!$A:$AD,14,FALSE) -> 1.1669659 | AG80: =VLOOKUP($A:$A,Variables_extraites!$A:$AD,15,FALSE) -> 17 | AH80: =VLOOKUP($A:$A,Variables_extraites!$A:$AD,16,FALSE) -> 144 | AI80: =VLOOKUP($A:$A,Variables_extraites!$A:$AD,17,FALSE) -> 42527 | AJ80: =VLOOKUP($A:$A,Variables_extraites!$A:$AD,18,FALSE) -> 43250 | AK80: =VLOOKUP($A:$A,Variables_extraites!$A:$AD,19,FALSE) -> 0 | AL80: =VLOOKUP($A:$A,Variables_extraites!$A:$AD,20,FALSE) -> 43250 | AM80: =VLOOKUP($A:$A,Variables_extraites!$A:$AD,21,FALSE) -> 24 | AN80: =VLOOKUP($A:$A,Variables_extraites!$A:$AD,22,FALSE) -> 0 | AO80: =VLOOKUP($A:$A,Variables_extraites!$A:$AD,23,FALSE) -> 43250 | AP80: =VLOOKUP($A:$A,Variables_extraites!$A:$AD,24,FALSE) -> 24 | AQ80: =VLOOKUP($A:$A,Variables_extraites!$A:$AD,25,FALSE) -> 0 | AR80: =VLOOKUP($A:$A,Variables_extraites!$A:$AD,26,FALSE) -> 43250 | AS80: =VLOOKUP($A:$A,Variables_extraites!$A:$AD,27,FALSE) -> 24 | AT80: =VLOOKUP($A:$A,Variables_extraites!$A:$AD,28,FALSE) -> 24 | AU80: =VLOOKUP($A:$A,Variables_extraites!$A:$AD,29,FALSE) -> 723 | AV80: =VLOOKUP($A:$A,Variables_extraites!$A:$AD,30,FALSE) -> -20.26
A81: 145 | B81: 145 | C81: 2 | D81: HFpEF | E81: 10406 | F81: YES | H81: 73 | I81: 33.912513 | J81: 1 | K81: 3 | L81: 1 | M81: 36 | N81: 36.42 | O81: 1196.9498 | P81: 78 | Q81: 28 | R81: 30.899092 | S81: 17.978261 | T81: 26 | U81: -18.03 | V81: 73.393776 | W81: 29.57115 | X81: 122.3035 | Y81: =VLOOKUP($A:$A,Variables_extraites!$A:$AD,7,FALSE) -> 0 | Z81: =VLOOKUP($A:$A,Variables_extraites!$A:$AD,8,FALSE) -> 0 | AA81: =VLOOKUP($A:$A,Variables_extraites!$A:$AD,9,FALSE) -> 10 | AB81: =VLOOKUP($A:$A,Variables_extraites!$A:$AD,10,FALSE) -> 1 | AC81: =VLOOKUP($A:$A,Variables_extraites!$A:$AD,11,FALSE) -> 0 | AD81: =VLOOKUP($A:$A,Variables_extraites!$A:$AD,12,FALSE) -> 0 | AE81: =VLOOKUP($A:$A,Variables_extraites!$A:$AD,13,FALSE) -> 69.263699 | AF81: =VLOOKUP($A:$A,Variables_extraites!$A:$AD,14,FALSE) -> 0.71663778 | AG81: =VLOOKUP($A:$A,Variables_extraites!$A:$AD,15,FALSE) -> 28 | AH81: =VLOOKUP($A:$A,Variables_extraites!$A:$AD,16,FALSE) -> 145 | AI81: =VLOOKUP($A:$A,Variables_extraites!$A:$AD,17,FALSE) -> 42528 | AJ81: =VLOOKUP($A:$A,Variables_extraites!$A:$AD,18,FALSE) -> 42765 | AK81: =VLOOKUP($A:$A,Variables_extraites!$A:$AD,19,FALSE) -> 1 | AL81: =VLOOKUP($A:$A,Variables_extraites!$A:$AD,20,FALSE) -> 42765 | AM81: =VLOOKUP($A:$A,Variables_extraites!$A:$AD,21,FALSE) -> 7 | AN81: =VLOOKUP($A:$A,Variables_extraites!$A:$AD,22,FALSE) -> 1 | AO81: =VLOOKUP($A:$A,Variables_extraites!$A:$AD,23,FALSE) -> 42660 | AP81: =VLOOKUP($A:$A,Variables_extraites!$A:$AD,24,FALSE) -> 4 | AQ81: =VLOOKUP($A:$A,Variables_extraites!$A:$AD,25,FALSE) -> 1 | AR81: =VLOOKUP($A:$A,Variables_extraites!$A:$AD,26,FALSE) -> 42660 | AS81: =VLOOKUP($A:$A,Variables_extraites!$A:$AD,27,FALSE) -> 4 | AT81: =VLOOKUP($A:$A,Variables_extraites!$A:$AD,28,FALSE) -> 7 | AU81: =VLOOKUP($A:$A,Variables_extraites!$A:$AD,29,FALSE) -> 237 | AV81: =VLOOKUP($A:$A,Variables_extraites!$A:$AD,30,FALSE) -> -27.17
A82: 146 | B82: 146 | C82: 2 | D82: HFpEF | E82: 10612 | F82: YES | H82: 85 | I82: 22.981902 | J82: 0 | K82: 4 | L82: 0 | M82: 96 | N82: 32.93 | O82: 132.29332 | P82: 10454 | Q82: 42 | R82: 44.7007 | S82: 21.886792 | T82: 58 | U82: -11.53 | V82: 77.581601 | W82: 29.361518 | X82: 26.7743 | Y82: =VLOOKUP($A:$A,Variables_extraites!$A:$AD,7,FALSE) -> 0 | Z82: =VLOOKUP($A:$A,Variables_extraites!$A:$AD,8,FALSE) -> 0 | AA82: =VLOOKUP($A:$A,Variables_extraites!$A:$AD,9,FALSE) -> 10.7 | AB82: =VLOOKUP($A:$A,Variables_extraites!$A:$AD,10,FALSE) -> 0 | AC82: =VLOOKUP($A:$A,Variables_extraites!$A:$AD,11,FALSE) -> 0 | AD82: =VLOOKUP($A:$A,Variables_extraites!$A:$AD,12,FALSE) -> 0 | AE82: =VLOOKUP($A:$A,Variables_extraites!$A:$AD,13,FALSE) -> 59.372747 | AF82: =VLOOKUP($A:$A,Variables_extraites!$A:$AD,14,FALSE) -> 1.4026602 | AG82: =VLOOKUP($A:$A,Variables_extraites!$A:$AD,15,FALSE) -> 21 | AH82: =VLOOKUP($A:$A,Variables_extraites!$A:$AD,16,FALSE) -> 146 | AI82: =VLOOKUP($A:$A,Variables_extraites!$A:$AD,17,FALSE) -> 42535 | AJ82: =VLOOKUP($A:$A,Variables_extraites!$A:$AD,18,FALSE) -> 43039 | AK82: =VLOOKUP($A:$A,Variables_extraites!$A:$AD,19,FALSE) -> 0 | AL82: =VLOOKUP($A:$A,Variables_extraites!$A:$AD,20,FALSE) -> 43039 | AM82: =VLOOKUP($A:$A,Variables_extraites!$A:$AD,21,FALSE) -> 17 | AN82: =VLOOKUP($A:$A,Variables_extraites!$A:$AD,22,FALSE) -> 0 | AO82: =VLOOKUP($A:$A,Variables_extraites!$A:$AD,23,FALSE) -> 43039 | AP82: =VLOOKUP($A:$A,Variables_extraites!$A:$AD,24,FALSE) -> 17 | AQ82: =VLOOKUP($A:$A,Variables_extraites!$A:$AD,25,FALSE) -> 0 | AR82: =VLOOKUP($A:$A,Variables_extraites!$A:$AD,26,FALSE) -> 43039 | AS82: =VLOOKUP($A:$A,Variables_extraites!$A:$AD,27,FALSE) -> 17 | AT82: =VLOOKUP($A:$A,Variables_extraites!$A:$AD,28,FALSE) -> 16.5 | AU82: =VLOOKUP($A:$A,Variables_extraites!$A:$AD,29,FALSE) -> 504 | AV82: =VLOOKUP($A:$A,Variables_extraites!$A:$AD,30,FALSE) -> -23.87
A83: 152 | B83: 152 | C83: 2 | D83: HFpEF | E83: 10441 | F83: YES | G83: YES | H83: 62 | I83: 38.21499 | J83: 1 | K83: 3 | L83: 1 | M83: 25 | N83: 32.37 | O83: 405.81174 | P83: 1126 | Q83: 15 | R83: 48.081661 | S83: 23.59375 | T83: 49 | U83: -19.473333 | V83: 58.179072 | W83: 31.833036 | X83: 67.6484 | Y83: =VLOOKUP($A:$A,Variables_extraites!$A:$AD,7,FALSE) -> 0 | Z83: =VLOOKUP($A:$A,Variables_extraites!$A:$AD,8,FALSE) -> 0 | AA83: =VLOOKUP($A:$A,Variables_extraites!$A:$AD,9,FALSE) -> 10.5 | AB83: =VLOOKUP($A:$A,Variables_extraites!$A:$AD,10,FALSE) -> 1 | AC83: =VLOOKUP($A:$A,Variables_extraites!$A:$AD,11,FALSE) -> 0 | AD83: =VLOOKUP($A:$A,Variables_extraites!$A:$AD,12,FALSE) -> 1 | AE83: =VLOOKUP($A:$A,Variables_extraites!$A:$AD,13,FALSE) -> 68.0138 | AF83: =VLOOKUP($A:$A,Variables_extraites!$A:$AD,14,FALSE) -> NA | AG83: =VLOOKUP($A:$A,Variables_extraites!$A:$AD,15,FALSE) -> 21 | AH83: =VLOOKUP($A:$A,Variables_extraites!$A:$AD,16,FALSE) -> 152 | AI83: =VLOOKUP($A:$A,Variables_extraites!$A:$AD,17,FALSE) -> 42555 | AJ83: =VLOOKUP($A:$A,Variables_extraites!$A:$AD,18,FALSE) -> 43444 | AK83: =VLOOKUP($A:$A,Variables_extraites!$A:$AD,19,FALSE) -> 0 | AL83: =VLOOKUP($A:$A,Variables_extraites!$A:$AD,20,FALSE) -> 43444 | AM83: =VLOOKUP($A:$A,Variables_extraites!$A:$AD,21,FALSE) -> 29 | AN83: =VLOOKUP($A:$A,Variables_extraites!$A:$AD,22,FALSE) -> 1 | AO83: =VLOOKUP($A:$A,Variables_extraites!$A:$AD,23,FALSE) -> 42618 | AP83: =VLOOKUP($A:$A,Variables_extraites!$A:$AD,24,FALSE) -> 2 | AQ83: =VLOOKUP($A:$A,Variables_extraites!$A:$AD,25,FALSE) -> 1 | AR83: =VLOOKUP($A:$A,Variables_extraites!$A:$AD,26,FALSE) -> 42618 | AS83: =VLOOKUP($A:$A,Variables_extraites!$A:$AD,27,FALSE) -> 2 | AT83: =VLOOKUP($A:$A,Variables_extraites!$A:$AD,28,FALSE) -> 29 | AU83: =VLOOKUP($A:$A,Variables_extraites!$A:$AD,29,FALSE) -> 889 | AV83: =VLOOKUP($A:$A,Variables_extraites!$A:$AD,30,FALSE) -> -24.62 | AW83: 9.0219793 | AX83: 7.8834986 | AY83: 5.2418402 | AZ83: 2.8196682 | BA83: 7.9505267 | BB83: 7.3060617 | BC83: 9.078898 | BD83: 8.128149 | BE83: 5.8574834 | BF83: 1.7136958 | BG83: 6.9555918 | BH83: 7.2098432 | BI83: 7.6043679 | BJ83: 4.7766304 | BK83: 5.990728 | BL83: 8.1531467 | BM83: 6.0701746 | BN83: 7.4964943 | BO83: 6.2224568 | BP83: 6.4503865 | BQ83: 8.3032328 | BR83: 2.707083 | BS83: 11.886116 | BT83: 3.5434959 | BU83: 5.5376067 | BV83: 6.9781956 | BW83: 5.5918589 | BX83: 10.985223 | BY83: 2.8757801 | BZ83: 8.8709503 | CA83: 3.9316831 | CB83: 2.1142726 | CC83: 2.8305237 | CD83: 8.3426198
A84: 153 | B84: 153 | C84: 2 | D84: HFpEF | E84: 10372 | F84: YES | H84: 83 | I84: 30.043262 | J84: 1 | K84: 1 | L84: 1 | M84: 43 | N84: 22.06 | O84: 221.64996 | P84: 642.6 | Q84: 29 | R84: 33.838214 | S84: 14.477273 | T84: 26 | U84: -17.87 | V84: 62.179302 | W84: 35.449444 | X84: 65.0632 | Y84: =VLOOKUP($A:$A,Variables_extraites!$A:$AD,7,FALSE) -> 0 | Z84: =VLOOKUP($A:$A,Variables_extraites!$A:$AD,8,FALSE) -> 0 | AA84: =VLOOKUP($A:$A,Variables_extraites!$A:$AD,9,FALSE) -> 9.6 | AB84: =VLOOKUP($A:$A,Variables_extraites!$A:$AD,10,FALSE) -> 0 | AC84: =VLOOKUP($A:$A,Variables_extraites!$A:$AD,11,FALSE) -> 0 | AD84: =VLOOKUP($A:$A,Variables_extraites!$A:$AD,12,FALSE) -> 0 | AE84: =VLOOKUP($A:$A,Variables_extraites!$A:$AD,13,FALSE) -> 69.270497 | AF84: =VLOOKUP($A:$A,Variables_extraites!$A:$AD,14,FALSE) -> 0.54074703 | AG84: =VLOOKUP($A:$A,Variables_extraites!$A:$AD,15,FALSE) -> 22.5 | AH84: =VLOOKUP($A:$A,Variables_extraites!$A:$AD,16,FALSE) -> 153 | AI84: =VLOOKUP($A:$A,Variables_extraites!$A:$AD,17,FALSE) -> 42555 | AJ84: =VLOOKUP($A:$A,Variables_extraites!$A:$AD,18,FALSE) -> 43054 | AK84: =VLOOKUP($A:$A,Variables_extraites!$A:$AD,19,FALSE) -> 0 | AL84: =VLOOKUP($A:$A,Variables_extraites!$A:$AD,20,FALSE) -> 43054 | AM84: =VLOOKUP($A:$A,Variables_extraites!$A:$AD,21,FALSE) -> 16 | AN84: =VLOOKUP($A:$A,Variables_extraites!$A:$AD,22,FALSE) -> 0 | AO84: =VLOOKUP($A:$A,Variables_extraites!$A:$AD,23,FALSE) -> 43054 | AP84: =VLOOKUP($A:$A,Variables_extraites!$A:$AD,24,FALSE) -> 16 | AQ84: =VLOOKUP($A:$A,Variables_extraites!$A:$AD,25,FALSE) -> 0 | AR84: =VLOOKUP($A:$A,Variables_extraites!$A:$AD,26,FALSE) -> 43054 | AS84: =VLOOKUP($A:$A,Variables_extraites!$A:$AD,27,FALSE) -> 16 | AT84: =VLOOKUP($A:$A,Variables_extraites!$A:$AD,28,FALSE) -> 16.41 | AU84: =VLOOKUP($A:$A,Variables_extraites!$A:$AD,29,FALSE) -> 499 | AV84: =VLOOKUP($A:$A,Variables_extraites!$A:$AD,30,FALSE) -> -27.69
A85: 155 | B85: 155 | C85: 2 | D85: HFpEF | E85: 10474 | F85: YES | G85: YES | H85: 69 | I85: 21.306818 | J85: 0 | K85: 4 | L85: 1 | M85: 124 | N85: 250 | O85: 80.620318 | P85: 286.6 | Q85: 16 | R85: 27.652532 | S85: 10.616667 | T85: 26 | U85: -18.21 | V85: 65.050931 | W85: 42.368544 | X85: 57.6281 | Y85: =VLOOKUP($A:$A,Variables_extraites!$A:$AD,7,FALSE) -> 0 | Z85: =VLOOKUP($A:$A,Variables_extraites!$A:$AD,8,FALSE) -> 0 | AA85: =VLOOKUP($A:$A,Variables_extraites!$A:$AD,9,FALSE) -> 7.2 | AB85: =VLOOKUP($A:$A,Variables_extraites!$A:$AD,10,FALSE) -> 1 | AC85: =VLOOKUP($A:$A,Variables_extraites!$A:$AD,11,FALSE) -> 0 | AD85: =VLOOKUP($A:$A,Variables_extraites!$A:$AD,12,FALSE) -> 0 | AE85: =VLOOKUP($A:$A,Variables_extraites!$A:$AD,13,FALSE) -> 66.770186 | AF85: =VLOOKUP($A:$A,Variables_extraites!$A:$AD,14,FALSE) -> 0.78641975 | AG85: =VLOOKUP($A:$A,Variables_extraites!$A:$AD,15,FALSE) -> 24 | AH85: =VLOOKUP($A:$A,Variables_extraites!$A:$AD,16,FALSE) -> 155 | AI85: =VLOOKUP($A:$A,Variables_extraites!$A:$AD,17,FALSE) -> 42556 | AJ85: =VLOOKUP($A:$A,Variables_extraites!$A:$AD,18,FALSE) -> 43218 | AK85: =VLOOKUP($A:$A,Variables_extraites!$A:$AD,19,FALSE) -> 1 | AL85: =VLOOKUP($A:$A,Variables_extraites!$A:$AD,20,FALSE) -> 43218 | AM85: =VLOOKUP($A:$A,Variables_extraites!$A:$AD,21,FALSE) -> 21 | AN85: =VLOOKUP($A:$A,Variables_extraites!$A:$AD,22,FALSE) -> 1 | AO85: =VLOOKUP($A:$A,Variables_extraites!$A:$AD,23,FALSE) -> 43132 | AP85: =VLOOKUP($A:$A,Variables_extraites!$A:$AD,24,FALSE) -> 18 | AQ85: =VLOOKUP($A:$A,Variables_extraites!$A:$AD,25,FALSE) -> 1 | AR85: =VLOOKUP($A:$A,Variables_extraites!$A:$AD,26,FALSE) -> 43132 | AS85: =VLOOKUP($A:$A,Variables_extraites!$A:$AD,27,FALSE) -> 18 | AT85: =VLOOKUP($A:$A,Variables_extraites!$A:$AD,28,FALSE) -> 21 | AU85: =VLOOKUP($A:$A,Variables_extraites!$A:$AD,29,FALSE) -> 662 | AV85: =VLOOKUP($A:$A,Variables_extraites!$A:$AD,30,FALSE) -> -31.69 | AW85: 7.6297937 | AX85: 7.7005091 | AY85: 5.9683212 | AZ85: 2.8399596 | BA85: 7.5359752 | BB85: 7.0064102 | BC85: 8.9663612 | BD85: 7.4621341 | BE85: 5.9866385 | BF85: 1.4956952 | BG85: 6.8992965 | BH85: 7.412104 | BI85: 7.8651765 | BJ85: 4.6380738 | BK85: 6.0936024 | BL85: 8.0192015 | BM85: 6.8172395 | BN85: 7.160174 | BO85: 5.3291236 | BP85: 6.2541783 | BQ85: 8.2824861 | BR85: 5.308157 | BS85: 10.601214 | BT85: 2.5849625 | BU85: 7.3924892 | BV85: 5.8472453 | BW85: 4.3212066 | BX85: 10.57144 | BY85: 2.707083 | BZ85: 8.0958717 | CA85: 3.8459918 | CB85: 2.4755681 | CC85: 2.0843322 | CD85: 8.0162512
A86: 156 | B86: 156 | C86: 2 | D86: HFpEF | E86: 10308 | F86: YES | H86: 51 | I86: 32.029086 | J86: 1 | K86: 3 | L86: 1 | M86: 85 | N86: 25.57 | O86: 112.4974 | P86: 294 | Q86: 17 | R86: 28.386728 | S86: 21.083333 | T86: x | U86: -12.42 | V86: 80.248866 | W86: 42.706575 | X86: 19.8981 | Y86: =VLOOKUP($A:$A,Variables_extraites!$A:$AD,7,FALSE) -> 0 | Z86: =VLOOKUP($A:$A,Variables_extraites!$A:$AD,8,FALSE) -> 0 | AA86: =VLOOKUP($A:$A,Variables_extraites!$A:$AD,9,FALSE) -> 12.5 | AB86: =VLOOKUP($A:$A,Variables_extraites!$A:$AD,10,FALSE) -> 0 | AC86: =VLOOKUP($A:$A,Variables_extraites!$A:$AD,11,FALSE) -> 0 | AD86: =VLOOKUP($A:$A,Variables_extraites!$A:$AD,12,FALSE) -> 0 | AE86: =VLOOKUP($A:$A,Variables_extraites!$A:$AD,13,FALSE) -> 55.832321 | AF86: =VLOOKUP($A:$A,Variables_extraites!$A:$AD,14,FALSE) -> 1.4904271 | AG86: =VLOOKUP($A:$A,Variables_extraites!$A:$AD,15,FALSE) -> 20 | AH86: =VLOOKUP($A:$A,Variables_extraites!$A:$AD,16,FALSE) -> NA | AI86: =VLOOKUP($A:$A,Variables_extraites!$A:$AD,17,FALSE) -> 42562 | AJ86: =VLOOKUP($A:$A,Variables_extraites!$A:$AD,18,FALSE) -> NA | AK86: =VLOOKUP($A:$A,Variables_extraites!$A:$AD,19,FALSE) -> NA | AL86: =VLOOKUP($A:$A,Variables_extraites!$A:$AD,20,FALSE) -> NA | AM86: =VLOOKUP($A:$A,Variables_extraites!$A:$AD,21,FALSE) -> NA | AN86: =VLOOKUP($A:$A,Variables_extraites!$A:$AD,22,FALSE) -> NA | AO86: =VLOOKUP($A:$A,Variables_extraites!$A:$AD,23,FALSE) -> NA | AP86: =VLOOKUP($A:$A,Variables_extraites!$A:$AD,24,FALSE) -> NA | AQ86: =VLOOKUP($A:$A,Variables_extraites!$A:$AD,25,FALSE) -> NA | AR86: =VLOOKUP($A:$A,Variables_extraites!$A:$AD,26,FALSE) -> NA | AS86: =VLOOKUP($A:$A,Variables_extraites!$A:$AD,27,FALSE) -> NA | AT86: =VLOOKUP($A:$A,Variables_extraites!$A:$AD,28,FALSE) -> NA | AU86: =VLOOKUP($A:$A,Variables_extraites!$A:$AD,29,FALSE) -> NA | AV86: =VLOOKUP($A:$A,Variables_extraites!$A:$AD,30,FALSE) -> -19.87
A87: 159 | B87: 159 | C87: 2 | D87: HFpEF | E87: 10634 | F87: YES | G87: YES | H87: 83 | I87: 25.249337 | J87: 0 | K87: 2 | L87: 1 | M87: 55 | N87: 65.92 | O87: 591.79743 | P87: 1474 | Q87: 37 | R87: 42.240775 | S87: 18.232558 | T87: 35.366667 | U87: -15.096667 | V87: 79.870577 | W87: 31.031681 | X87: 43.9734 | Y87: =VLOOKUP($A:$A,Variables_extraites!$A:$AD,7,FALSE) -> 0 | Z87: =VLOOKUP($A:$A,Variables_extraites!$A:$AD,8,FALSE) -> 0 | AA87: =VLOOKUP($A:$A,Variables_extraites!$A:$AD,9,FALSE) -> 14 | AB87: =VLOOKUP($A:$A,Variables_extraites!$A:$AD,10,FALSE) -> 1 | AC87: =VLOOKUP($A:$A,Variables_extraites!$A:$AD,11,FALSE) -> 0 | AD87: =VLOOKUP($A:$A,Variables_extraites!$A:$AD,12,FALSE) -> 1 | AE87: =VLOOKUP($A:$A,Variables_extraites!$A:$AD,13,FALSE) -> 61.502146 | AF87: =VLOOKUP($A:$A,Variables_extraites!$A:$AD,14,FALSE) -> NA | AG87: =VLOOKUP($A:$A,Variables_extraites!$A:$AD,15,FALSE) -> 16.5 | AH87: =VLOOKUP($A:$A,Variables_extraites!$A:$AD,16,FALSE) -> 159 | AI87: =VLOOKUP($A:$A,Variables_extraites!$A:$AD,17,FALSE) -> 42566 | AJ87: =VLOOKUP($A:$A,Variables_extraites!$A:$AD,18,FALSE) -> 43046 | AK87: =VLOOKUP($A:$A,Variables_extraites!$A:$AD,19,FALSE) -> 1 | AL87: =VLOOKUP($A:$A,Variables_extraites!$A:$AD,20,FALSE) -> 43046 | AM87: =VLOOKUP($A:$A,Variables_extraites!$A:$AD,21,FALSE) -> 15 | AN87: =VLOOKUP($A:$A,Variables_extraites!$A:$AD,22,FALSE) -> 0 | AO87: =VLOOKUP($A:$A,Variables_extraites!$A:$AD,23,FALSE) -> 43046 | AP87: =VLOOKUP($A:$A,Variables_extraites!$A:$AD,24,FALSE) -> 15 | AQ87: =VLOOKUP($A:$A,Variables_extraites!$A:$AD,25,FALSE) -> 1 | AR87: =VLOOKUP($A:$A,Variables_extraites!$A:$AD,26,FALSE) -> 43046 | AS87: =VLOOKUP($A:$A,Variables_extraites!$A:$AD,27,FALSE) -> 15 | AT87: =VLOOKUP($A:$A,Variables_extraites!$A:$AD,28,FALSE) -> 15 | AU87: =VLOOKUP($A:$A,Variables_extraites!$A:$AD,29,FALSE) -> 480 | AV87: =VLOOKUP($A:$A,Variables_extraites!$A:$AD,30,FALSE) -> -23.996667 | AW87: 8.3814564 | AX87: 6.6954371 | AY87: 5.210233 | AZ87: 2.5185351 | BA87: 6.8498742 | BB87: 6.1426177 | BC87: 9.1219997 | BD87: 7.6448657 | BE87: 6.2982917 | BF87: 1.275007 | BG87: 6.6940444 | BH87: 7.1545144 | BI87: 7.3781648 | BJ87: 4.6507646 | BK87: 5.639811 | BL87: 7.76739 | BM87: 6.7452373 | BN87: 7.0064102 | BO87: 6.1193562 | BP87: 5.9478999 | BQ87: 8.2623768 | BR87: -1.9378783 | BS87: 10.527633 | BT87: 1.5459684 | BU87: 6.5501311 | BV87: 6.2883586 | BW87: 4.6369146 | BX87: 11.840211 | BY87: 2.8237494 | BZ87: 8.8748584 | CA87: 4.342697 | CB87: 2.965353 | CC87: 8.4880094 | CD87: 8.981665
